Workbook
Name Balancetecontbilporperodo: 'PREVISTO 2026'!#REF!
Name Balancetecontbilporperodo: 'PREVISTO 2026 REVISADO'!#REF!
Name Balancetecontbilporperodo: 'PREVISTO 2026 REVISADO (2)'!#REF!
Name Balancetecontbilporperodo: 'REALIZADO 2025'!#REF!
Name JR_PAGE_ANCHOR_0_1: 'PREVISTO 2026'!#REF!
Name JR_PAGE_ANCHOR_0_1: 'PREVISTO 2026 REVISADO'!#REF!
Name JR_PAGE_ANCHOR_0_1: 'PREVISTO 2026 REVISADO (2)'!#REF!
Name JR_PAGE_ANCHOR_0_1: 'REALIZADO 2025'!#REF!

Sheet PREVISTO 2026 REVISADO
C1: Horiontal Praia Brava
C2: Previsão Orçamentária 2026
C3: Categorias | F3: Dezembro | G3: Janeiro | H3: Fevereiro | I3: Março | J3: Abril | K3: Maio | L3: Junho | M3: Julho | N3: Agosto | O3: Setembro | P3: Outubro | Q3: Novembro | R3: Total | S3: Média
C4: 2 Despesas | F4: =F5+F22+F38+F78+F86+#REF! -> #REF! | G4: =G5+G22+G38+G78+G86+#REF! -> #REF! | H4: =H5+H22+H38+H78+H86+#REF! -> #REF! | I4: =I5+I22+I38+I78+I86+#REF! -> #REF! | J4: =J5+J22+J38+J78+J86+#REF! -> #REF! | K4: =K5+K22+K38+K78+K86+#REF! -> #REF! | L4: =L5+L22+L38+L78+L86+#REF! -> #REF! | M4: =M5+M22+M38+M78+M86+#REF! -> #REF! | ... Q4: =Q5+Q22+Q38+Q78+Q86+#REF! -> #REF! | T4: REAJUSTE | U4: 1.045 | V4: 0.045
C5: 2.1 Administrativas | F5: =SUM(F6:F21) -> 9137.3607 | G5: =SUM(G6:G21) -> 8418.0037 | H5: =SUM(H6:H21) -> 83898.212 | I5: =SUM(I6:I21) -> 11787.819 | J5: =SUM(J6:J21) -> 9820.2203 | K5: =SUM(K6:K21) -> 11732.215 | L5: =SUM(L6:L21) -> 11683.814 | M5: =SUM(M6:M21) -> 10756.028 | ... R5: =SUM(R6:R21) -> 203286.84 | S5: =R5/12 -> 16940.57
C6: 2.1.1 Despesas Bancárias | F6: 34 | G6: 34 | H6: ='REALIZADO 2025'!F28*'PREVISTO 2026 REVISADO'!$U$4 -> 82.54455 | I6: ='REALIZADO 2025'!G28*'PREVISTO 2026 REVISADO'!$U$4 -> 62.06255 | J6: ='REALIZADO 2025'!H28*'PREVISTO 2026 REVISADO'!$U$4 -> 101.5949 | K6: ='REALIZADO 2025'!I28*'PREVISTO 2026 REVISADO'!$U$4 -> 39.6055 | L6: 35 | M6: ='REALIZADO 2025'!K28*'PREVISTO 2026 REVISADO'!$U$4 -> 33.3355 | N6: ='REALIZADO 2025'!L28*'PREVISTO 2026 REVISADO'!$U$4 -> 33.3355 | O6: ='REALIZADO 2025'!M28*'PREVISTO 2026 REVISADO'!$U$4 -> 34.3805 | P6: ='REALIZADO 2025'!N28*'PREVISTO 2026 REVISADO'!$U$4 -> 31.2455 | Q6: ='REALIZADO 2025'!O28*'PREVISTO 2026 REVISADO'!$U$4 -> 31.5172 | R6: =SUM(F6:Q6) -> 552.6217 | S6: =R6/12 -> 46.051808
C7: 2.1.11 Reuniões-treinamentos | F7: ='REALIZADO 2025'!D29*'PREVISTO 2026 REVISADO'!$U$4 -> 0 | G7: ='REALIZADO 2025'!E29*'PREVISTO 2026 REVISADO'!$U$4 -> 0 | H7: ='REALIZADO 2025'!F29*'PREVISTO 2026 REVISADO'!$U$4 -> 196.34505 | I7: ='REALIZADO 2025'!G29*'PREVISTO 2026 REVISADO'!$U$4 -> 0 | J7: ='REALIZADO 2025'!H29*'PREVISTO 2026 REVISADO'!$U$4 -> 0 | K7: ='REALIZADO 2025'!I29*'PREVISTO 2026 REVISADO'!$U$4 -> 0 | L7: ='REALIZADO 2025'!J29*'PREVISTO 2026 REVISADO'!$U$4 -> 415.91 | M7: ='REALIZADO 2025'!K29*'PREVISTO 2026 REVISADO'!$U$4 -> 176.5423 | ... Q7: ='REALIZADO 2025'!O29*'PREVISTO 2026 REVISADO'!$U$4 -> 0 | R7: =SUM(F7:Q7) -> 1213.4853 | S7: =R7/12 -> 101.12378
C8: 2.1.12 Certificado Digital | F8: ='REALIZADO 2025'!D30*'PREVISTO 2026 REVISADO'!$U$4 -> 0 | G8: ='REALIZADO 2025'!E30*'PREVISTO 2026 REVISADO'!$U$4 -> 0 | H8: ='REALIZADO 2025'!F30*'PREVISTO 2026 REVISADO'!$U$4 -> 0 | I8: ='REALIZADO 2025'!G30*'PREVISTO 2026 REVISADO'!$U$4 -> 0 | J8: ='REALIZADO 2025'!H30*'PREVISTO 2026 REVISADO'!$U$4 -> 187.65065 | K8: ='REALIZADO 2025'!I30*'PREVISTO 2026 REVISADO'!$U$4 -> 0 | L8: ='REALIZADO 2025'!J30*'PREVISTO 2026 REVISADO'!$U$4 -> 0 | M8: ='REALIZADO 2025'!K30*'PREVISTO 2026 REVISADO'!$U$4 -> 0 | ... Q8: ='REALIZADO 2025'!O30*'PREVISTO 2026 REVISADO'!$U$4 -> 0 | R8: =SUM(F8:Q8) -> 396.65065 | S8: =R8/12 -> 33.054221
C9: 2.1.14 Outros-não Previstos | F9: ='REALIZADO 2025'!D31*'PREVISTO 2026 REVISADO'!$U$4 -> 0 | G9: ='REALIZADO 2025'!E31*'PREVISTO 2026 REVISADO'!$U$4 -> 0 | H9: ='REALIZADO 2025'!F31*'PREVISTO 2026 REVISADO'!$U$4 -> 0 | I9: ='REALIZADO 2025'!G31*'PREVISTO 2026 REVISADO'!$U$4 -> 2612.5 | J9: ='REALIZADO 2025'!H31*'PREVISTO 2026 REVISADO'!$U$4 -> 0 | K9: ='REALIZADO 2025'!I31*'PREVISTO 2026 REVISADO'!$U$4 -> 0 | L9: ='REALIZADO 2025'!J31*'PREVISTO 2026 REVISADO'!$U$4 -> 0 | M9: ='REALIZADO 2025'!K31*'PREVISTO 2026 REVISADO'!$U$4 -> 0 | ... Q9: ='REALIZADO 2025'!O31*'PREVISTO 2026 REVISADO'!$U$4 -> 0 | R9: =SUM(F9:Q9) -> 2612.5 | S9: =R9/12 -> 217.70833
C10: 2.1.19 Alvará De Funcionamento | F10: ='REALIZADO 2025'!D34*'PREVISTO 2026 REVISADO'!$U$4 -> 0 | G10: ='REALIZADO 2025'!E34*'PREVISTO 2026 REVISADO'!$U$4 -> 0 | H10: ='REALIZADO 2025'!F34*'PREVISTO 2026 REVISADO'!$U$4 -> 0 | I10: ='REALIZADO 2025'!G34*'PREVISTO 2026 REVISADO'!$U$4 -> 0 | J10: ='REALIZADO 2025'!H34*'PREVISTO 2026 REVISADO'!$U$4 -> 0 | K10: ='REALIZADO 2025'!I34*'PREVISTO 2026 REVISADO'!$U$4 -> 621.4824 | L10: ='REALIZADO 2025'!J34*'PREVISTO 2026 REVISADO'!$U$4 -> 0 | M10: ='REALIZADO 2025'!K34*'PREVISTO 2026 REVISADO'!$U$4 -> 0 | ... Q10: ='REALIZADO 2025'!O34*'PREVISTO 2026 REVISADO'!$U$4 -> 0 | R10: =SUM(F10:Q10) -> 621.4824 | S10: =R10/12 -> 51.7902
C11: 2.1.2 Material De Expediente-correio | F11: ='REALIZADO 2025'!D35*'PREVISTO 2026 REVISADO'!$U$4 -> 372.17675 | G11: ='REALIZADO 2025'!E35*'PREVISTO 2026 REVISADO'!$U$4 -> 365.75 | H11: ='REALIZADO 2025'!F35*'PREVISTO 2026 REVISADO'!$U$4 -> 937.0515 | I11: ='REALIZADO 2025'!G35*'PREVISTO 2026 REVISADO'!$U$4 -> 510.43025 | J11: ='REALIZADO 2025'!H35*'PREVISTO 2026 REVISADO'!$U$4 -> 320.76275 | K11: ='REALIZADO 2025'!I35*'PREVISTO 2026 REVISADO'!$U$4 -> 403.37 | L11: ='REALIZADO 2025'!J35*'PREVISTO 2026 REVISADO'!$U$4 -> 1135.706 | M11: ='REALIZADO 2025'!K35*'PREVISTO 2026 REVISADO'!$U$4 -> 406.45275 | ... Q11: ='REALIZADO 2025'!O35*'PREVISTO 2026 REVISADO'!$U$4 -> 328.757 | R11: =SUM(F11:Q11) -> 7239.9167 | S11: =R11/12 -> 603.3264
C12: 2.1.21 Sistema De Reservas On-line | F12: ='REALIZADO 2025'!D36*'PREVISTO 2026 REVISADO'!$U$4 -> 522.5 | G12: ='REALIZADO 2025'!E36*'PREVISTO 2026 REVISADO'!$U$4 -> 0 | H12: ='REALIZADO 2025'!F36*'PREVISTO 2026 REVISADO'!$U$4 -> 522.5 | I12: ='REALIZADO 2025'!G36*'PREVISTO 2026 REVISADO'!$U$4 -> 522.5 | J12: ='REALIZADO 2025'!H36*'PREVISTO 2026 REVISADO'!$U$4 -> 522.5 | K12: ='REALIZADO 2025'!I36*'PREVISTO 2026 REVISADO'!$U$4 -> 522.5 | L12: ='REALIZADO 2025'!J36*'PREVISTO 2026 REVISADO'!$U$4 -> 0 | M12: ='REALIZADO 2025'!K36*'PREVISTO 2026 REVISADO'!$U$4 -> 522.5 | ... Q12: ='REALIZADO 2025'!O36*'PREVISTO 2026 REVISADO'!$U$4 -> 0 | R12: =SUM(F12:Q12) -> 4702.5 | S12: =R12/12 -> 391.875
C13: 2.1.22 Material Expediente- Impressões/Digitalizações/Encadernação/Envelopes | F13: ='REALIZADO 2025'!D37*'PREVISTO 2026 REVISADO'!$U$4 -> 0 | G13: ='REALIZADO 2025'!E37*'PREVISTO 2026 REVISADO'!$U$4 -> 0 | H13: ='REALIZADO 2025'!F37*'PREVISTO 2026 REVISADO'!$U$4 -> 0 | I13: ='REALIZADO 2025'!G37*'PREVISTO 2026 REVISADO'!$U$4 -> 0 | J13: ='REALIZADO 2025'!H37*'PREVISTO 2026 REVISADO'!$U$4 -> 0 | K13: ='REALIZADO 2025'!I37*'PREVISTO 2026 REVISADO'!$U$4 -> 0 | L13: ='REALIZADO 2025'!J37*'PREVISTO 2026 REVISADO'!$U$4 -> 0 | M13: ='REALIZADO 2025'!K37*'PREVISTO 2026 REVISADO'!$U$4 -> 0 | ... Q13: ='REALIZADO 2025'!O37*'PREVISTO 2026 REVISADO'!$U$4 -> 1418.4307 | R13: =SUM(F13:Q13) -> 1418.4307 | S13: =R13/12 -> 118.20256
C14: 2.1.3 Honorário Síndico | F14: =5043.17*$U$4 -> 5270.1127 | G14: =5043.17*$U$4 -> 5270.1127 | H14: =5043.17*$U$4 -> 5270.1127 | I14: =5043.17*$U$4 -> 5270.1127 | J14: =5043.17*$U$4 -> 5270.1127 | K14: =5043.17*$U$4 -> 5270.1127 | L14: =5043.17*$U$4 -> 5270.1127 | M14: =5043.17*$U$4 -> 5270.1127 | ... Q14: =5043.17*$U$4 -> 5270.1127 | R14: =SUM(F14:Q14) -> 63241.352 | S14: =R14/12 -> 5270.1127
C15: 2.1.4 Inss-ir-síndico | F15: =2570.4*$U$4 -> 2686.068 | G15: =2570.4*$U$4 -> 2686.068 | H15: =2570.4*$U$4 -> 2686.068 | I15: =2570.4*$U$4 -> 2686.068 | J15: =2570.4*$U$4 -> 2686.068 | K15: =2570.4*$U$4 -> 2686.068 | L15: =2570.4*$U$4 -> 2686.068 | M15: =2570.4*$U$4 -> 2686.068 | ... Q15: =2570.4*$U$4 -> 2686.068 | R15: =SUM(F15:Q15) -> 32232.816 | S15: =R15/12 -> 2686.068
C16: 2.1.5 Iptu | F16: ='REALIZADO 2025'!D40*'PREVISTO 2026 REVISADO'!$U$4 -> 0 | G16: ='REALIZADO 2025'!E40*'PREVISTO 2026 REVISADO'!$U$4 -> 0 | H16: ='REALIZADO 2025'!F40*'PREVISTO 2026 REVISADO'!$U$4 -> 68382.052 | I16: ='REALIZADO 2025'!G40*'PREVISTO 2026 REVISADO'!$U$4 -> 0 | J16: ='REALIZADO 2025'!H40*'PREVISTO 2026 REVISADO'!$U$4 -> 0 | K16: ='REALIZADO 2025'!I40*'PREVISTO 2026 REVISADO'!$U$4 -> 0 | L16: ='REALIZADO 2025'!J40*'PREVISTO 2026 REVISADO'!$U$4 -> 0 | M16: ='REALIZADO 2025'!K40*'PREVISTO 2026 REVISADO'!$U$4 -> 0 | ... Q16: ='REALIZADO 2025'!O40*'PREVISTO 2026 REVISADO'!$U$4 -> 0 | R16: =SUM(F16:Q16) -> 68382.052 | S16: =R16/12 -> 5698.5043
C17: 2.1.6 Taxa De Lixo | F17: ='REALIZADO 2025'!D41*'PREVISTO 2026 REVISADO'!$U$4 -> 0 | G17: ='REALIZADO 2025'!E41*'PREVISTO 2026 REVISADO'!$U$4 -> 0 | H17: ='REALIZADO 2025'!F41*'PREVISTO 2026 REVISADO'!$U$4 -> 5540.266 | I17: ='REALIZADO 2025'!G41*'PREVISTO 2026 REVISADO'!$U$4 -> 0 | J17: ='REALIZADO 2025'!H41*'PREVISTO 2026 REVISADO'!$U$4 -> 0 | K17: ='REALIZADO 2025'!I41*'PREVISTO 2026 REVISADO'!$U$4 -> 0 | L17: ='REALIZADO 2025'!J41*'PREVISTO 2026 REVISADO'!$U$4 -> 0 | M17: ='REALIZADO 2025'!K41*'PREVISTO 2026 REVISADO'!$U$4 -> 0 | ... Q17: ='REALIZADO 2025'!O41*'PREVISTO 2026 REVISADO'!$U$4 -> 0 | R17: =SUM(F17:Q17) -> 5540.266 | S17: =R17/12 -> 461.68884
C18: 2.1.60 Outros | F18: ='REALIZADO 2025'!D42*'PREVISTO 2026 REVISADO'!$U$4 -> 0 | G18: ='REALIZADO 2025'!E42*'PREVISTO 2026 REVISADO'!$U$4 -> 0 | H18: ='REALIZADO 2025'!F42*'PREVISTO 2026 REVISADO'!$U$4 -> 0 | I18: ='REALIZADO 2025'!G42*'PREVISTO 2026 REVISADO'!$U$4 -> 0 | J18: ='REALIZADO 2025'!H42*'PREVISTO 2026 REVISADO'!$U$4 -> 731.53135 | K18: ='REALIZADO 2025'!I42*'PREVISTO 2026 REVISADO'!$U$4 -> 0 | L18: ='REALIZADO 2025'!J42*'PREVISTO 2026 REVISADO'!$U$4 -> 0 | M18: ='REALIZADO 2025'!K42*'PREVISTO 2026 REVISADO'!$U$4 -> 0 | ... Q18: ='REALIZADO 2025'!O42*'PREVISTO 2026 REVISADO'!$U$4 -> 0 | R18: =SUM(F18:Q18) -> 731.53135 | S18: =R18/12 -> 60.960946
C19: 2.1.7 Seguro | F19: ='REALIZADO 2025'!D43*'PREVISTO 2026 REVISADO'!$U$4 -> 0 | G19: ='REALIZADO 2025'!E43*'PREVISTO 2026 REVISADO'!$U$4 -> 0 | H19: ='REALIZADO 2025'!F43*'PREVISTO 2026 REVISADO'!$U$4 -> 0 | I19: ='REALIZADO 2025'!G43*'PREVISTO 2026 REVISADO'!$U$4 -> 0 | J19: ='REALIZADO 2025'!H43*'PREVISTO 2026 REVISADO'!$U$4 -> 0 | K19: ='REALIZADO 2025'!I43*'PREVISTO 2026 REVISADO'!$U$4 -> 1386.6418 | L19: ='REALIZADO 2025'!J43*'PREVISTO 2026 REVISADO'!$U$4 -> 1386.6418 | M19: ='REALIZADO 2025'!K43*'PREVISTO 2026 REVISADO'!$U$4 -> 1386.6418 | ... Q19: ='REALIZADO 2025'!O43*'PREVISTO 2026 REVISADO'!$U$4 -> 0 | R19: =SUM(F19:Q19) -> 8319.9556 | S19: =R19/12 -> 693.32963
C20: 2.1.8 Cartório | F20: ='REALIZADO 2025'!D44*'PREVISTO 2026 REVISADO'!$U$4 -> 252.50335 | G20: ='REALIZADO 2025'!E44*'PREVISTO 2026 REVISADO'!$U$4 -> 62.073 | H20: ='REALIZADO 2025'!F44*'PREVISTO 2026 REVISADO'!$U$4 -> 281.2722 | I20: ='REALIZADO 2025'!G44*'PREVISTO 2026 REVISADO'!$U$4 -> 124.146 | J20: ='REALIZADO 2025'!H44*'PREVISTO 2026 REVISADO'!$U$4 -> 0 | K20: ='REALIZADO 2025'!I44*'PREVISTO 2026 REVISADO'!$U$4 -> 802.4346 | L20: ='REALIZADO 2025'!J44*'PREVISTO 2026 REVISADO'!$U$4 -> 754.37505 | M20: ='REALIZADO 2025'!K44*'PREVISTO 2026 REVISADO'!$U$4 -> 274.3752 | ... Q20: ='REALIZADO 2025'!O44*'PREVISTO 2026 REVISADO'!$U$4 -> 0 | R20: =SUM(F20:Q20) -> 2818.6576 | S20: =R20/12 -> 234.88813
C21: 2.1.9 Documentação Veículo / Multas e Infrações | F21: ='REALIZADO 2025'!D45*'PREVISTO 2026 REVISADO'!$U$4 -> 0 | G21: ='REALIZADO 2025'!E45*'PREVISTO 2026 REVISADO'!$U$4 -> 0 | H21: ='REALIZADO 2025'!F45*'PREVISTO 2026 REVISADO'!$U$4 -> 0 | I21: ='REALIZADO 2025'!G45*'PREVISTO 2026 REVISADO'!$U$4 -> 0 | J21: ='REALIZADO 2025'!H45*'PREVISTO 2026 REVISADO'!$U$4 -> 0 | K21: ='REALIZADO 2025'!I45*'PREVISTO 2026 REVISADO'!$U$4 -> 0 | L21: ='REALIZADO 2025'!J45*'PREVISTO 2026 REVISADO'!$U$4 -> 0 | M21: ='REALIZADO 2025'!K45*'PREVISTO 2026 REVISADO'!$U$4 -> 0 | ... Q21: ='REALIZADO 2025'!O45*'PREVISTO 2026 REVISADO'!$U$4 -> 0 | R21: =SUM(F21:Q21) -> 3262.6258 | S21: =R21/12 -> 271.88549
C22: 2.2 Colaboradores | F22: =SUM(F23:F37) -> 154479.97 | G22: =SUM(G23:G37) -> 112015.2 | H22: =SUM(H23:H37) -> 94533.512 | I22: =SUM(I23:I37) -> 129753.64 | J22: =SUM(J23:J37) -> 99742.99 | K22: =SUM(K23:K37) -> 125942.13 | L22: =SUM(L23:L37) -> 124648.07 | M22: =SUM(M23:M37) -> 100689.33 | ... R22: =SUM(R23:R37) -> 1483394.4 | S22: =R22/12 -> 123616.2 | T22: REAJUSTE | U22: 1.08 | V22: 0.08
C23: 2.2.1 Salários Líquidos | F23: ='REALIZADO 2025'!D47*'PREVISTO 2026 REVISADO'!$U$22 -> 52560.36 | G23: ='REALIZADO 2025'!E47*'PREVISTO 2026 REVISADO'!$U$22 -> 50335.56 | H23: ='REALIZADO 2025'!F47*'PREVISTO 2026 REVISADO'!$U$22 -> 47781.36 | I23: ='REALIZADO 2025'!G47*'PREVISTO 2026 REVISADO'!$U$22 -> 51606.72 | J23: ='REALIZADO 2025'!H47*'PREVISTO 2026 REVISADO'!$U$22 -> 47565.36 | K23: ='REALIZADO 2025'!I47*'PREVISTO 2026 REVISADO'!$U$22 -> 51570.432 | L23: ='REALIZADO 2025'!J47*'PREVISTO 2026 REVISADO'!$U$22 -> 52953.48 | M23: ='REALIZADO 2025'!K47*'PREVISTO 2026 REVISADO'!$U$22 -> 47341.8 | ... Q23: ='REALIZADO 2025'!O47*'PREVISTO 2026 REVISADO'!$U$22 -> 57690.36 | R23: =SUM(F23:Q23) -> 616611.1 | S23: =R23/12 -> 51384.258
C24: 2.2.10 Benefícios Saúde-cesta Básica-copa | F24: ='REALIZADO 2025'!D48*'PREVISTO 2026 REVISADO'!$U$22 -> 23252.497 | G24: ='REALIZADO 2025'!E48*'PREVISTO 2026 REVISADO'!$U$22 -> 15102.04 | H24: ='REALIZADO 2025'!F48*'PREVISTO 2026 REVISADO'!$U$22 -> 6936.1164 | I24: ='REALIZADO 2025'!G48*'PREVISTO 2026 REVISADO'!$U$22 -> 23643.932 | J24: ='REALIZADO 2025'!H48*'PREVISTO 2026 REVISADO'!$U$22 -> 16979.242 | K24: ='REALIZADO 2025'!I48*'PREVISTO 2026 REVISADO'!$U$22 -> 21597.602 | L24: ='REALIZADO 2025'!J48*'PREVISTO 2026 REVISADO'!$U$22 -> 16055.701 | M24: ='REALIZADO 2025'!K48*'PREVISTO 2026 REVISADO'!$U$22 -> 17160.498 | ... Q24: ='REALIZADO 2025'!O48*'PREVISTO 2026 REVISADO'!$U$22 -> 17840.444 | R24: =SUM(F24:Q24) -> 210724.09 | S24: =R24/12 -> 17560.341
C25: 2.2.11 Uniforme-epi | F25: ='REALIZADO 2025'!D49*'PREVISTO 2026 REVISADO'!$U$22 -> 77.652 | G25: ='REALIZADO 2025'!E49*'PREVISTO 2026 REVISADO'!$U$22 -> 847.4112 | H25: ='REALIZADO 2025'!F49*'PREVISTO 2026 REVISADO'!$U$22 -> 342.9108 | I25: ='REALIZADO 2025'!G49*'PREVISTO 2026 REVISADO'!$U$22 -> 528.444 | J25: ='REALIZADO 2025'!H49*'PREVISTO 2026 REVISADO'!$U$22 -> 1798.74 | K25: ='REALIZADO 2025'!I49*'PREVISTO 2026 REVISADO'!$U$22 -> 1893.78 | L25: ='REALIZADO 2025'!J49*'PREVISTO 2026 REVISADO'!$U$22 -> 539.784 | M25: ='REALIZADO 2025'!K49*'PREVISTO 2026 REVISADO'!$U$22 -> 0 | ... Q25: ='REALIZADO 2025'!O49*'PREVISTO 2026 REVISADO'!$U$22 -> 1808.298 | R25: 12000 | S25: =R25/12 -> 1000
C26: 2.2.12 Laudos Médicos-exames | F26: ='REALIZADO 2025'!D50*'PREVISTO 2026 REVISADO'!$U$22 -> 266.1444 | G26: ='REALIZADO 2025'!E50*'PREVISTO 2026 REVISADO'!$U$22 -> 263.25 | H26: ='REALIZADO 2025'!F50*'PREVISTO 2026 REVISADO'!$U$22 -> 291.5676 | I26: ='REALIZADO 2025'!G50*'PREVISTO 2026 REVISADO'!$U$22 -> 278.7804 | J26: ='REALIZADO 2025'!H50*'PREVISTO 2026 REVISADO'!$U$22 -> 235.6236 | K26: ='REALIZADO 2025'!I50*'PREVISTO 2026 REVISADO'!$U$22 -> 247.7088 | L26: ='REALIZADO 2025'!J50*'PREVISTO 2026 REVISADO'!$U$22 -> 248.4 | M26: ='REALIZADO 2025'!K50*'PREVISTO 2026 REVISADO'!$U$22 -> 248.4 | ... Q26: ='REALIZADO 2025'!O50*'PREVISTO 2026 REVISADO'!$U$22 -> 308.6208 | R26: =SUM(F26:Q26) -> 3452.004 | S26: =R26/12 -> 287.667
C27: 2.2.13 Cursos-treinamentos | F27: ='REALIZADO 2025'!D51*'PREVISTO 2026 REVISADO'!$U$22 -> 0 | G27: ='REALIZADO 2025'!E51*'PREVISTO 2026 REVISADO'!$U$22 -> 0 | H27: ='REALIZADO 2025'!F51*'PREVISTO 2026 REVISADO'!$U$22 -> 0 | I27: ='REALIZADO 2025'!G51*'PREVISTO 2026 REVISADO'!$U$22 -> 0 | J27: ='REALIZADO 2025'!H51*'PREVISTO 2026 REVISADO'!$U$22 -> 0 | K27: ='REALIZADO 2025'!I51*'PREVISTO 2026 REVISADO'!$U$22 -> 0 | L27: ='REALIZADO 2025'!J51*'PREVISTO 2026 REVISADO'!$U$22 -> 0 | M27: ='REALIZADO 2025'!K51*'PREVISTO 2026 REVISADO'!$U$22 -> 0 | ... Q27: ='REALIZADO 2025'!O51*'PREVISTO 2026 REVISADO'!$U$22 -> 51.0624 | R27: =SUM(F27:Q27) -> 2204.2584 | S27: =R27/12 -> 183.6882
C28: 2.2.14 Brindes-confraternizações | F28: ='REALIZADO 2025'!D52*'PREVISTO 2026 REVISADO'!$U$22 -> 3033.612 | G28: ='REALIZADO 2025'!E52*'PREVISTO 2026 REVISADO'!$U$22 -> 3616.272 | H28: ='REALIZADO 2025'!F52*'PREVISTO 2026 REVISADO'!$U$22 -> 1596.888 | I28: ='REALIZADO 2025'!G52*'PREVISTO 2026 REVISADO'!$U$22 -> 788.4 | J28: ='REALIZADO 2025'!H52*'PREVISTO 2026 REVISADO'!$U$22 -> 0 | K28: ='REALIZADO 2025'!I52*'PREVISTO 2026 REVISADO'!$U$22 -> 1690.0596 | L28: ='REALIZADO 2025'!J52*'PREVISTO 2026 REVISADO'!$U$22 -> 0 | M28: ='REALIZADO 2025'!K52*'PREVISTO 2026 REVISADO'!$U$22 -> 0 | ... Q28: ='REALIZADO 2025'!O52*'PREVISTO 2026 REVISADO'!$U$22 -> 0 | R28: =SUM(F28:Q28) -> 11296.422 | S28: =R28/12 -> 941.3685
C29: 2.2.15 Seguro De Vida | F29: ='REALIZADO 2025'!D53*'PREVISTO 2026 REVISADO'!$U$22 -> 319.5936 | G29: ='REALIZADO 2025'!E53*'PREVISTO 2026 REVISADO'!$U$22 -> 319.5936 | H29: ='REALIZADO 2025'!F53*'PREVISTO 2026 REVISADO'!$U$22 -> 319.5936 | I29: ='REALIZADO 2025'!G53*'PREVISTO 2026 REVISADO'!$U$22 -> 319.5936 | J29: ='REALIZADO 2025'!H53*'PREVISTO 2026 REVISADO'!$U$22 -> 332.802 | K29: ='REALIZADO 2025'!I53*'PREVISTO 2026 REVISADO'!$U$22 -> 332.802 | L29: ='REALIZADO 2025'!J53*'PREVISTO 2026 REVISADO'!$U$22 -> 332.802 | M29: ='REALIZADO 2025'!K53*'PREVISTO 2026 REVISADO'!$U$22 -> 332.802 | ... Q29: ='REALIZADO 2025'!O53*'PREVISTO 2026 REVISADO'!$U$22 -> 534.5352 | R29: =SUM(F29:Q29) -> 4344.2568 | S29: =R29/12 -> 362.0214
C30: 2.2.16 Contribuição Sindical Empregados | F30: ='REALIZADO 2025'!D54*'PREVISTO 2026 REVISADO'!$U$22 -> 324 | G30: ='REALIZADO 2025'!E54*'PREVISTO 2026 REVISADO'!$U$22 -> 324 | H30: ='REALIZADO 2025'!F54*'PREVISTO 2026 REVISADO'!$U$22 -> 367.2 | I30: ='REALIZADO 2025'!G54*'PREVISTO 2026 REVISADO'!$U$22 -> 345.6 | J30: ='REALIZADO 2025'!H54*'PREVISTO 2026 REVISADO'!$U$22 -> 345.6 | K30: ='REALIZADO 2025'!I54*'PREVISTO 2026 REVISADO'!$U$22 -> 324 | L30: ='REALIZADO 2025'!J54*'PREVISTO 2026 REVISADO'!$U$22 -> 302.4 | M30: ='REALIZADO 2025'!K54*'PREVISTO 2026 REVISADO'!$U$22 -> 324 | ... Q30: ='REALIZADO 2025'!O54*'PREVISTO 2026 REVISADO'!$U$22 -> 0 | R30: =SUM(F30:Q30) -> 3304.8 | S30: =R30/12 -> 275.4
C31: 2.2.17 Contribuição Sindical Patronal | F31: ='REALIZADO 2025'!D55*'PREVISTO 2026 REVISADO'!$U$22 -> 0 | G31: ='REALIZADO 2025'!E55*'PREVISTO 2026 REVISADO'!$U$22 -> 0 | H31: ='REALIZADO 2025'!F55*'PREVISTO 2026 REVISADO'!$U$22 -> 0 | I31: ='REALIZADO 2025'!G55*'PREVISTO 2026 REVISADO'!$U$22 -> 0 | J31: ='REALIZADO 2025'!H55*'PREVISTO 2026 REVISADO'!$U$22 -> 0 | K31: ='REALIZADO 2025'!I55*'PREVISTO 2026 REVISADO'!$U$22 -> 0 | L31: ='REALIZADO 2025'!J55*'PREVISTO 2026 REVISADO'!$U$22 -> 0 | M31: ='REALIZADO 2025'!K55*'PREVISTO 2026 REVISADO'!$U$22 -> 0 | ... Q31: ='REALIZADO 2025'!O55*'PREVISTO 2026 REVISADO'!$U$22 -> 367.2 | R31: =SUM(F31:Q31) -> 712.8 | S31: =R31/12 -> 59.4
C32: 2.2.20 Tributos Dctf-web | F32: ='REALIZADO 2025'!D57*'PREVISTO 2026 REVISADO'!$U$22 -> 26005.406 | G32: ='REALIZADO 2025'!E57*'PREVISTO 2026 REVISADO'!$U$22 -> 25600.212 | H32: ='REALIZADO 2025'!F57*'PREVISTO 2026 REVISADO'!$U$22 -> 24219.011 | I32: ='REALIZADO 2025'!G57*'PREVISTO 2026 REVISADO'!$U$22 -> 24259.932 | J32: ='REALIZADO 2025'!H57*'PREVISTO 2026 REVISADO'!$U$22 -> 26176.943 | K32: ='REALIZADO 2025'!I57*'PREVISTO 2026 REVISADO'!$U$22 -> 27497.815 | L32: ='REALIZADO 2025'!J57*'PREVISTO 2026 REVISADO'!$U$22 -> 29137.298 | M32: ='REALIZADO 2025'!K57*'PREVISTO 2026 REVISADO'!$U$22 -> 28422.446 | ... Q32: ='REALIZADO 2025'!O57*'PREVISTO 2026 REVISADO'!$U$22 -> 29389.878 | R32: =SUM(F32:Q32) -> 321580.7 | S32: =R32/12 -> 26798.392
C33: 2.2.3 Fgts | F33: ='REALIZADO 2025'!D58*'PREVISTO 2026 REVISADO'!$U$22 -> 5940.0108 | G33: ='REALIZADO 2025'!E58*'PREVISTO 2026 REVISADO'!$U$22 -> 6738.3576 | H33: ='REALIZADO 2025'!F58*'PREVISTO 2026 REVISADO'!$U$22 -> 4368.816 | I33: ='REALIZADO 2025'!G58*'PREVISTO 2026 REVISADO'!$U$22 -> 4458.0024 | J33: ='REALIZADO 2025'!H58*'PREVISTO 2026 REVISADO'!$U$22 -> 4821.5196 | K33: ='REALIZADO 2025'!I58*'PREVISTO 2026 REVISADO'!$U$22 -> 4989.3084 | L33: ='REALIZADO 2025'!J58*'PREVISTO 2026 REVISADO'!$U$22 -> 5267.2032 | M33: ='REALIZADO 2025'!K58*'PREVISTO 2026 REVISADO'!$U$22 -> 5605.5024 | ... Q33: ='REALIZADO 2025'!O58*'PREVISTO 2026 REVISADO'!$U$22 -> 6208.488 | R33: =SUM(F33:Q33) -> 65711.941 | S33: =R33/12 -> 5475.9951
C34: 2.2.6 Férias | F34: ='REALIZADO 2025'!D59*'PREVISTO 2026 REVISADO'!$U$22 -> 0 | G34: ='REALIZADO 2025'!E59*'PREVISTO 2026 REVISADO'!$U$22 -> 0 | H34: ='REALIZADO 2025'!F59*'PREVISTO 2026 REVISADO'!$U$22 -> 6453.5292 | I34: ='REALIZADO 2025'!G59*'PREVISTO 2026 REVISADO'!$U$22 -> 9554.8356 | J34: ='REALIZADO 2025'!H59*'PREVISTO 2026 REVISADO'!$U$22 -> 0 | K34: ='REALIZADO 2025'!I59*'PREVISTO 2026 REVISADO'!$U$22 -> 14145.57 | L34: ='REALIZADO 2025'!J59*'PREVISTO 2026 REVISADO'!$U$22 -> 18469.642 | M34: ='REALIZADO 2025'!K59*'PREVISTO 2026 REVISADO'!$U$22 -> 0 | ... Q34: ='REALIZADO 2025'!O59*'PREVISTO 2026 REVISADO'!$U$22 -> 0 | R34: =SUM(F34:Q34) -> 57366.209 | S34: =R34/12 -> 4780.5174
C35: 2.2.7 13 Salário | F35: ='REALIZADO 2025'!D60*'PREVISTO 2026 REVISADO'!$U$22 -> 41884.214 | G35: ='REALIZADO 2025'!E60*'PREVISTO 2026 REVISADO'!$U$22 -> 0 | H35: ='REALIZADO 2025'!F60*'PREVISTO 2026 REVISADO'!$U$22 -> 0 | I35: ='REALIZADO 2025'!G60*'PREVISTO 2026 REVISADO'!$U$22 -> 0 | J35: ='REALIZADO 2025'!H60*'PREVISTO 2026 REVISADO'!$U$22 -> 0 | K35: ='REALIZADO 2025'!I60*'PREVISTO 2026 REVISADO'!$U$22 -> 0 | L35: ='REALIZADO 2025'!J60*'PREVISTO 2026 REVISADO'!$U$22 -> 0 | M35: ='REALIZADO 2025'!K60*'PREVISTO 2026 REVISADO'!$U$22 -> 0 | ... Q35: ='REALIZADO 2025'!O60*'PREVISTO 2026 REVISADO'!$U$22 -> 20089.08 | R35: =SUM(F35:Q35) -> 71808.854 | S35: =R35/12 -> 5984.0712
C36: 2.2.8 Rescisões | F36: ='REALIZADO 2025'!D61*'PREVISTO 2026 REVISADO'!$U$22 -> 0 | G36: ='REALIZADO 2025'!E61*'PREVISTO 2026 REVISADO'!$U$22 -> 7352.1864 | H36: ='REALIZADO 2025'!F61*'PREVISTO 2026 REVISADO'!$U$22 -> 0 | I36: ='REALIZADO 2025'!G61*'PREVISTO 2026 REVISADO'!$U$22 -> 13862.48 | J36: ='REALIZADO 2025'!H61*'PREVISTO 2026 REVISADO'!$U$22 -> 0 | K36: ='REALIZADO 2025'!I61*'PREVISTO 2026 REVISADO'!$U$22 -> 0 | L36: ='REALIZADO 2025'!J61*'PREVISTO 2026 REVISADO'!$U$22 -> 0 | M36: ='REALIZADO 2025'!K61*'PREVISTO 2026 REVISADO'!$U$22 -> 0 | ... Q36: ='REALIZADO 2025'!O61*'PREVISTO 2026 REVISADO'!$U$22 -> 1015.2 | R36: 90000 | S36: =R36/12 -> 7500
C37: 2.2.9 Vale Transporte | F37: ='REALIZADO 2025'!D62*'PREVISTO 2026 REVISADO'!$U$22 -> 816.48 | G37: ='REALIZADO 2025'!E62*'PREVISTO 2026 REVISADO'!$U$22 -> 1516.32 | H37: ='REALIZADO 2025'!F62*'PREVISTO 2026 REVISADO'!$U$22 -> 1856.52 | I37: ='REALIZADO 2025'!G62*'PREVISTO 2026 REVISADO'!$U$22 -> 106.92 | J37: ='REALIZADO 2025'!H62*'PREVISTO 2026 REVISADO'!$U$22 -> 1487.16 | K37: ='REALIZADO 2025'!I62*'PREVISTO 2026 REVISADO'!$U$22 -> 1653.048 | L37: ='REALIZADO 2025'!J62*'PREVISTO 2026 REVISADO'!$U$22 -> 1341.36 | M37: ='REALIZADO 2025'!K62*'PREVISTO 2026 REVISADO'!$U$22 -> 1253.88 | ... Q37: ='REALIZADO 2025'!O62*'PREVISTO 2026 REVISADO'!$U$22 -> 0 | R37: =SUM(F37:Q37) -> 12277.008 | S37: =R37/12 -> 1023.084
C38: 2.3 Manutenção | F38: =F39+F55+F68+F72 -> 48895.278 | G38: =G39+G55+G68+G72 -> 40170.981 | H38: =H39+H55+H68+H72 -> 45046.554 | I38: =I39+I55+I68+I72 -> 48792.712 | J38: =J39+J55+J68+J72 -> 77235.741 | K38: =K39+K55+K68+K72 -> 75126.429 | L38: =L39+L55+L68+L72 -> 57768.373 | M38: =M39+M55+M68+M72 -> 45237.298 | ... R38: =R39+R55+R68+R72 -> 638498.62 | S38: =R38/12 -> 53208.219 | T38: REAJUSTE | U38: 1.045 | V38: 0.045
C39: 2.3.1 Areas De Lazer | F39: =SUM(F40:F48) -> 11772.991 | G39: =SUM(G40:G48) -> 6239.162 | H39: =SUM(H40:H48) -> 4612.3374 | I39: =SUM(I40:I48) -> 5200.2335 | J39: =SUM(J40:J48) -> 55340.149 | K39: =SUM(K40:K48) -> 52472.271 | L39: =SUM(L40:L48) -> 32692.501 | M39: =SUM(M40:M48) -> 16665.378 | ... Q39: =SUM(Q40:Q48) -> 24886.111 | R39: =SUM(R40:R54) -> 332522.31 | S39: =R39/12 -> 27710.192
C40: 2.3.1.1 Salão De Festas Bosque | F40: ='REALIZADO 2025'!D65*'PREVISTO 2026 REVISADO'!$U$38 -> 1550.686 | G40: ='REALIZADO 2025'!E65*'PREVISTO 2026 REVISADO'!$U$38 -> 470.25 | H40: ='REALIZADO 2025'!F65*'PREVISTO 2026 REVISADO'!$U$38 -> 1302.07 | I40: ='REALIZADO 2025'!G65*'PREVISTO 2026 REVISADO'!$U$38 -> 767.64655 | J40: ='REALIZADO 2025'!H65*'PREVISTO 2026 REVISADO'!$U$38 -> 8109.0955 | K40: ='REALIZADO 2025'!I65*'PREVISTO 2026 REVISADO'!$U$38 -> 9680.88 | L40: ='REALIZADO 2025'!J65*'PREVISTO 2026 REVISADO'!$U$38 -> 1657.37 | M40: ='REALIZADO 2025'!K65*'PREVISTO 2026 REVISADO'!$U$38 -> 5182.4685 | ... Q40: ='REALIZADO 2025'!O65*'PREVISTO 2026 REVISADO'!$U$38 -> 1478.9467 | R40: 63600 | S40: =R40/12 -> 5300
C41: 2.3.1.12 Churrasqueira Costela Fogo De Chão | F41: ='REALIZADO 2025'!D67*'PREVISTO 2026 REVISADO'!$U$38 -> 0 | G41: ='REALIZADO 2025'!E67*'PREVISTO 2026 REVISADO'!$U$38 -> 0 | H41: ='REALIZADO 2025'!F67*'PREVISTO 2026 REVISADO'!$U$38 -> 0 | I41: ='REALIZADO 2025'!G67*'PREVISTO 2026 REVISADO'!$U$38 -> 0 | J41: ='REALIZADO 2025'!H67*'PREVISTO 2026 REVISADO'!$U$38 -> 0 | K41: ='REALIZADO 2025'!I67*'PREVISTO 2026 REVISADO'!$U$38 -> 468.996 | L41: ='REALIZADO 2025'!J67*'PREVISTO 2026 REVISADO'!$U$38 -> 0 | M41: ='REALIZADO 2025'!K67*'PREVISTO 2026 REVISADO'!$U$38 -> 0 | ... Q41: ='REALIZADO 2025'!O67*'PREVISTO 2026 REVISADO'!$U$38 -> 1730.1229 | R41: =SUM(F41:Q41) -> 2199.1189 | S41: =R41/12 -> 183.25991
C42: 2.3.1.2 Salão De Festas Piscina | F42: ='REALIZADO 2025'!D68*'PREVISTO 2026 REVISADO'!$U$38 -> 3193.8857 | G42: ='REALIZADO 2025'!E68*'PREVISTO 2026 REVISADO'!$U$38 -> 491.15 | H42: ='REALIZADO 2025'!F68*'PREVISTO 2026 REVISADO'!$U$38 -> 778.525 | I42: ='REALIZADO 2025'!G68*'PREVISTO 2026 REVISADO'!$U$38 -> 1744.0527 | J42: ='REALIZADO 2025'!H68*'PREVISTO 2026 REVISADO'!$U$38 -> 39798.062 | K42: ='REALIZADO 2025'!I68*'PREVISTO 2026 REVISADO'!$U$38 -> 33495.207 | L42: ='REALIZADO 2025'!J68*'PREVISTO 2026 REVISADO'!$U$38 -> 22087.862 | M42: ='REALIZADO 2025'!K68*'PREVISTO 2026 REVISADO'!$U$38 -> 5523.6296 | ... Q42: ='REALIZADO 2025'!O68*'PREVISTO 2026 REVISADO'!$U$38 -> 8769.3787 | R42: 24000 | S42: =R42/12 -> 2000
C43: 2.3.1.3 Salão De Festas Pub | F43: ='REALIZADO 2025'!D69*'PREVISTO 2026 REVISADO'!$U$38 -> 610.8025 | G43: ='REALIZADO 2025'!E69*'PREVISTO 2026 REVISADO'!$U$38 -> 485.03675 | H43: ='REALIZADO 2025'!F69*'PREVISTO 2026 REVISADO'!$U$38 -> 192.4263 | I43: ='REALIZADO 2025'!G69*'PREVISTO 2026 REVISADO'!$U$38 -> 62.7 | J43: ='REALIZADO 2025'!H69*'PREVISTO 2026 REVISADO'!$U$38 -> 3135 | K43: ='REALIZADO 2025'!I69*'PREVISTO 2026 REVISADO'!$U$38 -> 5643 | L43: ='REALIZADO 2025'!J69*'PREVISTO 2026 REVISADO'!$U$38 -> 0 | M43: ='REALIZADO 2025'!K69*'PREVISTO 2026 REVISADO'!$U$38 -> 401.22775 | ... Q43: ='REALIZADO 2025'!O69*'PREVISTO 2026 REVISADO'!$U$38 -> 6967.1195 | R43: 16000 | S43: =R43/12 -> 1333.3333
C44: 2.3.1.4 Quiosque | F44: ='REALIZADO 2025'!D70*'PREVISTO 2026 REVISADO'!$U$38 -> 554.5188 | G44: ='REALIZADO 2025'!E70*'PREVISTO 2026 REVISADO'!$U$38 -> 0 | H44: ='REALIZADO 2025'!F70*'PREVISTO 2026 REVISADO'!$U$38 -> 0 | I44: ='REALIZADO 2025'!G70*'PREVISTO 2026 REVISADO'!$U$38 -> 0 | J44: ='REALIZADO 2025'!H70*'PREVISTO 2026 REVISADO'!$U$38 -> 0 | K44: ='REALIZADO 2025'!I70*'PREVISTO 2026 REVISADO'!$U$38 -> 0 | L44: ='REALIZADO 2025'!J70*'PREVISTO 2026 REVISADO'!$U$38 -> 0 | M44: ='REALIZADO 2025'!K70*'PREVISTO 2026 REVISADO'!$U$38 -> 0 | ... Q44: ='REALIZADO 2025'!O70*'PREVISTO 2026 REVISADO'!$U$38 -> 271.7 | R44: =SUM(F44:Q44) -> 5771.5977 | S44: =R44/12 -> 480.96648
C45: 2.3.1.5 Espaço Juvenil | F45: ='REALIZADO 2025'!D71*'PREVISTO 2026 REVISADO'!$U$38 -> 0 | G45: ='REALIZADO 2025'!E71*'PREVISTO 2026 REVISADO'!$U$38 -> 0 | H45: ='REALIZADO 2025'!F71*'PREVISTO 2026 REVISADO'!$U$38 -> 0 | I45: ='REALIZADO 2025'!G71*'PREVISTO 2026 REVISADO'!$U$38 -> 0 | J45: ='REALIZADO 2025'!H71*'PREVISTO 2026 REVISADO'!$U$38 -> 0 | K45: ='REALIZADO 2025'!I71*'PREVISTO 2026 REVISADO'!$U$38 -> 0 | L45: ='REALIZADO 2025'!J71*'PREVISTO 2026 REVISADO'!$U$38 -> 1440.01 | M45: ='REALIZADO 2025'!K71*'PREVISTO 2026 REVISADO'!$U$38 -> 543.4 | ... Q45: ='REALIZADO 2025'!O71*'PREVISTO 2026 REVISADO'!$U$38 -> 683.3464 | R45: =SUM(F45:Q45) -> 12602.575 | S45: =R45/12 -> 1050.2145
C46: 2.3.1.6 Piscina | F46: ='REALIZADO 2025'!D72*'PREVISTO 2026 REVISADO'!$U$38 -> 5500.8486 | G46: ='REALIZADO 2025'!E72*'PREVISTO 2026 REVISADO'!$U$38 -> 4596.8505 | H46: ='REALIZADO 2025'!F72*'PREVISTO 2026 REVISADO'!$U$38 -> 1380.1106 | I46: ='REALIZADO 2025'!G72*'PREVISTO 2026 REVISADO'!$U$38 -> 1256.4348 | J46: ='REALIZADO 2025'!H72*'PREVISTO 2026 REVISADO'!$U$38 -> 1988.7499 | K46: ='REALIZADO 2025'!I72*'PREVISTO 2026 REVISADO'!$U$38 -> 252.7646 | L46: ='REALIZADO 2025'!J72*'PREVISTO 2026 REVISADO'!$U$38 -> 202.7718 | M46: ='REALIZADO 2025'!K72*'PREVISTO 2026 REVISADO'!$U$38 -> 2318.855 | ... Q46: ='REALIZADO 2025'!O72*'PREVISTO 2026 REVISADO'!$U$38 -> 4023.1559 | R46: 20000 | S46: =R46/12 -> 1666.6667
C47: 2.3.1.7 Playground - Bosque | F47: ='REALIZADO 2025'!D73*'PREVISTO 2026 REVISADO'!$U$38 -> 349.70925 | G47: ='REALIZADO 2025'!E73*'PREVISTO 2026 REVISADO'!$U$38 -> 60.5055 | H47: ='REALIZADO 2025'!F73*'PREVISTO 2026 REVISADO'!$U$38 -> 60.5055 | I47: ='REALIZADO 2025'!G73*'PREVISTO 2026 REVISADO'!$U$38 -> 60.5055 | J47: ='REALIZADO 2025'!H73*'PREVISTO 2026 REVISADO'!$U$38 -> 60.5055 | K47: ='REALIZADO 2025'!I73*'PREVISTO 2026 REVISADO'!$U$38 -> 530.7555 | L47: ='REALIZADO 2025'!J73*'PREVISTO 2026 REVISADO'!$U$38 -> 3445.156 | M47: ='REALIZADO 2025'!K73*'PREVISTO 2026 REVISADO'!$U$38 -> 257.07 | ... Q47: ='REALIZADO 2025'!O73*'PREVISTO 2026 REVISADO'!$U$38 -> 0 | R47: 25000 | S47: =R47/12 -> 2083.3333
C48: 2.3.1.8 Academia | F48: ='REALIZADO 2025'!D74*'PREVISTO 2026 REVISADO'!$U$38 -> 12.54 | G48: ='REALIZADO 2025'!E74*'PREVISTO 2026 REVISADO'!$U$38 -> 135.3693 | H48: ='REALIZADO 2025'!F74*'PREVISTO 2026 REVISADO'!$U$38 -> 898.7 | I48: ='REALIZADO 2025'!G74*'PREVISTO 2026 REVISADO'!$U$38 -> 1308.8938 | J48: ='REALIZADO 2025'!H74*'PREVISTO 2026 REVISADO'!$U$38 -> 2248.7355 | K48: ='REALIZADO 2025'!I74*'PREVISTO 2026 REVISADO'!$U$38 -> 2400.668 | L48: ='REALIZADO 2025'!J74*'PREVISTO 2026 REVISADO'!$U$38 -> 3859.3313 | M48: ='REALIZADO 2025'!K74*'PREVISTO 2026 REVISADO'!$U$38 -> 2438.7269 | ... Q48: ='REALIZADO 2025'!O74*'PREVISTO 2026 REVISADO'!$U$38 -> 962.3405 | R48: =SUM(F48:Q48) -> 17349.017 | S48: =R48/12 -> 1445.7514
C49: 2.3.1.13 Quadra Futebol | R49: 10000 | S49: =R49/12 -> 833.33333
C50: 2.3.1.14 Quadra de tenis | R50: 10000 | S50: =R50/12 -> 833.33333
C51: 2.3.1.15 Quadra Poliesportiva | R51: 90000 | S51: =R51/12 -> 7500
C52: 2.3.1.16 Quadra Padle | R52: 3000 | S52: =R52/12 -> 250
C53: 2.3.1.17 Quadra de areia | R53: 3000 | S53: =R53/12 -> 250
C54: 2.3.1.18 Playground - Piscina | R54: 30000 | S54: =R54/12 -> 2500
C55: 2.3.2 Estrutura | F55: =SUM(F56:F67) -> 13069.94 | G55: =SUM(G56:G67) -> 14929.142 | H55: =SUM(H56:H67) -> 19163.168 | I55: =SUM(I56:I67) -> 16750.493 | J55: =SUM(J56:J67) -> 10903.938 | K55: =SUM(K56:K67) -> 10419.653 | L55: =SUM(L56:L67) -> 14561.835 | M55: =SUM(M56:M67) -> 8672.9984 | ... R55: =SUM(R56:R67) -> 149101.29 | S55: =R55/12 -> 12425.108
C56: 2.3.2.1 Areas e Instalações Comuns | F56: ='REALIZADO 2025'!D76*'PREVISTO 2026 REVISADO'!$U$38 -> 1201.7082 | G56: ='REALIZADO 2025'!E76*'PREVISTO 2026 REVISADO'!$U$38 -> 5668.4353 | H56: ='REALIZADO 2025'!F76*'PREVISTO 2026 REVISADO'!$U$38 -> 1839.4299 | I56: ='REALIZADO 2025'!G76*'PREVISTO 2026 REVISADO'!$U$38 -> 1707.436 | J56: ='REALIZADO 2025'!H76*'PREVISTO 2026 REVISADO'!$U$38 -> 1130.7213 | K56: ='REALIZADO 2025'!I76*'PREVISTO 2026 REVISADO'!$U$38 -> 410.50735 | L56: ='REALIZADO 2025'!J76*'PREVISTO 2026 REVISADO'!$U$38 -> 2901.2753 | M56: ='REALIZADO 2025'!K76*'PREVISTO 2026 REVISADO'!$U$38 -> 1329.752 | ... Q56: ='REALIZADO 2025'!O76*'PREVISTO 2026 REVISADO'!$U$38 -> 1431.65 | R56: =SUM(F56:Q56) -> 22780.404 | S56: =R56/12 -> 1898.367
C57: 2.3.2.10 Ruas-meio Fio-lombada-sinalização | F57: ='REALIZADO 2025'!D77*'PREVISTO 2026 REVISADO'!$U$38 -> 0 | G57: ='REALIZADO 2025'!E77*'PREVISTO 2026 REVISADO'!$U$38 -> 2427.5245 | H57: ='REALIZADO 2025'!F77*'PREVISTO 2026 REVISADO'!$U$38 -> 3773.1188 | I57: ='REALIZADO 2025'!G77*'PREVISTO 2026 REVISADO'!$U$38 -> 1885.3785 | J57: ='REALIZADO 2025'!H77*'PREVISTO 2026 REVISADO'!$U$38 -> 1016.2625 | K57: ='REALIZADO 2025'!I77*'PREVISTO 2026 REVISADO'!$U$38 -> 3881.9869 | L57: ='REALIZADO 2025'!J77*'PREVISTO 2026 REVISADO'!$U$38 -> 3093.2 | M57: ='REALIZADO 2025'!K77*'PREVISTO 2026 REVISADO'!$U$38 -> 1703.35 | ... Q57: ='REALIZADO 2025'!O77*'PREVISTO 2026 REVISADO'!$U$38 -> 2277.6716 | R57: =SUM(F57:Q57) -> 29107.096 | S57: =R57/12 -> 2425.5913
C58: 2.3.2.12 Pergola | F58: ='REALIZADO 2025'!D78*'PREVISTO 2026 REVISADO'!$U$38 -> 888.25 | G58: ='REALIZADO 2025'!E78*'PREVISTO 2026 REVISADO'!$U$38 -> 548.625 | H58: ='REALIZADO 2025'!F78*'PREVISTO 2026 REVISADO'!$U$38 -> 0 | I58: ='REALIZADO 2025'!G78*'PREVISTO 2026 REVISADO'!$U$38 -> 0 | J58: ='REALIZADO 2025'!H78*'PREVISTO 2026 REVISADO'!$U$38 -> 0 | K58: ='REALIZADO 2025'!I78*'PREVISTO 2026 REVISADO'!$U$38 -> 0 | L58: ='REALIZADO 2025'!J78*'PREVISTO 2026 REVISADO'!$U$38 -> 0 | M58: ='REALIZADO 2025'!K78*'PREVISTO 2026 REVISADO'!$U$38 -> 0 | ... Q58: ='REALIZADO 2025'!O78*'PREVISTO 2026 REVISADO'!$U$38 -> 0 | R58: =SUM(F58:Q58) -> 1436.875 | S58: =R58/12 -> 119.73958
C59: 2.3.2.13 Dog Park | F59: ='REALIZADO 2025'!D79*'PREVISTO 2026 REVISADO'!$U$38 -> 0 | G59: ='REALIZADO 2025'!E79*'PREVISTO 2026 REVISADO'!$U$38 -> 0 | H59: ='REALIZADO 2025'!F79*'PREVISTO 2026 REVISADO'!$U$38 -> 0 | I59: ='REALIZADO 2025'!G79*'PREVISTO 2026 REVISADO'!$U$38 -> 0 | J59: ='REALIZADO 2025'!H79*'PREVISTO 2026 REVISADO'!$U$38 -> 0 | K59: ='REALIZADO 2025'!I79*'PREVISTO 2026 REVISADO'!$U$38 -> 0 | L59: ='REALIZADO 2025'!J79*'PREVISTO 2026 REVISADO'!$U$38 -> 0 | M59: ='REALIZADO 2025'!K79*'PREVISTO 2026 REVISADO'!$U$38 -> 0 | ... Q59: ='REALIZADO 2025'!O79*'PREVISTO 2026 REVISADO'!$U$38 -> 0 | R59: =SUM(F59:Q59) -> 42.5733 | S59: =R59/12 -> 3.547775
C60: 2.3.2.2 Elétrica- Iluminação | F60: ='REALIZADO 2025'!D80*'PREVISTO 2026 REVISADO'!$U$38 -> 2080.5114 | G60: ='REALIZADO 2025'!E80*'PREVISTO 2026 REVISADO'!$U$38 -> 1775.5804 | H60: ='REALIZADO 2025'!F80*'PREVISTO 2026 REVISADO'!$U$38 -> 2668.5329 | I60: ='REALIZADO 2025'!G80*'PREVISTO 2026 REVISADO'!$U$38 -> 5443.0915 | J60: ='REALIZADO 2025'!H80*'PREVISTO 2026 REVISADO'!$U$38 -> 3762.7419 | K60: ='REALIZADO 2025'!I80*'PREVISTO 2026 REVISADO'!$U$38 -> 3642.0862 | L60: ='REALIZADO 2025'!J80*'PREVISTO 2026 REVISADO'!$U$38 -> 372.7933 | M60: ='REALIZADO 2025'!K80*'PREVISTO 2026 REVISADO'!$U$38 -> 968.1925 | ... Q60: ='REALIZADO 2025'!O80*'PREVISTO 2026 REVISADO'!$U$38 -> 4547.422 | R60: 10000 | S60: =R60/12 -> 833.33333
C61: 2.3.2.3 Instalações Hidráulicas- Esgoto | F61: ='REALIZADO 2025'!D81*'PREVISTO 2026 REVISADO'!$U$38 -> 0 | G61: ='REALIZADO 2025'!E81*'PREVISTO 2026 REVISADO'!$U$38 -> 0 | H61: ='REALIZADO 2025'!F81*'PREVISTO 2026 REVISADO'!$U$38 -> 0 | I61: ='REALIZADO 2025'!G81*'PREVISTO 2026 REVISADO'!$U$38 -> 104.5 | J61: ='REALIZADO 2025'!H81*'PREVISTO 2026 REVISADO'!$U$38 -> 0 | K61: ='REALIZADO 2025'!I81*'PREVISTO 2026 REVISADO'!$U$38 -> 0 | L61: ='REALIZADO 2025'!J81*'PREVISTO 2026 REVISADO'!$U$38 -> 0 | M61: ='REALIZADO 2025'!K81*'PREVISTO 2026 REVISADO'!$U$38 -> 0 | ... Q61: ='REALIZADO 2025'!O81*'PREVISTO 2026 REVISADO'!$U$38 -> 56.7644 | R61: =SUM(F61:Q61) -> 161.2644 | S61: =R61/12 -> 13.4387
C62: 2.3.2.4 Jardim | F62: ='REALIZADO 2025'!D82*'PREVISTO 2026 REVISADO'!$U$38 -> 7691.6598 | G62: ='REALIZADO 2025'!E82*'PREVISTO 2026 REVISADO'!$U$38 -> 2713.0812 | H62: ='REALIZADO 2025'!F82*'PREVISTO 2026 REVISADO'!$U$38 -> 1018.875 | I62: ='REALIZADO 2025'!G82*'PREVISTO 2026 REVISADO'!$U$38 -> 2666.84 | J62: ='REALIZADO 2025'!H82*'PREVISTO 2026 REVISADO'!$U$38 -> 2783.88 | K62: ='REALIZADO 2025'!I82*'PREVISTO 2026 REVISADO'!$U$38 -> 836 | L62: ='REALIZADO 2025'!J82*'PREVISTO 2026 REVISADO'!$U$38 -> 877.8 | M62: ='REALIZADO 2025'!K82*'PREVISTO 2026 REVISADO'!$U$38 -> 1648.4875 | ... Q62: ='REALIZADO 2025'!O82*'PREVISTO 2026 REVISADO'!$U$38 -> 2016.1812 | R62: =SUM(F62:Q62) -> 27564.09 | S62: =R62/12 -> 2297.0075
C63: 2.3.2.5 Portaria Social | F63: ='REALIZADO 2025'!D83*'PREVISTO 2026 REVISADO'!$U$38 -> 1149.5 | G63: ='REALIZADO 2025'!E83*'PREVISTO 2026 REVISADO'!$U$38 -> 1481.5592 | H63: ='REALIZADO 2025'!F83*'PREVISTO 2026 REVISADO'!$U$38 -> 2122.2696 | I63: ='REALIZADO 2025'!G83*'PREVISTO 2026 REVISADO'!$U$38 -> 2265.5914 | J63: ='REALIZADO 2025'!H83*'PREVISTO 2026 REVISADO'!$U$38 -> 1493.2945 | K63: ='REALIZADO 2025'!I83*'PREVISTO 2026 REVISADO'!$U$38 -> 1497.5163 | L63: ='REALIZADO 2025'!J83*'PREVISTO 2026 REVISADO'!$U$38 -> 1918.2438 | M63: ='REALIZADO 2025'!K83*'PREVISTO 2026 REVISADO'!$U$38 -> 2009.5663 | ... Q63: ='REALIZADO 2025'!O83*'PREVISTO 2026 REVISADO'!$U$38 -> 1762.3507 | R63: 35000 | S63: =R63/12 -> 2916.6667
C64: 2.3.2.6 Portaria De Serviço | F64: ='REALIZADO 2025'!D84*'PREVISTO 2026 REVISADO'!$U$38 -> 0 | G64: ='REALIZADO 2025'!E84*'PREVISTO 2026 REVISADO'!$U$38 -> 0 | H64: ='REALIZADO 2025'!F84*'PREVISTO 2026 REVISADO'!$U$38 -> 425.942 | I64: ='REALIZADO 2025'!G84*'PREVISTO 2026 REVISADO'!$U$38 -> 250.8 | J64: ='REALIZADO 2025'!H84*'PREVISTO 2026 REVISADO'!$U$38 -> 0 | K64: ='REALIZADO 2025'!I84*'PREVISTO 2026 REVISADO'!$U$38 -> 78.2705 | L64: ='REALIZADO 2025'!J84*'PREVISTO 2026 REVISADO'!$U$38 -> 1254 | M64: ='REALIZADO 2025'!K84*'PREVISTO 2026 REVISADO'!$U$38 -> 731.5 | ... Q64: ='REALIZADO 2025'!O84*'PREVISTO 2026 REVISADO'!$U$38 -> 0 | R64: =SUM(F64:Q64) -> 2855.4625 | S64: =R64/12 -> 237.95521
C65: 2.3.2.7 Prédio-sala Administrativo-garagem | F65: ='REALIZADO 2025'!D85*'PREVISTO 2026 REVISADO'!$U$38 -> 58.311 | G65: ='REALIZADO 2025'!E85*'PREVISTO 2026 REVISADO'!$U$38 -> 314.336 | H65: ='REALIZADO 2025'!F85*'PREVISTO 2026 REVISADO'!$U$38 -> 0 | I65: ='REALIZADO 2025'!G85*'PREVISTO 2026 REVISADO'!$U$38 -> 776.80075 | J65: ='REALIZADO 2025'!H85*'PREVISTO 2026 REVISADO'!$U$38 -> 23.20945 | K65: ='REALIZADO 2025'!I85*'PREVISTO 2026 REVISADO'!$U$38 -> 0 | L65: ='REALIZADO 2025'!J85*'PREVISTO 2026 REVISADO'!$U$38 -> 3766.18 | M65: ='REALIZADO 2025'!K85*'PREVISTO 2026 REVISADO'!$U$38 -> 282.15 | ... Q65: ='REALIZADO 2025'!O85*'PREVISTO 2026 REVISADO'!$U$38 -> 0 | R65: =SUM(F65:Q65) -> 9779.6743 | S65: =R65/12 -> 814.97286
C66: 2.3.2.8 Poço Artesiano | F66: ='REALIZADO 2025'!D86*'PREVISTO 2026 REVISADO'!$U$38 -> 0 | G66: ='REALIZADO 2025'!E86*'PREVISTO 2026 REVISADO'!$U$38 -> 0 | H66: ='REALIZADO 2025'!F86*'PREVISTO 2026 REVISADO'!$U$38 -> 7315 | I66: ='REALIZADO 2025'!G86*'PREVISTO 2026 REVISADO'!$U$38 -> 1650.055 | J66: ='REALIZADO 2025'!H86*'PREVISTO 2026 REVISADO'!$U$38 -> 0 | K66: ='REALIZADO 2025'!I86*'PREVISTO 2026 REVISADO'!$U$38 -> 0 | L66: ='REALIZADO 2025'!J86*'PREVISTO 2026 REVISADO'!$U$38 -> 0 | M66: ='REALIZADO 2025'!K86*'PREVISTO 2026 REVISADO'!$U$38 -> 0 | ... Q66: ='REALIZADO 2025'!O86*'PREVISTO 2026 REVISADO'!$U$38 -> 0 | R66: =SUM(F66:Q66) -> 9228.395 | S66: =R66/12 -> 769.03292
C67: 2.3.2.9 Cerca Muro | F67: ='REALIZADO 2025'!D87*'PREVISTO 2026 REVISADO'!$U$38 -> 0 | G67: ='REALIZADO 2025'!E87*'PREVISTO 2026 REVISADO'!$U$38 -> 0 | H67: ='REALIZADO 2025'!F87*'PREVISTO 2026 REVISADO'!$U$38 -> 0 | I67: ='REALIZADO 2025'!G87*'PREVISTO 2026 REVISADO'!$U$38 -> 0 | J67: ='REALIZADO 2025'!H87*'PREVISTO 2026 REVISADO'!$U$38 -> 693.82775 | K67: ='REALIZADO 2025'!I87*'PREVISTO 2026 REVISADO'!$U$38 -> 73.28585 | L67: ='REALIZADO 2025'!J87*'PREVISTO 2026 REVISADO'!$U$38 -> 378.34225 | M67: ='REALIZADO 2025'!K87*'PREVISTO 2026 REVISADO'!$U$38 -> 0 | ... Q67: ='REALIZADO 2025'!O87*'PREVISTO 2026 REVISADO'!$U$38 -> 0 | R67: =SUM(F67:Q67) -> 1145.4559 | S67: =R67/12 -> 95.454654
C68: 2.3.3 Máquinas e Equipamentos | F68: =SUM(F69:F71) -> 16132.187 | G68: =SUM(G69:G71) -> 14734.814 | H68: =SUM(H69:H71) -> 13166.112 | I68: =SUM(I69:I71) -> 15843.767 | J68: =SUM(J69:J71) -> 6390.175 | K68: =SUM(K69:K71) -> 10054.99 | L68: =SUM(L69:L71) -> 7028.67 | M68: =SUM(M69:M71) -> 8206.0401 | ... R68: =SUM(R69:R71) -> 95374.689 | S68: =R68/12 -> 7947.8907
C69: 2.3.3.1 Sistema De Segurança | F69: ='REALIZADO 2025'!D89*'PREVISTO 2026 REVISADO'!$U$38 -> 6040.6225 | G69: ='REALIZADO 2025'!E89*'PREVISTO 2026 REVISADO'!$U$38 -> 6040.6225 | H69: ='REALIZADO 2025'!F89*'PREVISTO 2026 REVISADO'!$U$38 -> 5339.95 | I69: ='REALIZADO 2025'!G89*'PREVISTO 2026 REVISADO'!$U$38 -> 7947.225 | J69: ='REALIZADO 2025'!H89*'PREVISTO 2026 REVISADO'!$U$38 -> 6390.175 | K69: ='REALIZADO 2025'!I89*'PREVISTO 2026 REVISADO'!$U$38 -> 5956.5 | L69: ='REALIZADO 2025'!J89*'PREVISTO 2026 REVISADO'!$U$38 -> 3423.42 | M69: ='REALIZADO 2025'!K89*'PREVISTO 2026 REVISADO'!$U$38 -> 5016 | ... Q69: ='REALIZADO 2025'!O89*'PREVISTO 2026 REVISADO'!$U$38 -> 0 | R69: =SUM(F69:Q69) -> 52460.045 | S69: =R69/12 -> 4371.6704
C70: 2.3.3.2 Aparelhos-máquinas-ferramentas-equipamentos | F70: ='REALIZADO 2025'!D90*'PREVISTO 2026 REVISADO'!$U$38 -> 7357.845 | G70: ='REALIZADO 2025'!E90*'PREVISTO 2026 REVISADO'!$U$38 -> 4558.081 | H70: ='REALIZADO 2025'!F90*'PREVISTO 2026 REVISADO'!$U$38 -> 5275.1077 | I70: ='REALIZADO 2025'!G90*'PREVISTO 2026 REVISADO'!$U$38 -> 7008.2925 | J70: ='REALIZADO 2025'!H90*'PREVISTO 2026 REVISADO'!$U$38 -> 0 | K70: ='REALIZADO 2025'!I90*'PREVISTO 2026 REVISADO'!$U$38 -> 2102.54 | L70: ='REALIZADO 2025'!J90*'PREVISTO 2026 REVISADO'!$U$38 -> 606.1 | M70: ='REALIZADO 2025'!K90*'PREVISTO 2026 REVISADO'!$U$38 -> 1864.9801 | ... Q70: ='REALIZADO 2025'!O90*'PREVISTO 2026 REVISADO'!$U$38 -> 1264.3455 | R70: 25000 | S70: =R70/12 -> 2083.3333
C71: 2.3.3.3 Veículo-moto | F71: ='REALIZADO 2025'!D91*'PREVISTO 2026 REVISADO'!$U$38 -> 2733.72 | G71: ='REALIZADO 2025'!E91*'PREVISTO 2026 REVISADO'!$U$38 -> 4136.11 | H71: ='REALIZADO 2025'!F91*'PREVISTO 2026 REVISADO'!$U$38 -> 2551.054 | I71: ='REALIZADO 2025'!G91*'PREVISTO 2026 REVISADO'!$U$38 -> 888.25 | J71: ='REALIZADO 2025'!H91*'PREVISTO 2026 REVISADO'!$U$38 -> 0 | K71: ='REALIZADO 2025'!I91*'PREVISTO 2026 REVISADO'!$U$38 -> 1995.95 | L71: ='REALIZADO 2025'!J91*'PREVISTO 2026 REVISADO'!$U$38 -> 2999.15 | M71: ='REALIZADO 2025'!K91*'PREVISTO 2026 REVISADO'!$U$38 -> 1325.06 | ... Q71: ='REALIZADO 2025'!O91*'PREVISTO 2026 REVISADO'!$U$38 -> 574.75 | R71: =SUM(F71:Q71) -> 17914.644 | S71: =R71/12 -> 1492.887
C72: 2.3.4 Serviços Especializados | F72: =SUM(F73:F77) -> 7920.1595 | G72: =SUM(G73:G77) -> 4267.8636 | H72: =SUM(H73:H77) -> 8104.9364 | I72: =SUM(I73:I77) -> 10998.217 | J72: =SUM(J73:J77) -> 4601.4798 | K72: =SUM(K73:K77) -> 2179.5147 | L72: =SUM(L73:L77) -> 3485.3676 | M72: =SUM(M73:M77) -> 11692.881 | ... R72: =SUM(R73:R77) -> 61500.336 | S72: =R72/12 -> 5125.028
C73: 2.3.4.1 Extintores | F73: ='REALIZADO 2025'!D93*'PREVISTO 2026 REVISADO'!$U$38 -> 909.15 | G73: ='REALIZADO 2025'!E93*'PREVISTO 2026 REVISADO'!$U$38 -> 0 | H73: ='REALIZADO 2025'!F93*'PREVISTO 2026 REVISADO'!$U$38 -> 0 | I73: ='REALIZADO 2025'!G93*'PREVISTO 2026 REVISADO'!$U$38 -> 0 | J73: ='REALIZADO 2025'!H93*'PREVISTO 2026 REVISADO'!$U$38 -> 0 | K73: ='REALIZADO 2025'!I93*'PREVISTO 2026 REVISADO'!$U$38 -> 0 | L73: ='REALIZADO 2025'!J93*'PREVISTO 2026 REVISADO'!$U$38 -> 0 | M73: ='REALIZADO 2025'!K93*'PREVISTO 2026 REVISADO'!$U$38 -> 0 | ... Q73: ='REALIZADO 2025'!O93*'PREVISTO 2026 REVISADO'!$U$38 -> 0 | R73: =SUM(F73:Q73) -> 1018.875 | S73: =R73/12 -> 84.90625
C74: 2.3.4.2 Dedetização-desinsetização-desratização | F74: ='REALIZADO 2025'!D94*'PREVISTO 2026 REVISADO'!$U$38 -> 752.4 | G74: ='REALIZADO 2025'!E94*'PREVISTO 2026 REVISADO'!$U$38 -> 686.1888 | H74: ='REALIZADO 2025'!F94*'PREVISTO 2026 REVISADO'!$U$38 -> 818.6112 | I74: ='REALIZADO 2025'!G94*'PREVISTO 2026 REVISADO'!$U$38 -> 1368.95 | J74: ='REALIZADO 2025'!H94*'PREVISTO 2026 REVISADO'!$U$38 -> 686.1888 | K74: ='REALIZADO 2025'!I94*'PREVISTO 2026 REVISADO'!$U$38 -> 818.6112 | L74: ='REALIZADO 2025'!J94*'PREVISTO 2026 REVISADO'!$U$38 -> 1813.3676 | M74: ='REALIZADO 2025'!K94*'PREVISTO 2026 REVISADO'!$U$38 -> 1575.1912 | ... Q74: ='REALIZADO 2025'!O94*'PREVISTO 2026 REVISADO'!$U$38 -> 852.72 | R74: =SUM(F74:Q74) -> 12477.3 | S74: =R74/12 -> 1039.775
C75: 2.3.4.3 Fossa-caixa De Gordura | F75: ='REALIZADO 2025'!D95*'PREVISTO 2026 REVISADO'!$U$38 -> 2403.5 | G75: ='REALIZADO 2025'!E95*'PREVISTO 2026 REVISADO'!$U$38 -> 545.49 | H75: ='REALIZADO 2025'!F95*'PREVISTO 2026 REVISADO'!$U$38 -> 447.26 | I75: ='REALIZADO 2025'!G95*'PREVISTO 2026 REVISADO'!$U$38 -> 900.69595 | J75: ='REALIZADO 2025'!H95*'PREVISTO 2026 REVISADO'!$U$38 -> 469.19455 | K75: ='REALIZADO 2025'!I95*'PREVISTO 2026 REVISADO'!$U$38 -> 0 | L75: ='REALIZADO 2025'!J95*'PREVISTO 2026 REVISADO'!$U$38 -> 418 | M75: ='REALIZADO 2025'!K95*'PREVISTO 2026 REVISADO'!$U$38 -> 921.69 | ... Q75: ='REALIZADO 2025'!O95*'PREVISTO 2026 REVISADO'!$U$38 -> 516.82565 | R75: =SUM(F75:Q75) -> 8399.9608 | S75: =R75/12 -> 699.99673
C76: 2.3.4.4 Reservatórios De Água | F76: ='REALIZADO 2025'!D96*'PREVISTO 2026 REVISADO'!$U$38 -> 1472.5095 | G76: ='REALIZADO 2025'!E96*'PREVISTO 2026 REVISADO'!$U$38 -> 528.1848 | H76: ='REALIZADO 2025'!F96*'PREVISTO 2026 REVISADO'!$U$38 -> 5585.0652 | I76: ='REALIZADO 2025'!G96*'PREVISTO 2026 REVISADO'!$U$38 -> 6136.9715 | J76: ='REALIZADO 2025'!H96*'PREVISTO 2026 REVISADO'!$U$38 -> 2192.0965 | K76: ='REALIZADO 2025'!I96*'PREVISTO 2026 REVISADO'!$U$38 -> 106.9035 | L76: ='REALIZADO 2025'!J96*'PREVISTO 2026 REVISADO'!$U$38 -> 0 | M76: ='REALIZADO 2025'!K96*'PREVISTO 2026 REVISADO'!$U$38 -> 7942 | ... Q76: ='REALIZADO 2025'!O96*'PREVISTO 2026 REVISADO'!$U$38 -> 428.7635 | R76: 20000 | S76: =R76/12 -> 1666.6667
C77: 2.3.4.5 Análise De Água | F77: ='REALIZADO 2025'!D97*'PREVISTO 2026 REVISADO'!$U$38 -> 2382.6 | G77: ='REALIZADO 2025'!E97*'PREVISTO 2026 REVISADO'!$U$38 -> 2508 | H77: ='REALIZADO 2025'!F97*'PREVISTO 2026 REVISADO'!$U$38 -> 1254 | I77: ='REALIZADO 2025'!G97*'PREVISTO 2026 REVISADO'!$U$38 -> 2591.6 | J77: ='REALIZADO 2025'!H97*'PREVISTO 2026 REVISADO'!$U$38 -> 1254 | K77: ='REALIZADO 2025'!I97*'PREVISTO 2026 REVISADO'!$U$38 -> 1254 | L77: ='REALIZADO 2025'!J97*'PREVISTO 2026 REVISADO'!$U$38 -> 1254 | M77: ='REALIZADO 2025'!K97*'PREVISTO 2026 REVISADO'!$U$38 -> 1254 | ... Q77: ='REALIZADO 2025'!O97*'PREVISTO 2026 REVISADO'!$U$38 -> 1672 | R77: =SUM(F77:Q77) -> 19604.2 | S77: =R77/12 -> 1633.6833
C78: 2.4 Serviços | F78: =SUM(F79:F85) -> 74062.4 | G78: =SUM(G79:G85) -> 69791.715 | H78: =SUM(H79:H85) -> 66502.577 | I78: =SUM(I79:I85) -> 61074.283 | J78: =SUM(J79:J85) -> 83086.623 | K78: =SUM(K79:K85) -> 79588.203 | L78: =SUM(L79:L85) -> 78941.129 | M78: =SUM(M79:M85) -> 79605.331 | ... R78: =SUM(R79:R85) -> 916617.03 | S78: =R78/12 -> 76384.752 | T78: REAJUSTE | U78: 1.045
C79: 2.4.1 Honorários Advocatícios | F79: ='REALIZADO 2025'!D99*'PREVISTO 2026 REVISADO'!$U$78 -> 4117.3 | G79: ='REALIZADO 2025'!E99*'PREVISTO 2026 REVISADO'!$U$78 -> 2058.65 | H79: ='REALIZADO 2025'!F99*'PREVISTO 2026 REVISADO'!$U$78 -> 0 | I79: ='REALIZADO 2025'!G99*'PREVISTO 2026 REVISADO'!$U$78 -> 0 | J79: ='REALIZADO 2025'!H99*'PREVISTO 2026 REVISADO'!$U$78 -> 6667.1 | K79: ='REALIZADO 2025'!I99*'PREVISTO 2026 REVISADO'!$U$78 -> 2304.225 | L79: ='REALIZADO 2025'!J99*'PREVISTO 2026 REVISADO'!$U$78 -> 2304.225 | M79: ='REALIZADO 2025'!K99*'PREVISTO 2026 REVISADO'!$U$78 -> 2304.225 | ... Q79: ='REALIZADO 2025'!O99*'PREVISTO 2026 REVISADO'!$U$78 -> 2304.225 | R79: =SUM(F79:Q79) -> 32003.344 | S79: =R79/12 -> 2666.9454
C80: 2.4.2 Honorários Engenharia | F80: ='REALIZADO 2025'!D100*'PREVISTO 2026 REVISADO'!$U$78 -> 2951.08 | G80: ='REALIZADO 2025'!E100*'PREVISTO 2026 REVISADO'!$U$78 -> 3172.62 | H80: ='REALIZADO 2025'!F100*'PREVISTO 2026 REVISADO'!$U$78 -> 3172.62 | I80: ='REALIZADO 2025'!G100*'PREVISTO 2026 REVISADO'!$U$78 -> 3172.62 | J80: ='REALIZADO 2025'!H100*'PREVISTO 2026 REVISADO'!$U$78 -> 3172.62 | K80: ='REALIZADO 2025'!I100*'PREVISTO 2026 REVISADO'!$U$78 -> 3172.62 | L80: ='REALIZADO 2025'!J100*'PREVISTO 2026 REVISADO'!$U$78 -> 3172.62 | M80: ='REALIZADO 2025'!K100*'PREVISTO 2026 REVISADO'!$U$78 -> 3172.62 | ... Q80: ='REALIZADO 2025'!O100*'PREVISTO 2026 REVISADO'!$U$78 -> 3172.62 | R80: =SUM(F80:Q80) -> 37849.9 | S80: =R80/12 -> 3154.1583
C81: 2.4.3 Honorários Contábeis | F81: ='REALIZADO 2025'!D101*'PREVISTO 2026 REVISADO'!$U$78 -> 4270.2671 | G81: ='REALIZADO 2025'!E101*'PREVISTO 2026 REVISADO'!$U$78 -> 3642.0444 | H81: ='REALIZADO 2025'!F101*'PREVISTO 2026 REVISADO'!$U$78 -> 2614.7885 | I81: ='REALIZADO 2025'!G101*'PREVISTO 2026 REVISADO'!$U$78 -> 2692.4738 | J81: ='REALIZADO 2025'!H101*'PREVISTO 2026 REVISADO'!$U$78 -> 2692.4634 | K81: ='REALIZADO 2025'!I101*'PREVISTO 2026 REVISADO'!$U$78 -> 3530.1667 | L81: ='REALIZADO 2025'!J101*'PREVISTO 2026 REVISADO'!$U$78 -> 2792.24 | M81: ='REALIZADO 2025'!K101*'PREVISTO 2026 REVISADO'!$U$78 -> 3253.085 | ... Q81: ='REALIZADO 2025'!O101*'PREVISTO 2026 REVISADO'!$U$78 -> 4425.0525 | R81: =SUM(F81:Q81) -> 38980.047 | S81: =R81/12 -> 3248.3372
C82: 2.4.4 Segurança- Serviço Vigilância | F82: ='REALIZADO 2025'!D102*'PREVISTO 2026 REVISADO'!$U$78 -> 58965.41 | G82: ='REALIZADO 2025'!E102*'PREVISTO 2026 REVISADO'!$U$78 -> 58988.808 | H82: ='REALIZADO 2025'!F102*'PREVISTO 2026 REVISADO'!$U$78 -> 58988.808 | I82: ='REALIZADO 2025'!G102*'PREVISTO 2026 REVISADO'!$U$78 -> 54895.689 | J82: ='REALIZADO 2025'!H102*'PREVISTO 2026 REVISADO'!$U$78 -> 69237.739 | K82: ='REALIZADO 2025'!I102*'PREVISTO 2026 REVISADO'!$U$78 -> 68417.164 | L82: ='REALIZADO 2025'!J102*'PREVISTO 2026 REVISADO'!$U$78 -> 64109.026 | M82: ='REALIZADO 2025'!K102*'PREVISTO 2026 REVISADO'!$U$78 -> 64109.026 | ... Q82: ='REALIZADO 2025'!O102*'PREVISTO 2026 REVISADO'!$U$78 -> 64109.026 | R82: =SUM(F82:Q82) -> 754147.79 | S82: =R82/12 -> 62845.649
C83: 2.4.5 Cobertura De Férias | F83: ='REALIZADO 2025'!D103*'PREVISTO 2026 REVISADO'!$U$78 -> 0 | G83: ='REALIZADO 2025'!E103*'PREVISTO 2026 REVISADO'!$U$78 -> 0 | H83: ='REALIZADO 2025'!F103*'PREVISTO 2026 REVISADO'!$U$78 -> 0 | I83: ='REALIZADO 2025'!G103*'PREVISTO 2026 REVISADO'!$U$78 -> 0 | J83: ='REALIZADO 2025'!H103*'PREVISTO 2026 REVISADO'!$U$78 -> 0 | K83: ='REALIZADO 2025'!I103*'PREVISTO 2026 REVISADO'!$U$78 -> 0 | L83: ='REALIZADO 2025'!J103*'PREVISTO 2026 REVISADO'!$U$78 -> 0 | M83: ='REALIZADO 2025'!K103*'PREVISTO 2026 REVISADO'!$U$78 -> 5198.875 | ... Q83: ='REALIZADO 2025'!O103*'PREVISTO 2026 REVISADO'!$U$78 -> 0 | R83: =SUM(F83:Q83) -> 10528.375 | S83: =R83/12 -> 877.36458
C84: 2.4.6 Serviços Extras | F84: ='REALIZADO 2025'!D104*'PREVISTO 2026 REVISADO'!$U$78 -> 2508 | G84: ='REALIZADO 2025'!E104*'PREVISTO 2026 REVISADO'!$U$78 -> 679.25 | H84: ='REALIZADO 2025'!F104*'PREVISTO 2026 REVISADO'!$U$78 -> 476.0184 | I84: ='REALIZADO 2025'!G104*'PREVISTO 2026 REVISADO'!$U$78 -> 313.5 | J84: ='REALIZADO 2025'!H104*'PREVISTO 2026 REVISADO'!$U$78 -> 0 | K84: ='REALIZADO 2025'!I104*'PREVISTO 2026 REVISADO'!$U$78 -> 2164.0278 | L84: ='REALIZADO 2025'!J104*'PREVISTO 2026 REVISADO'!$U$78 -> 746.548 | M84: ='REALIZADO 2025'!K104*'PREVISTO 2026 REVISADO'!$U$78 -> 1567.5 | ... Q84: ='REALIZADO 2025'!O104*'PREVISTO 2026 REVISADO'!$U$78 -> 418 | R84: =SUM(F84:Q84) -> 9290.8442 | S84: =R84/12 -> 774.23702
C85: 2.4.7 Eletro-eletrônica-comunicação-sistemas | F85: ='REALIZADO 2025'!D106*'PREVISTO 2026 REVISADO'!$U$78 -> 1250.3425 | G85: ='REALIZADO 2025'!E106*'PREVISTO 2026 REVISADO'!$U$78 -> 1250.3425 | H85: ='REALIZADO 2025'!F106*'PREVISTO 2026 REVISADO'!$U$78 -> 1250.3425 | I85: ='REALIZADO 2025'!G106*'PREVISTO 2026 REVISADO'!$U$78 -> 0 | J85: ='REALIZADO 2025'!H106*'PREVISTO 2026 REVISADO'!$U$78 -> 1316.7 | K85: ='REALIZADO 2025'!I106*'PREVISTO 2026 REVISADO'!$U$78 -> 0 | L85: ='REALIZADO 2025'!J106*'PREVISTO 2026 REVISADO'!$U$78 -> 5816.47 | M85: ='REALIZADO 2025'!K106*'PREVISTO 2026 REVISADO'!$U$78 -> 0 | ... Q85: ='REALIZADO 2025'!O106*'PREVISTO 2026 REVISADO'!$U$78 -> 5016 | R85: =SUM(F85:Q85) -> 33816.722 | S85: =R85/12 -> 2818.0602
C86: 2.5 Consumíveis | F86: =SUM(F87:F98) -> 15905.234 | G86: =SUM(G87:G98) -> 21901.246 | H86: =SUM(H87:H98) -> 21263.148 | I86: =SUM(I87:I98) -> 9530.8075 | J86: =SUM(J87:J98) -> 35037.606 | K86: =SUM(K87:K98) -> 20789.784 | L86: =SUM(L87:L98) -> 22684.745 | M86: =SUM(M87:M98) -> 22941.178 | ... R86: =SUM(R87:R98) -> 167560.8 | S86: =R86/12 -> 13963.4 | T86: REAJUSTE | U86: 1.045
C87: 2.5.1 Energia Elétrica | F87: ='REALIZADO 2025'!D109*'PREVISTO 2026 REVISADO'!$U$86 -> 11147.161 | G87: ='REALIZADO 2025'!E109*'PREVISTO 2026 REVISADO'!$U$86 -> 13803.468 | H87: ='REALIZADO 2025'!F109*'PREVISTO 2026 REVISADO'!$U$86 -> 13427.445 | I87: ='REALIZADO 2025'!G109*'PREVISTO 2026 REVISADO'!$U$86 -> 0 | J87: ='REALIZADO 2025'!H109*'PREVISTO 2026 REVISADO'!$U$86 -> 28468.81 | K87: ='REALIZADO 2025'!I109*'PREVISTO 2026 REVISADO'!$U$86 -> 12181.69 | L87: ='REALIZADO 2025'!J109*'PREVISTO 2026 REVISADO'!$U$86 -> 11368.022 | M87: ='REALIZADO 2025'!K109*'PREVISTO 2026 REVISADO'!$U$86 -> 12092.416 | ... Q87: ='REALIZADO 2025'!O109*'PREVISTO 2026 REVISADO'!$U$86 -> 3925.4798 | R87: 70000 | S87: =R87/12 -> 5833.3333
C88: 2.5.10 Material De Limpeza | F88: ='REALIZADO 2025'!D110*'PREVISTO 2026 REVISADO'!$U$86 -> 1863.7366 | G88: ='REALIZADO 2025'!E110*'PREVISTO 2026 REVISADO'!$U$86 -> 1517.8625 | H88: ='REALIZADO 2025'!F110*'PREVISTO 2026 REVISADO'!$U$86 -> 2064.8155 | I88: ='REALIZADO 2025'!G110*'PREVISTO 2026 REVISADO'!$U$86 -> 2181.124 | J88: ='REALIZADO 2025'!H110*'PREVISTO 2026 REVISADO'!$U$86 -> 1091.8264 | K88: ='REALIZADO 2025'!I110*'PREVISTO 2026 REVISADO'!$U$86 -> 2025.4085 | L88: ='REALIZADO 2025'!J110*'PREVISTO 2026 REVISADO'!$U$86 -> 5704.5505 | M88: ='REALIZADO 2025'!K110*'PREVISTO 2026 REVISADO'!$U$86 -> 2946.691 | ... Q88: ='REALIZADO 2025'!O110*'PREVISTO 2026 REVISADO'!$U$86 -> 1340.735 | R88: 24000 | S88: =R88/12 -> 2000
C89: 2.5.11 Pomar-reciclagem | F89: ='REALIZADO 2025'!D111*'PREVISTO 2026 REVISADO'!$U$86 -> 0 | G89: ='REALIZADO 2025'!E111*'PREVISTO 2026 REVISADO'!$U$86 -> 0 | H89: ='REALIZADO 2025'!F111*'PREVISTO 2026 REVISADO'!$U$86 -> 276.1935 | I89: ='REALIZADO 2025'!G111*'PREVISTO 2026 REVISADO'!$U$86 -> 64.31975 | J89: ='REALIZADO 2025'!H111*'PREVISTO 2026 REVISADO'!$U$86 -> 0 | K89: ='REALIZADO 2025'!I111*'PREVISTO 2026 REVISADO'!$U$86 -> 1661.55 | L89: ='REALIZADO 2025'!J111*'PREVISTO 2026 REVISADO'!$U$86 -> 852.72 | M89: ='REALIZADO 2025'!K111*'PREVISTO 2026 REVISADO'!$U$86 -> 2309.45 | ... Q89: ='REALIZADO 2025'!O111*'PREVISTO 2026 REVISADO'!$U$86 -> 0 | R89: =SUM(F89:Q89) -> 8386.8251 | S89: =R89/12 -> 698.9021
C90: 2.5.12 Açúde | F90: ='REALIZADO 2025'!D112*'PREVISTO 2026 REVISADO'!$U$86 -> 169.6035 | G90: ='REALIZADO 2025'!E112*'PREVISTO 2026 REVISADO'!$U$86 -> 366.32475 | H90: ='REALIZADO 2025'!F112*'PREVISTO 2026 REVISADO'!$U$86 -> 196.72125 | I90: ='REALIZADO 2025'!G112*'PREVISTO 2026 REVISADO'!$U$86 -> 169.6035 | J90: ='REALIZADO 2025'!H112*'PREVISTO 2026 REVISADO'!$U$86 -> 169.6035 | K90: ='REALIZADO 2025'!I112*'PREVISTO 2026 REVISADO'!$U$86 -> 0 | L90: ='REALIZADO 2025'!J112*'PREVISTO 2026 REVISADO'!$U$86 -> 0 | M90: ='REALIZADO 2025'!K112*'PREVISTO 2026 REVISADO'!$U$86 -> 182.5615 | ... Q90: ='REALIZADO 2025'!O112*'PREVISTO 2026 REVISADO'!$U$86 -> 0 | R90: =SUM(F90:Q90) -> 1450.669 | S90: =R90/12 -> 120.88908
C91: 2.5.2 Semasa-esgoto | F91: ='REALIZADO 2025'!D113*'PREVISTO 2026 REVISADO'!$U$86 -> 0 | G91: ='REALIZADO 2025'!E113*'PREVISTO 2026 REVISADO'!$U$86 -> 2439.7824 | H91: ='REALIZADO 2025'!F113*'PREVISTO 2026 REVISADO'!$U$86 -> 2439.7824 | I91: ='REALIZADO 2025'!G113*'PREVISTO 2026 REVISADO'!$U$86 -> 2439.7824 | J91: ='REALIZADO 2025'!H113*'PREVISTO 2026 REVISADO'!$U$86 -> 2439.7824 | K91: ='REALIZADO 2025'!I113*'PREVISTO 2026 REVISADO'!$U$86 -> 2439.7824 | L91: ='REALIZADO 2025'!J113*'PREVISTO 2026 REVISADO'!$U$86 -> 2439.7824 | M91: ='REALIZADO 2025'!K113*'PREVISTO 2026 REVISADO'!$U$86 -> 2439.7824 | ... Q91: ='REALIZADO 2025'!O113*'PREVISTO 2026 REVISADO'!$U$86 -> 2649.4512 | R91: =SUM(F91:Q91) -> 27256.944 | S91: =R91/12 -> 2271.412
C92: 2.5.3 Telefone Fixo | F92: ='REALIZADO 2025'!D114*'PREVISTO 2026 REVISADO'!$U$86 -> 102.8489 | G92: ='REALIZADO 2025'!E114*'PREVISTO 2026 REVISADO'!$U$86 -> 105.09565 | H92: ='REALIZADO 2025'!F114*'PREVISTO 2026 REVISADO'!$U$86 -> 104.92845 | I92: ='REALIZADO 2025'!G114*'PREVISTO 2026 REVISADO'!$U$86 -> 104.92845 | J92: ='REALIZADO 2025'!H114*'PREVISTO 2026 REVISADO'!$U$86 -> 102.8489 | K92: ='REALIZADO 2025'!I114*'PREVISTO 2026 REVISADO'!$U$86 -> 0 | L92: ='REALIZADO 2025'!J114*'PREVISTO 2026 REVISADO'!$U$86 -> 102.8489 | M92: ='REALIZADO 2025'!K114*'PREVISTO 2026 REVISADO'!$U$86 -> 102.8489 | ... Q92: ='REALIZADO 2025'!O114*'PREVISTO 2026 REVISADO'!$U$86 -> 92.2735 | R92: =SUM(F92:Q92) -> 1127.1683 | S92: =R92/12 -> 93.930696
C93: 2.5.4 Telefone Móvel | F93: ='REALIZADO 2025'!D115*'PREVISTO 2026 REVISADO'!$U$86 -> 208.98955 | G93: ='REALIZADO 2025'!E115*'PREVISTO 2026 REVISADO'!$U$86 -> 594.6677 | H93: ='REALIZADO 2025'!F115*'PREVISTO 2026 REVISADO'!$U$86 -> 188.3926 | I93: ='REALIZADO 2025'!G115*'PREVISTO 2026 REVISADO'!$U$86 -> 619.476 | J93: ='REALIZADO 2025'!H115*'PREVISTO 2026 REVISADO'!$U$86 -> 411.88675 | K93: ='REALIZADO 2025'!I115*'PREVISTO 2026 REVISADO'!$U$86 -> 197.4841 | L93: ='REALIZADO 2025'!J115*'PREVISTO 2026 REVISADO'!$U$86 -> 312.36095 | M93: ='REALIZADO 2025'!K115*'PREVISTO 2026 REVISADO'!$U$86 -> 0 | ... Q93: ='REALIZADO 2025'!O115*'PREVISTO 2026 REVISADO'!$U$86 -> 88.62645 | R93: =SUM(F93:Q93) -> 3469.6613 | S93: =R93/12 -> 289.13844
C94: 2.5.5 Tv a Cabo | F94: ='REALIZADO 2025'!D116*'PREVISTO 2026 REVISADO'!$U$86 -> 0 | G94: ='REALIZADO 2025'!E116*'PREVISTO 2026 REVISADO'!$U$86 -> 128.21105 | H94: ='REALIZADO 2025'!F116*'PREVISTO 2026 REVISADO'!$U$86 -> 256.4221 | I94: ='REALIZADO 2025'!G116*'PREVISTO 2026 REVISADO'!$U$86 -> 9.54085 | J94: ='REALIZADO 2025'!H116*'PREVISTO 2026 REVISADO'!$U$86 -> 128.21105 | K94: ='REALIZADO 2025'!I116*'PREVISTO 2026 REVISADO'!$U$86 -> 140.35395 | L94: ='REALIZADO 2025'!J116*'PREVISTO 2026 REVISADO'!$U$86 -> 0 | M94: ='REALIZADO 2025'!K116*'PREVISTO 2026 REVISADO'!$U$86 -> 335.35095 | ... Q94: ='REALIZADO 2025'!O116*'PREVISTO 2026 REVISADO'!$U$86 -> 140.9078 | R94: =SUM(F94:Q94) -> 1560.9269 | S94: =R94/12 -> 130.07725
C95: 2.5.6 Internet | F95: ='REALIZADO 2025'!D117*'PREVISTO 2026 REVISADO'!$U$86 -> 101.25005 | G95: ='REALIZADO 2025'!E117*'PREVISTO 2026 REVISADO'!$U$86 -> 101.25005 | H95: ='REALIZADO 2025'!F117*'PREVISTO 2026 REVISADO'!$U$86 -> 101.25005 | I95: ='REALIZADO 2025'!G117*'PREVISTO 2026 REVISADO'!$U$86 -> 101.25005 | J95: ='REALIZADO 2025'!H117*'PREVISTO 2026 REVISADO'!$U$86 -> 0 | K95: ='REALIZADO 2025'!I117*'PREVISTO 2026 REVISADO'!$U$86 -> 550.70455 | L95: ='REALIZADO 2025'!J117*'PREVISTO 2026 REVISADO'!$U$86 -> 137.7519 | M95: ='REALIZADO 2025'!K117*'PREVISTO 2026 REVISADO'!$U$86 -> 352.46805 | ... Q95: ='REALIZADO 2025'!O117*'PREVISTO 2026 REVISADO'!$U$86 -> 308.93335 | R95: =SUM(F95:Q95) -> 2371.5334 | S95: =R95/12 -> 197.62779
C96: 2.5.7 Hospedagem Site - E-mail | F96: ='REALIZADO 2025'!D118*'PREVISTO 2026 REVISADO'!$U$86 -> 36.4705 | G96: ='REALIZADO 2025'!E118*'PREVISTO 2026 REVISADO'!$U$86 -> 36.4705 | H96: ='REALIZADO 2025'!F118*'PREVISTO 2026 REVISADO'!$U$86 -> 36.4705 | I96: ='REALIZADO 2025'!G118*'PREVISTO 2026 REVISADO'!$U$86 -> 36.4705 | J96: ='REALIZADO 2025'!H118*'PREVISTO 2026 REVISADO'!$U$86 -> 36.4705 | K96: ='REALIZADO 2025'!I118*'PREVISTO 2026 REVISADO'!$U$86 -> 0 | L96: ='REALIZADO 2025'!J118*'PREVISTO 2026 REVISADO'!$U$86 -> 36.4705 | M96: ='REALIZADO 2025'!K118*'PREVISTO 2026 REVISADO'!$U$86 -> 36.4705 | ... Q96: ='REALIZADO 2025'!O118*'PREVISTO 2026 REVISADO'!$U$86 -> 36.4705 | R96: =SUM(F96:Q96) -> 401.1755 | S96: =R96/12 -> 33.431292
C97: 2.5.8 Gás | F97: ='REALIZADO 2025'!D119*'PREVISTO 2026 REVISADO'!$U$86 -> 762.85 | G97: ='REALIZADO 2025'!E119*'PREVISTO 2026 REVISADO'!$U$86 -> 0 | H97: ='REALIZADO 2025'!F119*'PREVISTO 2026 REVISADO'!$U$86 -> 0 | I97: ='REALIZADO 2025'!G119*'PREVISTO 2026 REVISADO'!$U$86 -> 893.475 | J97: ='REALIZADO 2025'!H119*'PREVISTO 2026 REVISADO'!$U$86 -> 0 | K97: ='REALIZADO 2025'!I119*'PREVISTO 2026 REVISADO'!$U$86 -> 0 | L97: ='REALIZADO 2025'!J119*'PREVISTO 2026 REVISADO'!$U$86 -> 0 | M97: ='REALIZADO 2025'!K119*'PREVISTO 2026 REVISADO'!$U$86 -> 893.475 | ... Q97: ='REALIZADO 2025'!O119*'PREVISTO 2026 REVISADO'!$U$86 -> 0 | R97: =SUM(F97:Q97) -> 3443.275 | S97: =R97/12 -> 286.93958
C98: 2.5.9 Combustível | F98: ='REALIZADO 2025'!D120*'PREVISTO 2026 REVISADO'!$U$86 -> 1512.324 | G98: ='REALIZADO 2025'!E120*'PREVISTO 2026 REVISADO'!$U$86 -> 2808.1136 | H98: ='REALIZADO 2025'!F120*'PREVISTO 2026 REVISADO'!$U$86 -> 2170.7262 | I98: ='REALIZADO 2025'!G120*'PREVISTO 2026 REVISADO'!$U$86 -> 2910.837 | J98: ='REALIZADO 2025'!H120*'PREVISTO 2026 REVISADO'!$U$86 -> 2188.1673 | K98: ='REALIZADO 2025'!I120*'PREVISTO 2026 REVISADO'!$U$86 -> 1592.8099 | L98: ='REALIZADO 2025'!J120*'PREVISTO 2026 REVISADO'!$U$86 -> 1730.2378 | M98: ='REALIZADO 2025'!K120*'PREVISTO 2026 REVISADO'!$U$86 -> 1249.6632 | ... Q98: ='REALIZADO 2025'!O120*'PREVISTO 2026 REVISADO'!$U$86 -> 2191.3023 | R98: =SUM(F98:Q98) -> 24092.621 | S98: =R98/12 -> 2007.7184
C99: TOTAL GERAL DESPESAS | F99: =F4 -> #REF! | G99: =G4 -> #REF! | H99: =H4 -> #REF! | I99: =I4 -> #REF! | J99: =J4 -> #REF! | K99: =K4 -> #REF! | L99: =L4 -> #REF! | M99: =M4 -> #REF! | ... Q99: =Q4 -> #REF! | R99: =R86+R78+R38+R22+R5 -> 3409357.7 | S99: =R99/12 -> 284113.14
C101: Previsão Mensal 2025 | E101: 270297.34
...

Sheet REALIZADO 2025
D1: Dezembro | E1: Janeiro | F1: Fevereiro | G1: Março | H1: Abril | I1: Maio | J1: Junho | K1: Julho | L1: Agosto | M1: Setembro | N1: Outubro | O1: Novembro | P1: Total | Q1: Média
A2: 1 Receitas | D2: =SUM(D3:D24) -> 290185.65 | E2: =SUM(E3:E24) -> 308732.3 | F2: =SUM(F3:F24) -> 313677.08 | G2: =SUM(G3:G24) -> 309911.84 | H2: =SUM(H3:H24) -> 316572.56 | I2: =SUM(I3:I24) -> 290740.15 | J2: =SUM(J3:J24) -> 318477.94 | K2: =SUM(K3:K24) -> 363077.67 | ... O2: =SUM(O3:O24) -> 341763.38 | P2: =SUM(D2:O2) -> 3896477.6 | Q2: =P2/12 -> 324706.47
A3: 1.1 Taxa Condominial | D3: 239580.04 | E3: 253005.09 | F3: 265582.35 | G3: 262254.65 | H3: 263648.06 | I3: 255243.67 | J3: 276285.49 | K3: 278926.44 | L3: 289938.72 | M3: 267854.46 | N3: 263900.09 | O3: 284892.08 | P3: =SUM(D3:O3) -> 3201111.1 | Q3: =P3/12 -> 266759.26
A4: 1.10 Rendimentos | D4: 8221.95 | E4: 12462.57 | F4: 8020.57 | G4: 9758.01 | H4: 14865.92 | I4: 131.75 | J4: 1440.44 | K4: 750.81 | L4: 6352.3 | M4: 19987.08 | N4: 6970.17 | O4: 4858.56 | P4: =SUM(D4:O4) -> 93820.13 | Q4: =P4/12 -> 7818.3442
A5: 1.11 Liberação Obra | D5: 0 | E5: 0 | F5: 0 | G5: 0 | H5: 0 | I5: 0 | J5: 0 | K5: 1379.6 | L5: 2950.48 | M5: 1379.6 | N5: 0 | O5: 0 | P5: =SUM(D5:O5) -> 5709.68 | Q5: =P5/12 -> 475.80667
A6: 1.12 Honorário Advocatício | D6: 0 | E6: 0 | F6: 0 | G6: 0 | H6: 0 | I6: 0 | J6: 1458.91 | K6: 0 | L6: 3358.15 | M6: 0 | N6: 0 | O6: 686.92 | P6: =SUM(D6:O6) -> 5503.98 | Q6: =P6/12 -> 458.665
A7: 1.13 Pagamentos a Menor | D7: 0 | E7: 0 | F7: 0 | G7: 0 | H7: -10.85 | I7: 0 | J7: 10.85 | K7: 0 | L7: 0 | M7: 0 | N7: 0 | O7: 0 | P7: =SUM(D7:O7) -> 0 | Q7: =P7/12 -> 0
A8: 1.17 Taxa Salão Bosque | D8: 525 | E8: 1050 | F8: 0 | G8: 1050 | H8: 1050 | I8: 0 | J8: 0 | K8: 1050 | L8: 525 | M8: 0 | N8: 0 | O8: 0 | P8: =SUM(D8:O8) -> 5250 | Q8: =P8/12 -> 437.5
A9: 1.18 Taxa Salão Piscina | D9: 1260 | E9: 1260 | F9: 3150 | G9: 1680 | H9: 1470 | I9: 1680 | J9: 420 | K9: 1680 | L9: 1218 | M9: 1890 | N9: 1470 | O9: 882 | P9: =SUM(D9:O9) -> 18060 | Q9: =P9/12 -> 1505
A10: 1.19 Taxa Salão Pub | D10: 1706.95 | E10: 2126.95 | F10: 0 | G10: 1916.95 | H10: 1496.95 | I10: 1050 | J10: 1890 | K10: 1050 | L10: 1680 | M10: 2520 | N10: 1470 | O10: 1470 | P10: =SUM(D10:O10) -> 18377.8 | Q10: =P10/12 -> 1531.4833
A11: 1.2 Fundo De Reserva | D11: 23926.35 | E11: 25269.43 | F11: 26519.07 | G11: 26186.3 | H11: 26325.65 | I11: 25485.2 | J11: 27589.36 | K11: 27853.49 | L11: 28954.69 | M11: 26746.27 | N11: 26277.64 | O11: 28063.87 | P11: =SUM(D11:O11) -> 319197.32 | Q11: =P11/12 -> 26599.777
A12: 1.20 Taxa Quiosque | D12: 150 | E12: 250 | F12: 150 | G12: 450 | H12: 200 | I12: 250 | J12: 200 | K12: 100 | L12: 100 | M12: 300 | N12: 150 | O12: 0 | P12: =SUM(D12:O12) -> 2300 | Q12: =P12/12 -> 191.66667
A13: 1.21 Taxa Campo Futebol | D13: 0 | E13: 0 | F13: 1800 | G13: 0 | H13: 800 | I13: 1700 | J13: 1900 | K13: 1800 | L13: 1400 | M13: 1400 | N13: 1200 | O13: 1200 | P13: =SUM(D13:O13) -> 13200 | Q13: =P13/12 -> 1100
A14: 1.23 Ressarcimento Utensílios-danos | D14: 317.67 | E14: 447.46 | F14: 419.33 | G14: 489.74 | H14: 439.72 | I14: 21.99 | J14: 111.24 | K14: 631.29 | L14: 196.05 | M14: 326.5 | N14: 57.39 | O14: 0 | P14: =SUM(D14:O14) -> 3458.38 | Q14: =P14/12 -> 288.19833
... A24: 1.9 Atualização Monetária | D24: 164.67 | E24: 211.09 | F24: 253.21 | G24: 64.91 | H24: 75.54 | I24: 0 | J24: 297.41 | K24: 23.96 | L24: 688.42 | M24: 50.05 | N24: 0 | O24: 49.94 | P24: =SUM(D24:O24) -> 1879.2 | Q24: =P24/12 -> 156.6
A25: TOTAL GERAL RECEITAS | D25: =D2 -> 290185.65 | E25: =E2 -> 308732.3 | F25: =F2 -> 313677.08 | G25: =G2 -> 309911.84 | H25: =H2 -> 316572.56 | I25: =I2 -> 290740.15 | J25: =J2 -> 318477.94 | K25: =K2 -> 363077.67 | ... O25: =O2 -> 341763.38 | P25: =SUM(D25:O25) -> 3896477.6 | Q25: =P25/12 -> 324706.47
A26: 2 Despesas | D26: =D27+D46+D63+D98+D108+D121 -> 308825.79 | E26: =E27+E46+E63+E98+E108+E121 -> 256130.14 | F26: =F27+F46+F63+F98+F108+F121 -> 318039.96 | G26: =G27+G46+G63+G98+G108+G121 -> 281471.1 | H26: =H27+H46+H63+H98+H108+H121 -> 308302.8 | I26: =I27+I46+I63+I98+I108+I121 -> 334819.06 | J26: =J27+J46+J63+J98+J108+J121 -> 504020.49 | K26: =K27+K46+K63+K98+K108+K121 -> 338176.55 | ... O26: =O27+O46+O63+O98+O108+O121 -> 310388.35 | P26: =SUM(D26:O26) -> 4191740.1 | Q26: =P26/12 -> 349311.67
A27: 2.1 Administrativas | D27: =SUM(D28:D45) -> 8428.59 | E27: =SUM(E28:E45) -> 7532.59 | F27: =SUM(F28:F45) -> 79958.24 | G27: =SUM(G28:G45) -> 12361.98 | H27: =SUM(H28:H45) -> 9069.81 | I27: =SUM(I28:I45) -> 10392.02 | J27: =SUM(J28:J45) -> 43773.35 | K27: =SUM(K28:K45) -> 9965.99 | ... O27: =SUM(O28:O45) -> 8987.82 | P27: =SUM(D27:O27) -> 224244.8 | Q27: =P27/12 -> 18687.067
A28: 2.1.1 Despesas Bancárias | D28: 553.58 | E28: 338.96 | F28: 78.99 | G28: 59.39 | H28: 97.22 | I28: 37.9 | J28: 32953.02 | K28: 31.9 | L28: 31.9 | M28: 32.9 | N28: 29.9 | O28: 30.16 | P28: =SUM(D28:O28) -> 34275.82 | Q28: =P28/12 -> 2856.3183
A29: 2.1.11 Reuniões-treinamentos | D29: 0 | E29: 0 | F29: 187.89 | G29: 0 | H29: 0 | I29: 0 | J29: 398 | K29: 168.94 | L29: 0 | M29: 0 | N29: 406.4 | O29: 0 | P29: =SUM(D29:O29) -> 1161.23 | Q29: =P29/12 -> 96.769167
A30: 2.1.12 Certificado Digital | D30: 0 | E30: 0 | F30: 0 | G30: 0 | H30: 179.57 | I30: 0 | J30: 0 | K30: 0 | L30: 0 | M30: 200 | N30: 0 | O30: 0 | P30: =SUM(D30:O30) -> 379.57 | Q30: =P30/12 -> 31.630833
A31: 2.1.14 Outros-não Previstos | D31: 0 | E31: 0 | F31: 0 | G31: 2500 | H31: 0 | I31: 0 | J31: 0 | K31: 0 | L31: 0 | M31: 0 | N31: 0 | O31: 0 | P31: =SUM(D31:O31) -> 2500 | Q31: =P31/12 -> 208.33333
A32: 2.1.16 Multa | D32: 0 | E32: 0 | F32: 0 | G32: 1408.64 | H32: 0 | I32: 0 | J32: 0 | K32: 0 | L32: 0 | M32: 0 | N32: 0 | O32: 0 | P32: =SUM(D32:O32) -> 1408.64 | Q32: =P32/12 -> 117.38667
A33: 2.1.17 Juros | D33: 0 | E33: 0 | F33: 0 | G33: 0 | H33: 0 | I33: 0 | J33: 0 | K33: 0 | L33: 0 | M33: 0 | N33: 1.65 | O33: 0 | P33: =SUM(D33:O33) -> 1.65 | Q33: =P33/12 -> 0.1375
A34: 2.1.19 Alvará De Funcionamento | D34: 0 | E34: 0 | F34: 0 | G34: 0 | H34: 0 | I34: 594.72 | J34: 0 | K34: 0 | L34: 0 | M34: 0 | N34: 0 | O34: 0 | P34: =SUM(D34:O34) -> 594.72 | Q34: =P34/12 -> 49.56
A35: 2.1.2 Material De Expediente-correio | D35: 356.15 | E35: 350 | F35: 896.7 | G35: 488.45 | H35: 306.95 | I35: 386 | J35: 1086.8 | K35: 388.95 | L35: 939.25 | M35: 880.2 | N35: 534.1 | O35: 314.6 | P35: =SUM(D35:O35) -> 6928.15 | Q35: =P35/12 -> 577.34583
A36: 2.1.21 Sistema De Reservas On-line | D36: 500 | E36: 0 | F36: 500 | G36: 500 | H36: 500 | I36: 500 | J36: 0 | K36: 500 | L36: 500 | M36: 500 | N36: 500 | O36: 0 | P36: =SUM(D36:O36) -> 4500 | Q36: =P36/12 -> 375
A37: 2.1.22 Material Expediente- Impressões/Digitalizações/Encadernação/Envelopes | D37: 0 | E37: 0 | F37: 0 | G37: 0 | H37: 0 | I37: 0 | J37: 0 | K37: 0 | L37: 0 | M37: 0 | N37: 0 | O37: 1357.35 | P37: =SUM(D37:O37) -> 1357.35 | Q37: =P37/12 -> 113.1125
A38: 2.1.3 Honorário Síndico | D38: 4540 | E38: 4540 | F38: 4814 | G38: 4814 | H38: 4814 | I38: 4814 | J38: 4827 | K38: 4827 | L38: 4826 | M38: 4827 | N38: 4827 | O38: 4826 | P38: =SUM(D38:O38) -> 57296 | Q38: =P38/12 -> 4774.6667
A39: 2.1.4 Inss-ir-síndico | D39: 2237.23 | E39: 2244.23 | F39: 2472.44 | G39: 2472.7 | H39: 2472.04 | I39: 1964.59 | J39: 2459.71 | K39: 2459.71 | L39: 2459.71 | M39: 2459.71 | N39: 2459.71 | O39: 2459.71 | P39: =SUM(D39:O39) -> 28621.49 | Q39: =P39/12 -> 2385.1242
... A45: 2.1.9 Documentação Veículo | D45: 0 | E45: 0 | F45: 0 | G45: 0 | H45: 0 | I45: 0 | J45: 0 | K45: 0 | L45: 3122.13 | M45: 0 | N45: 0 | O45: 0 | P45: =SUM(D45:O45) -> 3122.13 | Q45: =P45/12 -> 260.1775
A46: 2.2 Colaboradores | D46: =SUM(D47:D62) -> 143203.01 | E46: =SUM(E47:E62) -> 103883.78 | F46: =SUM(F47:F62) -> 87697.03 | G46: =SUM(G47:G62) -> 120308.26 | H46: =SUM(H47:H62) -> 92354.62 | I46: =SUM(I47:I62) -> 116613.08 | J46: =SUM(J47:J62) -> 115414.88 | K46: =SUM(K47:K62) -> 93230.86 | ... O46: =SUM(O47:O62) -> 125280.71 | P46: =SUM(D46:O46) -> 1310755.2 | Q46: =P46/12 -> 109229.6
A47: 2.2.1 Salários Líquidos | D47: 48667 | E47: 46607 | F47: 44242 | G47: 47784 | H47: 44042 | I47: 47750.4 | J47: 49031 | K47: 43835 | L47: 44045.8 | M47: 48132 | N47: 53383 | O47: 53417 | P47: =SUM(D47:O47) -> 570936.2 | Q47: =P47/12 -> 47578.017
A48: 2.2.10 Benefícios Saúde-cesta Básica-copa | D48: 21530.09 | E48: 13983.37 | F48: 6422.33 | G48: 21892.53 | H48: 15721.52 | I48: 19997.78 | J48: 14866.39 | K48: 15889.35 | L48: 15336.89 | M48: 16278.65 | N48: 16677.07 | O48: 16518.93 | P48: =SUM(D48:O48) -> 195114.9 | Q48: =P48/12 -> 16259.575
A49: 2.2.11 Uniforme-epi | D49: 71.9 | E49: 784.64 | F49: 317.51 | G49: 489.3 | H49: 1665.5 | I49: 1753.5 | J49: 499.8 | K49: 0 | L49: 370.91 | M49: 0 | N49: 1272.65 | O49: 1674.35 | P49: =SUM(D49:O49) -> 8900.06 | Q49: =P49/12 -> 741.67167
A50: 2.2.12 Laudos Médicos-exames | D50: 246.43 | E50: 243.75 | F50: 269.97 | G50: 258.13 | H50: 218.17 | I50: 229.36 | J50: 230 | K50: 230 | L50: 390.93 | M50: 293.19 | N50: 300.61 | O50: 285.76 | P50: =SUM(D50:O50) -> 3196.3 | Q50: =P50/12 -> 266.35833
A51: 2.2.13 Cursos-treinamentos | D51: 0 | E51: 0 | F51: 0 | G51: 0 | H51: 0 | I51: 0 | J51: 0 | K51: 0 | L51: 0 | M51: 0 | N51: 1993.7 | O51: 47.28 | P51: =SUM(D51:O51) -> 2040.98 | Q51: =P51/12 -> 170.08167
A52: 2.2.14 Brindes-confraternizações | D52: 2808.9 | E52: 3348.4 | F52: 1478.6 | G52: 730 | H52: 0 | I52: 1564.87 | J52: 0 | K52: 0 | L52: 0 | M52: 528.88 | N52: 0 | O52: 0 | P52: =SUM(D52:O52) -> 10459.65 | Q52: =P52/12 -> 871.6375
A53: 2.2.15 Seguro De Vida | D53: 295.92 | E53: 295.92 | F53: 295.92 | G53: 295.92 | H53: 308.15 | I53: 308.15 | J53: 308.15 | K53: 308.15 | L53: 308.15 | M53: 308.15 | N53: 494.94 | O53: 494.94 | P53: =SUM(D53:O53) -> 4022.46 | Q53: =P53/12 -> 335.205
A54: 2.2.16 Contribuição Sindical Empregados | D54: 300 | E54: 300 | F54: 340 | G54: 320 | H54: 320 | I54: 300 | J54: 280 | K54: 300 | L54: 300 | M54: 300 | N54: 0 | O54: 0 | P54: =SUM(D54:O54) -> 3060 | Q54: =P54/12 -> 255
A55: 2.2.17 Contribuição Sindical Patronal | D55: 0 | E55: 0 | F55: 0 | G55: 0 | H55: 0 | I55: 0 | J55: 0 | K55: 0 | L55: 0 | M55: 0 | N55: 320 | O55: 340 | P55: =SUM(D55:O55) -> 660 | Q55: =P55/12 -> 55
A56: 2.2.19 Jovem Aprendiz | D56: 166 | E56: 166 | F56: 166 | G56: 166 | H56: 0 | I56: 0 | J56: 0 | K56: 0 | L56: 0 | M56: 0 | N56: 0 | O56: 0 | P56: =SUM(D56:O56) -> 664 | Q56: =P56/12 -> 55.333333
A57: 2.2.20 Tributos Dctf-web | D57: 24079.08 | E57: 23703.9 | F57: 22425.01 | G57: 22462.9 | H57: 24237.91 | I57: 25460.94 | J57: 26978.98 | K57: 26317.08 | L57: 24656.17 | M57: 25077.3 | N57: 25147.79 | O57: 27212.85 | P57: =SUM(D57:O57) -> 297759.91 | Q57: =P57/12 -> 24813.326
A58: 2.2.3 Fgts | D58: 5500.01 | E58: 6239.22 | F58: 4045.2 | G58: 4127.78 | H58: 4464.37 | I58: 4619.73 | J58: 4877.04 | K58: 5190.28 | L58: 5347.21 | M58: 5530.76 | N58: 5154.19 | O58: 5748.6 | P58: =SUM(D58:O58) -> 60844.39 | Q58: =P58/12 -> 5070.3658
... A62: 2.2.9 Vale Transporte | D62: 756 | E62: 1404 | F62: 1719 | G62: 99 | H62: 1377 | I62: 1530.6 | J62: 1242 | K62: 1161 | L62: 963 | M62: 1116 | N62: 0 | O62: 0 | P62: =SUM(D62:O62) -> 11367.6 | Q62: =P62/12 -> 947.3
A63: 2.3 Manutenção | D63: =D64+D75+D88+D92 -> 46933.69 | E63: =E64+E75+E88+E92 -> 38441.13 | F63: =F64+F75+F88+F92 -> 43106.75 | G63: =G64+G75+G88+G92 -> 55739.43 | H63: =H64+H75+H88+H92 -> 74070.3 | I63: =I64+I75+I88+I92 -> 80019.7 | J63: =J64+J75+J88+J92 -> 56343.06 | K63: =K64+K75+K88+K92 -> 49242.39 | ... O63: =O64+O75+O88+O92 -> 41050.25 | P63: =SUM(D63:O63) -> 639747.57 | Q63: =P63/12 -> 53312.298
A64: 2.3.1 Areas De Lazer | D64: =SUM(D65:D74) -> 11409.97 | E64: =SUM(E65:E74) -> 5970.49 | F64: =SUM(F65:F74) -> 4413.72 | G64: =SUM(G65:G74) -> 14024.14 | H64: =SUM(H65:H74) -> 53117.58 | I64: =SUM(I65:I74) -> 58341.08 | J64: =SUM(J65:J74) -> 32347.01 | K64: =SUM(K65:K74) -> 21900.84 | ... O64: =SUM(O65:O74) -> 24398.15 | P64: =SUM(D64:O64) -> 298471.52 | Q64: =P64/12 -> 24872.627
A65: 2.3.1.1 Salão De Festas Bosque | D65: 1483.91 | E65: 450 | F65: 1246 | G65: 734.59 | H65: 7759.9 | I65: 9264 | J65: 1586 | K65: 4959.3 | L65: 312 | M65: 1589.41 | N65: 1352.36 | O65: 1415.26 | P65: =SUM(D65:O65) -> 32152.73 | Q65: =P65/12 -> 2679.3942
A66: 2.3.1.10 Quadras-campo | D66: 143.95 | E66: 0 | F66: 0 | G66: 9047.84 | H66: 160.5 | I66: 8128.38 | J66: 1062.32 | K66: 5953.11 | L66: 596.48 | M66: 620.97 | N66: 0 | O66: 583.69 | P66: =SUM(D66:O66) -> 26297.24 | Q66: =P66/12 -> 2191.4367
A67: 2.3.1.12 Churrasqueira Costela Fogo De Chão | D67: 0 | E67: 0 | F67: 0 | G67: 0 | H67: 0 | I67: 448.8 | J67: 0 | K67: 0 | L67: 0 | M67: 0 | N67: 0 | O67: 1655.62 | P67: =SUM(D67:O67) -> 2104.42 | Q67: =P67/12 -> 175.36833
A68: 2.3.1.2 Salão De Festas Piscina | D68: 3056.35 | E68: 470 | F68: 745 | G68: 1668.95 | H68: 38084.27 | I68: 32052.83 | J68: 21136.71 | K68: 5285.77 | L68: 4280.74 | M68: 24962.31 | N68: 252.5 | O68: 8391.75 | P68: =SUM(D68:O68) -> 140387.18 | Q68: =P68/12 -> 11698.932
A69: 2.3.1.3 Salão De Festas Pub | D69: 584.5 | E69: 464.15 | F69: 184.14 | G69: 60 | H69: 3000 | I69: 5400 | J69: 0 | K69: 383.95 | L69: 700.29 | M69: 804.07 | N69: 5468.35 | O69: 6667.1 | P69: =SUM(D69:O69) -> 23716.55 | Q69: =P69/12 -> 1976.3792
A70: 2.3.1.4 Quiosque | D70: 530.64 | E70: 0 | F70: 0 | G70: 0 | H70: 0 | I70: 0 | J70: 0 | K70: 0 | L70: 1915.39 | M70: 1283.13 | N70: 1533.9 | O70: 260 | P70: =SUM(D70:O70) -> 5523.06 | Q70: =P70/12 -> 460.255
A71: 2.3.1.5 Espaço Juvenil | D71: 0 | E71: 0 | F71: 0 | G71: 0 | H71: 0 | I71: 0 | J71: 1378 | K71: 520 | L71: 6282.49 | M71: 1609.53 | N71: 1615.94 | O71: 653.92 | P71: =SUM(D71:O71) -> 12059.88 | Q71: =P71/12 -> 1004.99
A72: 2.3.1.6 Piscina | D72: 5263.97 | E72: 4398.9 | F72: 1320.68 | G72: 1202.33 | H72: 1903.11 | I72: 241.88 | J72: 194.04 | K72: 2219 | L72: 2112.04 | M72: 1344.99 | N72: 1026.17 | O72: 3849.91 | P72: =SUM(D72:O72) -> 25077.02 | Q72: =P72/12 -> 2089.7517
A73: 2.3.1.7 Playground | D73: 334.65 | E73: 57.9 | F73: 57.9 | G73: 57.9 | H73: 57.9 | I73: 507.9 | J73: 3296.8 | K73: 246 | L73: 403.63 | M73: 9132 | N73: 398.93 | O73: 0 | P73: =SUM(D73:O73) -> 14551.51 | Q73: =P73/12 -> 1212.6258
A74: 2.3.1.8 Academia | D74: 12 | E74: 129.54 | F74: 860 | G74: 1252.53 | H74: 2151.9 | I74: 2297.29 | J74: 3693.14 | K74: 2333.71 | L74: 1519.05 | M74: 652.66 | N74: 779.21 | O74: 920.9 | P74: =SUM(D74:O74) -> 16601.93 | Q74: =P74/12 -> 1383.4942
A75: 2.3.2 Estrutura | D75: =SUM(D76:D87) -> 12507.12 | E75: =SUM(E76:E87) -> 14286.26 | F75: =SUM(F76:F87) -> 18337.96 | G75: =SUM(G76:G87) -> 16029.18 | H75: =SUM(H76:H87) -> 10434.39 | I75: =SUM(I76:I87) -> 9970.96 | J75: =SUM(J76:J87) -> 13934.77 | K75: =SUM(K76:K87) -> 8299.52 | ... O75: =SUM(O76:O87) -> 11571.33 | P75: =SUM(D75:O75) -> 169903.66 | Q75: =P75/12 -> 14158.638
A76: 2.3.2.1 Areas e Instalações Comuns | D76: 1149.96 | E76: 5424.34 | F76: 1760.22 | G76: 1633.91 | H76: 1082.03 | I76: 392.83 | J76: 2776.34 | K76: 1272.49 | L76: 2465.4 | M76: 1917.67 | N76: 554.24 | O76: 1370 | P76: =SUM(D76:O76) -> 21799.43 | Q76: =P76/12 -> 1816.6192
A77: 2.3.2.10 Ruas-meio Fio-lombada-sinalização | D77: 0 | E77: 2322.99 | F77: 3610.64 | G77: 1804.19 | H77: 972.5 | I77: 3714.82 | J77: 2960 | K77: 1630 | L77: 1630 | M77: 4004.91 | N77: 3024.04 | O77: 2179.59 | P77: =SUM(D77:O77) -> 27853.68 | Q77: =P77/12 -> 2321.14
A78: 2.3.2.12 Pergola | D78: 850 | E78: 525 | F78: 0 | G78: 0 | H78: 0 | I78: 0 | J78: 0 | K78: 0 | L78: 0 | M78: 0 | N78: 0 | O78: 0 | P78: =SUM(D78:O78) -> 1375 | Q78: =P78/12 -> 114.58333
A79: 2.3.2.13 Dog Park | D79: 0 | E79: 0 | F79: 0 | G79: 0 | H79: 0 | I79: 0 | J79: 0 | K79: 0 | L79: 40.74 | M79: 0 | N79: 0 | O79: 0 | P79: =SUM(D79:O79) -> 40.74 | Q79: =P79/12 -> 3.395
A80: 2.3.2.2 Elétrica- Iluminação | D80: 1990.92 | E80: 1699.12 | F80: 2553.62 | G80: 5208.7 | H80: 3600.71 | I80: 3485.25 | J80: 356.74 | K80: 926.5 | L80: 4132.44 | M80: 5942.33 | N80: 6744.12 | O80: 4351.6 | P80: =SUM(D80:O80) -> 40992.05 | Q80: =P80/12 -> 3416.0042
A81: 2.3.2.3 Instalações Hidráulicas- Esgoto | D81: 0 | E81: 0 | F81: 0 | G81: 100 | H81: 0 | I81: 0 | J81: 0 | K81: 0 | L81: 0 | M81: 0 | N81: 0 | O81: 54.32 | P81: =SUM(D81:O81) -> 154.32 | Q81: =P81/12 -> 12.86
A82: 2.3.2.4 Jardim | D82: 7360.44 | E82: 2596.25 | F82: 975 | G82: 2552 | H82: 2664 | I82: 800 | J82: 840 | K82: 1577.5 | L82: 2219.25 | M82: 1821.66 | N82: 1041.66 | O82: 1929.36 | P82: =SUM(D82:O82) -> 26377.12 | Q82: =P82/12 -> 2198.0933
A83: 2.3.2.5 Portaria Social | D83: 1100 | E83: 1417.76 | F83: 2030.88 | G83: 2168.03 | H83: 1428.99 | I83: 1433.03 | J83: 1835.64 | K83: 1923.03 | L83: 7987.35 | M83: 3944.95 | N83: 2337.03 | O83: 1686.46 | P83: =SUM(D83:O83) -> 29293.15 | Q83: =P83/12 -> 2441.0958
A84: 2.3.2.6 Portaria De Serviço | D84: 0 | E84: 0 | F84: 407.6 | G84: 240 | H84: 0 | I84: 74.9 | J84: 1200 | K84: 700 | L84: 110 | M84: 0 | N84: 0 | O84: 0 | P84: =SUM(D84:O84) -> 2732.5 | Q84: =P84/12 -> 227.70833
A85: 2.3.2.7 Prédio-sala Administrativo-garagem | D85: 55.8 | E85: 300.8 | F85: 0 | G85: 743.35 | H85: 22.21 | I85: 0 | J85: 3604 | K85: 270 | L85: 481.48 | M85: 1871 | N85: 2009.9 | O85: 0 | P85: =SUM(D85:O85) -> 9358.54 | Q85: =P85/12 -> 779.87833
A86: 2.3.2.8 Poço Artesiano | D86: 0 | E86: 0 | F86: 7000 | G86: 1579 | H86: 0 | I86: 0 | J86: 0 | K86: 0 | L86: 252 | M86: 0 | N86: 0 | O86: 0 | P86: =SUM(D86:O86) -> 8831 | Q86: =P86/12 -> 735.91667
A87: 2.3.2.9 Cerca Muro | D87: 0 | E87: 0 | F87: 0 | G87: 0 | H87: 663.95 | I87: 70.13 | J87: 362.05 | K87: 0 | L87: 0 | M87: 0 | N87: 0 | O87: 0 | P87: =SUM(D87:O87) -> 1096.13 | Q87: =P87/12 -> 91.344167
A88: 2.3.3 Máquinas e Equipamentos | D88: =SUM(D89:D91) -> 15437.5 | E88: =SUM(E89:E91) -> 14100.3 | F88: =SUM(F89:F91) -> 12599.15 | G88: =SUM(G89:G91) -> 15161.5 | H88: =SUM(H89:H91) -> 6115 | I88: =SUM(I89:I91) -> 9622 | J88: =SUM(J89:J91) -> 6726 | K88: =SUM(K89:K91) -> 7852.67 | ... O88: =SUM(O89:O91) -> 1759.9 | P88: =SUM(D88:O88) -> 100629.35 | Q88: =P88/12 -> 8385.7792
A89: 2.3.3.1 Sistema De Segurança | D89: 5780.5 | E89: 5780.5 | F89: 5110 | G89: 7605 | H89: 6115 | I89: 5700 | J89: 3276 | K89: 4800 | L89: 1140 | M89: 4894 | N89: 0 | O89: 0 | P89: =SUM(D89:O89) -> 50201 | Q89: =P89/12 -> 4183.4167
A90: 2.3.3.2 Aparelhos-máquinas-ferramentas-equipamentos | D90: 7041 | E90: 4361.8 | F90: 5047.95 | G90: 6706.5 | H90: 0 | I90: 2012 | J90: 580 | K90: 1784.67 | L90: 2684.67 | M90: 1856.66 | N90: 0 | O90: 1209.9 | P90: =SUM(D90:O90) -> 33285.15 | Q90: =P90/12 -> 2773.7625
A91: 2.3.3.3 Veículo-moto | D91: 2616 | E91: 3958 | F91: 2441.2 | G91: 850 | H91: 0 | I91: 1910 | J91: 2870 | K91: 1268 | L91: 0 | M91: 0 | N91: 680 | O91: 550 | P91: =SUM(D91:O91) -> 17143.2 | Q91: =P91/12 -> 1428.6
A92: 2.3.4 Serviços Especializados | D92: =SUM(D93:D97) -> 7579.1 | E92: =SUM(E93:E97) -> 4084.08 | F92: =SUM(F93:F97) -> 7755.92 | G92: =SUM(G93:G97) -> 10524.61 | H92: =SUM(H93:H97) -> 4403.33 | I92: =SUM(I93:I97) -> 2085.66 | J92: =SUM(J93:J97) -> 3335.28 | K92: =SUM(K93:K97) -> 11189.36 | ... O92: =SUM(O93:O97) -> 3320.87 | P92: =SUM(D92:O92) -> 70743.04 | Q92: =P92/12 -> 5895.2533
A93: 2.3.4.1 Extintores | D93: 870 | E93: 0 | F93: 0 | G93: 0 | H93: 0 | I93: 0 | J93: 0 | K93: 0 | L93: 0 | M93: 0 | N93: 105 | O93: 0 | P93: =SUM(D93:O93) -> 975 | Q93: =P93/12 -> 81.25
A94: 2.3.4.2 Dedetização-desinsetização-desratização | D94: 720 | E94: 656.64 | F94: 783.36 | G94: 1310 | H94: 656.64 | I94: 783.36 | J94: 1735.28 | K94: 1507.36 | L94: 1537.36 | M94: 750 | N94: 684 | O94: 816 | P94: =SUM(D94:O94) -> 11940 | Q94: =P94/12 -> 995
A95: 2.3.4.3 Fossa-caixa De Gordura | D95: 2300 | E95: 522 | F95: 428 | G95: 861.91 | H95: 448.99 | I95: 0 | J95: 400 | K95: 882 | L95: 168 | M95: 650.01 | N95: 882.76 | O95: 494.57 | P95: =SUM(D95:O95) -> 8038.24 | Q95: =P95/12 -> 669.85333
A96: 2.3.4.4 Reservatórios De Água | D96: 1409.1 | E96: 505.44 | F96: 5344.56 | G96: 5872.7 | H96: 2097.7 | I96: 102.3 | J96: 0 | K96: 7600 | L96: 5500 | M96: 398 | N96: 1789.7 | O96: 410.3 | P96: =SUM(D96:O96) -> 31029.8 | Q96: =P96/12 -> 2585.8167
A97: 2.3.4.5 Análise De Água | D97: 2280 | E97: 2400 | F97: 1200 | G97: 2480 | H97: 1200 | I97: 1200 | J97: 1200 | K97: 1200 | L97: 1200 | M97: 1200 | N97: 1600 | O97: 1600 | P97: =SUM(D97:O97) -> 18760 | Q97: =P97/12 -> 1563.3333
A98: 2.4 Serviços | D98: =SUM(D99:D107) -> 70873.11 | E98: =SUM(E99:E107) -> 66786.33 | F98: =SUM(F99:F107) -> 63638.83 | G98: =SUM(G99:G107) -> 60444.29 | H98: =SUM(H99:H107) -> 79631.73 | I98: =SUM(I99:I107) -> 76850.96 | J98: =SUM(J99:J107) -> 80703.5 | K98: =SUM(K99:K107) -> 83030.35 | ... O98: =SUM(O99:O107) -> 76023.85 | P98: =SUM(D98:O98) -> 907458.48 | Q98: =P98/12 -> 75621.54
A99: 2.4.1 Honorários Advocatícios | D99: 3940 | E99: 1970 | F99: 0 | G99: 0 | H99: 6380 | I99: 2205 | J99: 2205 | K99: 2205 | L99: 2205 | M99: 5105.21 | N99: 2205 | O99: 2205 | P99: =SUM(D99:O99) -> 30625.21 | Q99: =P99/12 -> 2552.1008
A100: 2.4.2 Honorários Engenharia | D100: 2824 | E100: 3036 | F100: 3036 | G100: 3036 | H100: 3036 | I100: 3036 | J100: 3036 | K100: 3036 | L100: 3036 | M100: 3036 | N100: 3036 | O100: 3036 | P100: =SUM(D100:O100) -> 36220 | Q100: =P100/12 -> 3018.3333
A101: 2.4.3 Honorários Contábeis | D101: 4086.38 | E101: 3485.21 | F101: 2502.19 | G101: 2576.53 | H101: 2576.52 | I101: 3378.15 | J101: 2672 | K101: 3113 | L101: 2741 | M101: 2830 | N101: 3106 | O101: 4234.5 | P101: =SUM(D101:O101) -> 37301.48 | Q101: =P101/12 -> 3108.4567
A102: 2.4.4 Segurança- Serviço Vigilância | D102: 56426.23 | E102: 56448.62 | F102: 56448.62 | G102: 52531.76 | H102: 66256.21 | I102: 65470.97 | J102: 61348.35 | K102: 61348.35 | L102: 61348.35 | M102: 61348.36 | N102: 61348.36 | O102: 61348.35 | P102: =SUM(D102:O102) -> 721672.53 | Q102: =P102/12 -> 60139.377
A103: 2.4.5 Cobertura De Férias | D103: 0 | E103: 0 | F103: 0 | G103: 0 | H103: 0 | I103: 0 | J103: 0 | K103: 4975 | L103: 600 | M103: 0 | N103: 4500 | O103: 0 | P103: =SUM(D103:O103) -> 10075 | Q103: =P103/12 -> 839.58333
A104: 2.4.6 Serviços Extras | D104: 2400 | E104: 650 | F104: 455.52 | G104: 300 | H104: 0 | I104: 2070.84 | J104: 714.4 | K104: 1500 | L104: 0 | M104: 400 | N104: 0 | O104: 400 | P104: =SUM(D104:O104) -> 8890.76 | Q104: =P104/12 -> 740.89667
A105: 2.4.60 Outros | D105: 0 | E105: 0 | F105: 0 | G105: 0 | H105: 0 | I105: 690 | J105: 0 | K105: 0 | L105: 0 | M105: 0 | N105: 0 | O105: 0 | P105: =SUM(D105:O105) -> 690 | Q105: =P105/12 -> 57.5
A106: 2.4.7 Eletro-eletrônica-comunicação-sistemas | D106: 1196.5 | E106: 1196.5 | F106: 1196.5 | G106: 0 | H106: 1260 | I106: 0 | J106: 5566 | K106: 0 | L106: 7545 | M106: 4800 | N106: 4800 | O106: 4800 | P106: =SUM(D106:O106) -> 32360.5 | Q106: =P106/12 -> 2696.7083
A107: 2.4.9 Honorários Periciais e De Assistentes | D107: 0 | E107: 0 | F107: 0 | G107: 2000 | H107: 123 | I107: 0 | J107: 5161.75 | K107: 6853 | L107: 5161.75 | M107: 5161.75 | N107: 5161.75 | O107: 0 | P107: =SUM(D107:O107) -> 29623 | Q107: =P107/12 -> 2468.5833
A108: 2.5 Consumíveis | D108: =SUM(D109:D120) -> 15220.32 | E108: =SUM(E109:E120) -> 20958.13 | F108: =SUM(F109:F120) -> 20347.51 | G108: =SUM(G109:G120) -> 9120.39 | H108: =SUM(H109:H120) -> 33528.81 | I108: =SUM(I109:I120) -> 19894.53 | J108: =SUM(J109:J120) -> 21707.89 | K108: =SUM(K109:K120) -> 21953.28 | ... O108: =SUM(O109:O120) -> 10310.22 | P108: =SUM(D108:O108) -> 229071.58 | Q108: =P108/12 -> 19089.298
A109: 2.5.1 Energia Elétrica | D109: 10667.14 | E109: 13209.06 | F109: 12849.23 | G109: 0 | H109: 27242.88 | I109: 11657.12 | J109: 10878.49 | K109: 11571.69 | L109: 9662.11 | M109: 10993.88 | N109: 10260.36 | O109: 3756.44 | P109: =SUM(D109:O109) -> 132748.4 | Q109: =P109/12 -> 11062.367
A110: 2.5.10 Material De Limpeza | D110: 1783.48 | E110: 1452.5 | F110: 1975.9 | G110: 2087.2 | H110: 1044.81 | I110: 1938.19 | J110: 5458.9 | K110: 2819.8 | L110: 0 | M110: 3379.42 | N110: 2706.87 | O110: 1283 | P110: =SUM(D110:O110) -> 25930.07 | Q110: =P110/12 -> 2160.8392
A111: 2.5.11 Pomar-reciclagem | D111: 0 | E111: 0 | F111: 264.3 | G111: 61.55 | H111: 0 | I111: 1590 | J111: 816 | K111: 2210 | L111: 1480 | M111: 123.82 | N111: 1480 | O111: 0 | P111: =SUM(D111:O111) -> 8025.67 | Q111: =P111/12 -> 668.80583
A112: 2.5.12 Açúde | D112: 162.3 | E112: 350.55 | F112: 188.25 | G112: 162.3 | H112: 162.3 | I112: 0 | J112: 0 | K112: 174.7 | L112: 187.8 | M112: 0 | N112: 0 | O112: 0 | P112: =SUM(D112:O112) -> 1388.2 | Q112: =P112/12 -> 115.68333
A113: 2.5.2 Semasa-esgoto | D113: 0 | E113: 2334.72 | F113: 2334.72 | G113: 2334.72 | H113: 2334.72 | I113: 2334.72 | J113: 2334.72 | K113: 2334.72 | L113: 2334.72 | M113: 2334.72 | N113: 2535.36 | O113: 2535.36 | P113: =SUM(D113:O113) -> 26083.2 | Q113: =P113/12 -> 2173.6
A114: 2.5.3 Telefone Fixo | D114: 98.42 | E114: 100.57 | F114: 100.41 | G114: 100.41 | H114: 98.42 | I114: 0 | J114: 98.42 | K114: 98.42 | L114: 98.42 | M114: 98.42 | N114: 98.42 | O114: 88.3 | P114: =SUM(D114:O114) -> 1078.63 | Q114: =P114/12 -> 89.885833
A115: 2.5.4 Telefone Móvel | D115: 199.99 | E115: 569.06 | F115: 180.28 | G115: 592.8 | H115: 394.15 | I115: 188.98 | J115: 298.91 | K115: 0 | L115: 199.99 | M115: 189.21 | N115: 422.07 | O115: 84.81 | P115: =SUM(D115:O115) -> 3320.25 | Q115: =P115/12 -> 276.6875
A116: 2.5.5 Tv a Cabo | D116: 0 | E116: 122.69 | F116: 245.38 | G116: 9.13 | H116: 122.69 | I116: 134.31 | J116: 0 | K116: 320.91 | L116: 134.08 | M116: 134.84 | N116: 134.84 | O116: 134.84 | P116: =SUM(D116:O116) -> 1493.71 | Q116: =P116/12 -> 124.47583
A117: 2.5.6 Internet | D117: 96.89 | E117: 96.89 | F117: 96.89 | G117: 96.89 | H117: 0 | I117: 526.99 | J117: 131.82 | K117: 337.29 | L117: 92.83 | M117: 297.3 | N117: 199.99 | O117: 295.63 | P117: =SUM(D117:O117) -> 2269.41 | Q117: =P117/12 -> 189.1175
...

Sheet PREVISTO 2026 REVISADO (2)
C1: Horiontal Praia Brava
C2: Previsão Orçamentária 2026
C3: Categorias | F3: Dezembro | G3: Janeiro | H3: Fevereiro | I3: Março | J3: Abril | K3: Maio | L3: Junho | M3: Julho | N3: Agosto | O3: Setembro | P3: Outubro | Q3: Novembro | R3: Total | S3: Média
C4: 2 Despesas | F4: =F5+F22+F38+F78+F86+#REF! -> #REF! | G4: =G5+G22+G38+G78+G86+#REF! -> #REF! | H4: =H5+H22+H38+H78+H86+#REF! -> #REF! | I4: =I5+I22+I38+I78+I86+#REF! -> #REF! | J4: =J5+J22+J38+J78+J86+#REF! -> #REF! | K4: =K5+K22+K38+K78+K86+#REF! -> #REF! | L4: =L5+L22+L38+L78+L86+#REF! -> #REF! | M4: =M5+M22+M38+M78+M86+#REF! -> #REF! | ... Q4: =Q5+Q22+Q38+Q78+Q86+#REF! -> #REF! | T4: REAJUSTE | U4: 1.045 | V4: 0.045
C5: 2.1 Administrativas | F5: =SUM(F6:F21) -> 9137.3607 | G5: =SUM(G6:G21) -> 8418.0037 | H5: =SUM(H6:H21) -> 83898.212 | I5: =SUM(I6:I21) -> 11787.819 | J5: =SUM(J6:J21) -> 9820.2203 | K5: =SUM(K6:K21) -> 11732.215 | L5: =SUM(L6:L21) -> 11683.814 | M5: =SUM(M6:M21) -> 10756.028 | ... R5: =SUM(R6:R21) -> 203286.84 | S5: =R5/12 -> 16940.57
C6: 2.1.1 Despesas Bancárias | F6: 34 | G6: 34 | H6: ='REALIZADO 2025'!F28*'PREVISTO 2026 REVISADO (2)'!$U$4 -> 82.54455 | I6: ='REALIZADO 2025'!G28*'PREVISTO 2026 REVISADO (2)'!$U$4 -> 62.06255 | J6: ='REALIZADO 2025'!H28*'PREVISTO 2026 REVISADO (2)'!$U$4 -> 101.5949 | K6: ='REALIZADO 2025'!I28*'PREVISTO 2026 REVISADO (2)'!$U$4 -> 39.6055 | L6: 35 | M6: ='REALIZADO 2025'!K28*'PREVISTO 2026 REVISADO (2)'!$U$4 -> 33.3355 | N6: ='REALIZADO 2025'!L28*'PREVISTO 2026 REVISADO (2)'!$U$4 -> 33.3355 | O6: ='REALIZADO 2025'!M28*'PREVISTO 2026 REVISADO (2)'!$U$4 -> 34.3805 | P6: ='REALIZADO 2025'!N28*'PREVISTO 2026 REVISADO (2)'!$U$4 -> 31.2455 | Q6: ='REALIZADO 2025'!O28*'PREVISTO 2026 REVISADO (2)'!$U$4 -> 31.5172 | R6: =SUM(F6:Q6) -> 552.6217 | S6: =R6/12 -> 46.051808
C7: 2.1.11 Reuniões-treinamentos | F7: ='REALIZADO 2025'!D29*'PREVISTO 2026 REVISADO (2)'!$U$4 -> 0 | G7: ='REALIZADO 2025'!E29*'PREVISTO 2026 REVISADO (2)'!$U$4 -> 0 | H7: ='REALIZADO 2025'!F29*'PREVISTO 2026 REVISADO (2)'!$U$4 -> 196.34505 | I7: ='REALIZADO 2025'!G29*'PREVISTO 2026 REVISADO (2)'!$U$4 -> 0 | J7: ='REALIZADO 2025'!H29*'PREVISTO 2026 REVISADO (2)'!$U$4 -> 0 | K7: ='REALIZADO 2025'!I29*'PREVISTO 2026 REVISADO (2)'!$U$4 -> 0 | L7: ='REALIZADO 2025'!J29*'PREVISTO 2026 REVISADO (2)'!$U$4 -> 415.91 | M7: ='REALIZADO 2025'!K29*'PREVISTO 2026 REVISADO (2)'!$U$4 -> 176.5423 | ... Q7: ='REALIZADO 2025'!O29*'PREVISTO 2026 REVISADO (2)'!$U$4 -> 0 | R7: =SUM(F7:Q7) -> 1213.4853 | S7: =R7/12 -> 101.12378
C8: 2.1.12 Certificado Digital | F8: ='REALIZADO 2025'!D30*'PREVISTO 2026 REVISADO (2)'!$U$4 -> 0 | G8: ='REALIZADO 2025'!E30*'PREVISTO 2026 REVISADO (2)'!$U$4 -> 0 | H8: ='REALIZADO 2025'!F30*'PREVISTO 2026 REVISADO (2)'!$U$4 -> 0 | I8: ='REALIZADO 2025'!G30*'PREVISTO 2026 REVISADO (2)'!$U$4 -> 0 | J8: ='REALIZADO 2025'!H30*'PREVISTO 2026 REVISADO (2)'!$U$4 -> 187.65065 | K8: ='REALIZADO 2025'!I30*'PREVISTO 2026 REVISADO (2)'!$U$4 -> 0 | L8: ='REALIZADO 2025'!J30*'PREVISTO 2026 REVISADO (2)'!$U$4 -> 0 | M8: ='REALIZADO 2025'!K30*'PREVISTO 2026 REVISADO (2)'!$U$4 -> 0 | ... Q8: ='REALIZADO 2025'!O30*'PREVISTO 2026 REVISADO (2)'!$U$4 -> 0 | R8: =SUM(F8:Q8) -> 396.65065 | S8: =R8/12 -> 33.054221
C9: 2.1.14 Outros-não Previstos | F9: ='REALIZADO 2025'!D31*'PREVISTO 2026 REVISADO (2)'!$U$4 -> 0 | G9: ='REALIZADO 2025'!E31*'PREVISTO 2026 REVISADO (2)'!$U$4 -> 0 | H9: ='REALIZADO 2025'!F31*'PREVISTO 2026 REVISADO (2)'!$U$4 -> 0 | I9: ='REALIZADO 2025'!G31*'PREVISTO 2026 REVISADO (2)'!$U$4 -> 2612.5 | J9: ='REALIZADO 2025'!H31*'PREVISTO 2026 REVISADO (2)'!$U$4 -> 0 | K9: ='REALIZADO 2025'!I31*'PREVISTO 2026 REVISADO (2)'!$U$4 -> 0 | L9: ='REALIZADO 2025'!J31*'PREVISTO 2026 REVISADO (2)'!$U$4 -> 0 | M9: ='REALIZADO 2025'!K31*'PREVISTO 2026 REVISADO (2)'!$U$4 -> 0 | ... Q9: ='REALIZADO 2025'!O31*'PREVISTO 2026 REVISADO (2)'!$U$4 -> 0 | R9: =SUM(F9:Q9) -> 2612.5 | S9: =R9/12 -> 217.70833
C10: 2.1.19 Alvará De Funcionamento | F10: ='REALIZADO 2025'!D34*'PREVISTO 2026 REVISADO (2)'!$U$4 -> 0 | G10: ='REALIZADO 2025'!E34*'PREVISTO 2026 REVISADO (2)'!$U$4 -> 0 | H10: ='REALIZADO 2025'!F34*'PREVISTO 2026 REVISADO (2)'!$U$4 -> 0 | I10: ='REALIZADO 2025'!G34*'PREVISTO 2026 REVISADO (2)'!$U$4 -> 0 | J10: ='REALIZADO 2025'!H34*'PREVISTO 2026 REVISADO (2)'!$U$4 -> 0 | K10: ='REALIZADO 2025'!I34*'PREVISTO 2026 REVISADO (2)'!$U$4 -> 621.4824 | L10: ='REALIZADO 2025'!J34*'PREVISTO 2026 REVISADO (2)'!$U$4 -> 0 | M10: ='REALIZADO 2025'!K34*'PREVISTO 2026 REVISADO (2)'!$U$4 -> 0 | ... Q10: ='REALIZADO 2025'!O34*'PREVISTO 2026 REVISADO (2)'!$U$4 -> 0 | R10: =SUM(F10:Q10) -> 621.4824 | S10: =R10/12 -> 51.7902
C11: 2.1.2 Material De Expediente-correio | F11: ='REALIZADO 2025'!D35*'PREVISTO 2026 REVISADO (2)'!$U$4 -> 372.17675 | G11: ='REALIZADO 2025'!E35*'PREVISTO 2026 REVISADO (2)'!$U$4 -> 365.75 | H11: ='REALIZADO 2025'!F35*'PREVISTO 2026 REVISADO (2)'!$U$4 -> 937.0515 | I11: ='REALIZADO 2025'!G35*'PREVISTO 2026 REVISADO (2)'!$U$4 -> 510.43025 | J11: ='REALIZADO 2025'!H35*'PREVISTO 2026 REVISADO (2)'!$U$4 -> 320.76275 | K11: ='REALIZADO 2025'!I35*'PREVISTO 2026 REVISADO (2)'!$U$4 -> 403.37 | L11: ='REALIZADO 2025'!J35*'PREVISTO 2026 REVISADO (2)'!$U$4 -> 1135.706 | M11: ='REALIZADO 2025'!K35*'PREVISTO 2026 REVISADO (2)'!$U$4 -> 406.45275 | ... Q11: ='REALIZADO 2025'!O35*'PREVISTO 2026 REVISADO (2)'!$U$4 -> 328.757 | R11: =SUM(F11:Q11) -> 7239.9167 | S11: =R11/12 -> 603.3264
C12: 2.1.21 Sistema De Reservas On-line | F12: ='REALIZADO 2025'!D36*'PREVISTO 2026 REVISADO (2)'!$U$4 -> 522.5 | G12: ='REALIZADO 2025'!E36*'PREVISTO 2026 REVISADO (2)'!$U$4 -> 0 | H12: ='REALIZADO 2025'!F36*'PREVISTO 2026 REVISADO (2)'!$U$4 -> 522.5 | I12: ='REALIZADO 2025'!G36*'PREVISTO 2026 REVISADO (2)'!$U$4 -> 522.5 | J12: ='REALIZADO 2025'!H36*'PREVISTO 2026 REVISADO (2)'!$U$4 -> 522.5 | K12: ='REALIZADO 2025'!I36*'PREVISTO 2026 REVISADO (2)'!$U$4 -> 522.5 | L12: ='REALIZADO 2025'!J36*'PREVISTO 2026 REVISADO (2)'!$U$4 -> 0 | M12: ='REALIZADO 2025'!K36*'PREVISTO 2026 REVISADO (2)'!$U$4 -> 522.5 | ... Q12: ='REALIZADO 2025'!O36*'PREVISTO 2026 REVISADO (2)'!$U$4 -> 0 | R12: =SUM(F12:Q12) -> 4702.5 | S12: =R12/12 -> 391.875
C13: 2.1.22 Material Expediente- Impressões/Digitalizações/Encadernação/Envelopes | F13: ='REALIZADO 2025'!D37*'PREVISTO 2026 REVISADO (2)'!$U$4 -> 0 | G13: ='REALIZADO 2025'!E37*'PREVISTO 2026 REVISADO (2)'!$U$4 -> 0 | H13: ='REALIZADO 2025'!F37*'PREVISTO 2026 REVISADO (2)'!$U$4 -> 0 | I13: ='REALIZADO 2025'!G37*'PREVISTO 2026 REVISADO (2)'!$U$4 -> 0 | J13: ='REALIZADO 2025'!H37*'PREVISTO 2026 REVISADO (2)'!$U$4 -> 0 | K13: ='REALIZADO 2025'!I37*'PREVISTO 2026 REVISADO (2)'!$U$4 -> 0 | L13: ='REALIZADO 2025'!J37*'PREVISTO 2026 REVISADO (2)'!$U$4 -> 0 | M13: ='REALIZADO 2025'!K37*'PREVISTO 2026 REVISADO (2)'!$U$4 -> 0 | ... Q13: ='REALIZADO 2025'!O37*'PREVISTO 2026 REVISADO (2)'!$U$4 -> 1418.4307 | R13: =SUM(F13:Q13) -> 1418.4307 | S13: =R13/12 -> 118.20256
C14: 2.1.3 Honorário Síndico | F14: =5043.17*$U$4 -> 5270.1127 | G14: =5043.17*$U$4 -> 5270.1127 | H14: =5043.17*$U$4 -> 5270.1127 | I14: =5043.17*$U$4 -> 5270.1127 | J14: =5043.17*$U$4 -> 5270.1127 | K14: =5043.17*$U$4 -> 5270.1127 | L14: =5043.17*$U$4 -> 5270.1127 | M14: =5043.17*$U$4 -> 5270.1127 | ... Q14: =5043.17*$U$4 -> 5270.1127 | R14: =SUM(F14:Q14) -> 63241.352 | S14: =R14/12 -> 5270.1127
C15: 2.1.4 Inss-ir-síndico | F15: =2570.4*$U$4 -> 2686.068 | G15: =2570.4*$U$4 -> 2686.068 | H15: =2570.4*$U$4 -> 2686.068 | I15: =2570.4*$U$4 -> 2686.068 | J15: =2570.4*$U$4 -> 2686.068 | K15: =2570.4*$U$4 -> 2686.068 | L15: =2570.4*$U$4 -> 2686.068 | M15: =2570.4*$U$4 -> 2686.068 | ... Q15: =2570.4*$U$4 -> 2686.068 | R15: =SUM(F15:Q15) -> 32232.816 | S15: =R15/12 -> 2686.068
C16: 2.1.5 Iptu | F16: ='REALIZADO 2025'!D40*'PREVISTO 2026 REVISADO (2)'!$U$4 -> 0 | G16: ='REALIZADO 2025'!E40*'PREVISTO 2026 REVISADO (2)'!$U$4 -> 0 | H16: ='REALIZADO 2025'!F40*'PREVISTO 2026 REVISADO (2)'!$U$4 -> 68382.052 | I16: ='REALIZADO 2025'!G40*'PREVISTO 2026 REVISADO (2)'!$U$4 -> 0 | J16: ='REALIZADO 2025'!H40*'PREVISTO 2026 REVISADO (2)'!$U$4 -> 0 | K16: ='REALIZADO 2025'!I40*'PREVISTO 2026 REVISADO (2)'!$U$4 -> 0 | L16: ='REALIZADO 2025'!J40*'PREVISTO 2026 REVISADO (2)'!$U$4 -> 0 | M16: ='REALIZADO 2025'!K40*'PREVISTO 2026 REVISADO (2)'!$U$4 -> 0 | ... Q16: ='REALIZADO 2025'!O40*'PREVISTO 2026 REVISADO (2)'!$U$4 -> 0 | R16: =SUM(F16:Q16) -> 68382.052 | S16: =R16/12 -> 5698.5043
C17: 2.1.6 Taxa De Lixo | F17: ='REALIZADO 2025'!D41*'PREVISTO 2026 REVISADO (2)'!$U$4 -> 0 | G17: ='REALIZADO 2025'!E41*'PREVISTO 2026 REVISADO (2)'!$U$4 -> 0 | H17: ='REALIZADO 2025'!F41*'PREVISTO 2026 REVISADO (2)'!$U$4 -> 5540.266 | I17: ='REALIZADO 2025'!G41*'PREVISTO 2026 REVISADO (2)'!$U$4 -> 0 | J17: ='REALIZADO 2025'!H41*'PREVISTO 2026 REVISADO (2)'!$U$4 -> 0 | K17: ='REALIZADO 2025'!I41*'PREVISTO 2026 REVISADO (2)'!$U$4 -> 0 | L17: ='REALIZADO 2025'!J41*'PREVISTO 2026 REVISADO (2)'!$U$4 -> 0 | M17: ='REALIZADO 2025'!K41*'PREVISTO 2026 REVISADO (2)'!$U$4 -> 0 | ... Q17: ='REALIZADO 2025'!O41*'PREVISTO 2026 REVISADO (2)'!$U$4 -> 0 | R17: =SUM(F17:Q17) -> 5540.266 | S17: =R17/12 -> 461.68884
C18: 2.1.60 Outros | F18: ='REALIZADO 2025'!D42*'PREVISTO 2026 REVISADO (2)'!$U$4 -> 0 | G18: ='REALIZADO 2025'!E42*'PREVISTO 2026 REVISADO (2)'!$U$4 -> 0 | H18: ='REALIZADO 2025'!F42*'PREVISTO 2026 REVISADO (2)'!$U$4 -> 0 | I18: ='REALIZADO 2025'!G42*'PREVISTO 2026 REVISADO (2)'!$U$4 -> 0 | J18: ='REALIZADO 2025'!H42*'PREVISTO 2026 REVISADO (2)'!$U$4 -> 731.53135 | K18: ='REALIZADO 2025'!I42*'PREVISTO 2026 REVISADO (2)'!$U$4 -> 0 | L18: ='REALIZADO 2025'!J42*'PREVISTO 2026 REVISADO (2)'!$U$4 -> 0 | M18: ='REALIZADO 2025'!K42*'PREVISTO 2026 REVISADO (2)'!$U$4 -> 0 | ... Q18: ='REALIZADO 2025'!O42*'PREVISTO 2026 REVISADO (2)'!$U$4 -> 0 | R18: =SUM(F18:Q18) -> 731.53135 | S18: =R18/12 -> 60.960946
C19: 2.1.7 Seguro | F19: ='REALIZADO 2025'!D43*'PREVISTO 2026 REVISADO (2)'!$U$4 -> 0 | G19: ='REALIZADO 2025'!E43*'PREVISTO 2026 REVISADO (2)'!$U$4 -> 0 | H19: ='REALIZADO 2025'!F43*'PREVISTO 2026 REVISADO (2)'!$U$4 -> 0 | I19: ='REALIZADO 2025'!G43*'PREVISTO 2026 REVISADO (2)'!$U$4 -> 0 | J19: ='REALIZADO 2025'!H43*'PREVISTO 2026 REVISADO (2)'!$U$4 -> 0 | K19: ='REALIZADO 2025'!I43*'PREVISTO 2026 REVISADO (2)'!$U$4 -> 1386.6418 | L19: ='REALIZADO 2025'!J43*'PREVISTO 2026 REVISADO (2)'!$U$4 -> 1386.6418 | M19: ='REALIZADO 2025'!K43*'PREVISTO 2026 REVISADO (2)'!$U$4 -> 1386.6418 | ... Q19: ='REALIZADO 2025'!O43*'PREVISTO 2026 REVISADO (2)'!$U$4 -> 0 | R19: =SUM(F19:Q19) -> 8319.9556 | S19: =R19/12 -> 693.32963
C20: 2.1.8 Cartório | F20: ='REALIZADO 2025'!D44*'PREVISTO 2026 REVISADO (2)'!$U$4 -> 252.50335 | G20: ='REALIZADO 2025'!E44*'PREVISTO 2026 REVISADO (2)'!$U$4 -> 62.073 | H20: ='REALIZADO 2025'!F44*'PREVISTO 2026 REVISADO (2)'!$U$4 -> 281.2722 | I20: ='REALIZADO 2025'!G44*'PREVISTO 2026 REVISADO (2)'!$U$4 -> 124.146 | J20: ='REALIZADO 2025'!H44*'PREVISTO 2026 REVISADO (2)'!$U$4 -> 0 | K20: ='REALIZADO 2025'!I44*'PREVISTO 2026 REVISADO (2)'!$U$4 -> 802.4346 | L20: ='REALIZADO 2025'!J44*'PREVISTO 2026 REVISADO (2)'!$U$4 -> 754.37505 | M20: ='REALIZADO 2025'!K44*'PREVISTO 2026 REVISADO (2)'!$U$4 -> 274.3752 | ... Q20: ='REALIZADO 2025'!O44*'PREVISTO 2026 REVISADO (2)'!$U$4 -> 0 | R20: =SUM(F20:Q20) -> 2818.6576 | S20: =R20/12 -> 234.88813
C21: 2.1.9 Documentação Veículo / Multas e Infrações | F21: ='REALIZADO 2025'!D45*'PREVISTO 2026 REVISADO (2)'!$U$4 -> 0 | G21: ='REALIZADO 2025'!E45*'PREVISTO 2026 REVISADO (2)'!$U$4 -> 0 | H21: ='REALIZADO 2025'!F45*'PREVISTO 2026 REVISADO (2)'!$U$4 -> 0 | I21: ='REALIZADO 2025'!G45*'PREVISTO 2026 REVISADO (2)'!$U$4 -> 0 | J21: ='REALIZADO 2025'!H45*'PREVISTO 2026 REVISADO (2)'!$U$4 -> 0 | K21: ='REALIZADO 2025'!I45*'PREVISTO 2026 REVISADO (2)'!$U$4 -> 0 | L21: ='REALIZADO 2025'!J45*'PREVISTO 2026 REVISADO (2)'!$U$4 -> 0 | M21: ='REALIZADO 2025'!K45*'PREVISTO 2026 REVISADO (2)'!$U$4 -> 0 | ... Q21: ='REALIZADO 2025'!O45*'PREVISTO 2026 REVISADO (2)'!$U$4 -> 0 | R21: =SUM(F21:Q21) -> 3262.6258 | S21: =R21/12 -> 271.88549
C22: 2.2 Colaboradores | F22: =SUM(F23:F37) -> 154479.97 | G22: =SUM(G23:G37) -> 112015.2 | H22: =SUM(H23:H37) -> 94533.512 | I22: =SUM(I23:I37) -> 129753.64 | J22: =SUM(J23:J37) -> 99742.99 | K22: =SUM(K23:K37) -> 125942.13 | L22: =SUM(L23:L37) -> 124648.07 | M22: =SUM(M23:M37) -> 100689.33 | ... R22: =SUM(R23:R37) -> 1483394.4 | S22: =R22/12 -> 123616.2 | T22: REAJUSTE | U22: 1.08 | V22: 0.08
C23: 2.2.1 Salários Líquidos | F23: ='REALIZADO 2025'!D47*'PREVISTO 2026 REVISADO (2)'!$U$22 -> 52560.36 | G23: ='REALIZADO 2025'!E47*'PREVISTO 2026 REVISADO (2)'!$U$22 -> 50335.56 | H23: ='REALIZADO 2025'!F47*'PREVISTO 2026 REVISADO (2)'!$U$22 -> 47781.36 | I23: ='REALIZADO 2025'!G47*'PREVISTO 2026 REVISADO (2)'!$U$22 -> 51606.72 | J23: ='REALIZADO 2025'!H47*'PREVISTO 2026 REVISADO (2)'!$U$22 -> 47565.36 | K23: ='REALIZADO 2025'!I47*'PREVISTO 2026 REVISADO (2)'!$U$22 -> 51570.432 | L23: ='REALIZADO 2025'!J47*'PREVISTO 2026 REVISADO (2)'!$U$22 -> 52953.48 | M23: ='REALIZADO 2025'!K47*'PREVISTO 2026 REVISADO (2)'!$U$22 -> 47341.8 | ... Q23: ='REALIZADO 2025'!O47*'PREVISTO 2026 REVISADO (2)'!$U$22 -> 57690.36 | R23: =SUM(F23:Q23) -> 616611.1 | S23: =R23/12 -> 51384.258
C24: 2.2.10 Benefícios Saúde-cesta Básica-copa | F24: ='REALIZADO 2025'!D48*'PREVISTO 2026 REVISADO (2)'!$U$22 -> 23252.497 | G24: ='REALIZADO 2025'!E48*'PREVISTO 2026 REVISADO (2)'!$U$22 -> 15102.04 | H24: ='REALIZADO 2025'!F48*'PREVISTO 2026 REVISADO (2)'!$U$22 -> 6936.1164 | I24: ='REALIZADO 2025'!G48*'PREVISTO 2026 REVISADO (2)'!$U$22 -> 23643.932 | J24: ='REALIZADO 2025'!H48*'PREVISTO 2026 REVISADO (2)'!$U$22 -> 16979.242 | K24: ='REALIZADO 2025'!I48*'PREVISTO 2026 REVISADO (2)'!$U$22 -> 21597.602 | L24: ='REALIZADO 2025'!J48*'PREVISTO 2026 REVISADO (2)'!$U$22 -> 16055.701 | M24: ='REALIZADO 2025'!K48*'PREVISTO 2026 REVISADO (2)'!$U$22 -> 17160.498 | ... Q24: ='REALIZADO 2025'!O48*'PREVISTO 2026 REVISADO (2)'!$U$22 -> 17840.444 | R24: =SUM(F24:Q24) -> 210724.09 | S24: =R24/12 -> 17560.341
C25: 2.2.11 Uniforme-epi | F25: ='REALIZADO 2025'!D49*'PREVISTO 2026 REVISADO (2)'!$U$22 -> 77.652 | G25: ='REALIZADO 2025'!E49*'PREVISTO 2026 REVISADO (2)'!$U$22 -> 847.4112 | H25: ='REALIZADO 2025'!F49*'PREVISTO 2026 REVISADO (2)'!$U$22 -> 342.9108 | I25: ='REALIZADO 2025'!G49*'PREVISTO 2026 REVISADO (2)'!$U$22 -> 528.444 | J25: ='REALIZADO 2025'!H49*'PREVISTO 2026 REVISADO (2)'!$U$22 -> 1798.74 | K25: ='REALIZADO 2025'!I49*'PREVISTO 2026 REVISADO (2)'!$U$22 -> 1893.78 | L25: ='REALIZADO 2025'!J49*'PREVISTO 2026 REVISADO (2)'!$U$22 -> 539.784 | M25: ='REALIZADO 2025'!K49*'PREVISTO 2026 REVISADO (2)'!$U$22 -> 0 | ... Q25: ='REALIZADO 2025'!O49*'PREVISTO 2026 REVISADO (2)'!$U$22 -> 1808.298 | R25: 12000 | S25: =R25/12 -> 1000
C26: 2.2.12 Laudos Médicos-exames | F26: ='REALIZADO 2025'!D50*'PREVISTO 2026 REVISADO (2)'!$U$22 -> 266.1444 | G26: ='REALIZADO 2025'!E50*'PREVISTO 2026 REVISADO (2)'!$U$22 -> 263.25 | H26: ='REALIZADO 2025'!F50*'PREVISTO 2026 REVISADO (2)'!$U$22 -> 291.5676 | I26: ='REALIZADO 2025'!G50*'PREVISTO 2026 REVISADO (2)'!$U$22 -> 278.7804 | J26: ='REALIZADO 2025'!H50*'PREVISTO 2026 REVISADO (2)'!$U$22 -> 235.6236 | K26: ='REALIZADO 2025'!I50*'PREVISTO 2026 REVISADO (2)'!$U$22 -> 247.7088 | L26: ='REALIZADO 2025'!J50*'PREVISTO 2026 REVISADO (2)'!$U$22 -> 248.4 | M26: ='REALIZADO 2025'!K50*'PREVISTO 2026 REVISADO (2)'!$U$22 -> 248.4 | ... Q26: ='REALIZADO 2025'!O50*'PREVISTO 2026 REVISADO (2)'!$U$22 -> 308.6208 | R26: =SUM(F26:Q26) -> 3452.004 | S26: =R26/12 -> 287.667
C27: 2.2.13 Cursos-treinamentos | F27: ='REALIZADO 2025'!D51*'PREVISTO 2026 REVISADO (2)'!$U$22 -> 0 | G27: ='REALIZADO 2025'!E51*'PREVISTO 2026 REVISADO (2)'!$U$22 -> 0 | H27: ='REALIZADO 2025'!F51*'PREVISTO 2026 REVISADO (2)'!$U$22 -> 0 | I27: ='REALIZADO 2025'!G51*'PREVISTO 2026 REVISADO (2)'!$U$22 -> 0 | J27: ='REALIZADO 2025'!H51*'PREVISTO 2026 REVISADO (2)'!$U$22 -> 0 | K27: ='REALIZADO 2025'!I51*'PREVISTO 2026 REVISADO (2)'!$U$22 -> 0 | L27: ='REALIZADO 2025'!J51*'PREVISTO 2026 REVISADO (2)'!$U$22 -> 0 | M27: ='REALIZADO 2025'!K51*'PREVISTO 2026 REVISADO (2)'!$U$22 -> 0 | ... Q27: ='REALIZADO 2025'!O51*'PREVISTO 2026 REVISADO (2)'!$U$22 -> 51.0624 | R27: =SUM(F27:Q27) -> 2204.2584 | S27: =R27/12 -> 183.6882
C28: 2.2.14 Brindes-confraternizações | F28: ='REALIZADO 2025'!D52*'PREVISTO 2026 REVISADO (2)'!$U$22 -> 3033.612 | G28: ='REALIZADO 2025'!E52*'PREVISTO 2026 REVISADO (2)'!$U$22 -> 3616.272 | H28: ='REALIZADO 2025'!F52*'PREVISTO 2026 REVISADO (2)'!$U$22 -> 1596.888 | I28: ='REALIZADO 2025'!G52*'PREVISTO 2026 REVISADO (2)'!$U$22 -> 788.4 | J28: ='REALIZADO 2025'!H52*'PREVISTO 2026 REVISADO (2)'!$U$22 -> 0 | K28: ='REALIZADO 2025'!I52*'PREVISTO 2026 REVISADO (2)'!$U$22 -> 1690.0596 | L28: ='REALIZADO 2025'!J52*'PREVISTO 2026 REVISADO (2)'!$U$22 -> 0 | M28: ='REALIZADO 2025'!K52*'PREVISTO 2026 REVISADO (2)'!$U$22 -> 0 | ... Q28: ='REALIZADO 2025'!O52*'PREVISTO 2026 REVISADO (2)'!$U$22 -> 0 | R28: =SUM(F28:Q28) -> 11296.422 | S28: =R28/12 -> 941.3685
C29: 2.2.15 Seguro De Vida | F29: ='REALIZADO 2025'!D53*'PREVISTO 2026 REVISADO (2)'!$U$22 -> 319.5936 | G29: ='REALIZADO 2025'!E53*'PREVISTO 2026 REVISADO (2)'!$U$22 -> 319.5936 | H29: ='REALIZADO 2025'!F53*'PREVISTO 2026 REVISADO (2)'!$U$22 -> 319.5936 | I29: ='REALIZADO 2025'!G53*'PREVISTO 2026 REVISADO (2)'!$U$22 -> 319.5936 | J29: ='REALIZADO 2025'!H53*'PREVISTO 2026 REVISADO (2)'!$U$22 -> 332.802 | K29: ='REALIZADO 2025'!I53*'PREVISTO 2026 REVISADO (2)'!$U$22 -> 332.802 | L29: ='REALIZADO 2025'!J53*'PREVISTO 2026 REVISADO (2)'!$U$22 -> 332.802 | M29: ='REALIZADO 2025'!K53*'PREVISTO 2026 REVISADO (2)'!$U$22 -> 332.802 | ... Q29: ='REALIZADO 2025'!O53*'PREVISTO 2026 REVISADO (2)'!$U$22 -> 534.5352 | R29: =SUM(F29:Q29) -> 4344.2568 | S29: =R29/12 -> 362.0214
C30: 2.2.16 Contribuição Sindical Empregados | F30: ='REALIZADO 2025'!D54*'PREVISTO 2026 REVISADO (2)'!$U$22 -> 324 | G30: ='REALIZADO 2025'!E54*'PREVISTO 2026 REVISADO (2)'!$U$22 -> 324 | H30: ='REALIZADO 2025'!F54*'PREVISTO 2026 REVISADO (2)'!$U$22 -> 367.2 | I30: ='REALIZADO 2025'!G54*'PREVISTO 2026 REVISADO (2)'!$U$22 -> 345.6 | J30: ='REALIZADO 2025'!H54*'PREVISTO 2026 REVISADO (2)'!$U$22 -> 345.6 | K30: ='REALIZADO 2025'!I54*'PREVISTO 2026 REVISADO (2)'!$U$22 -> 324 | L30: ='REALIZADO 2025'!J54*'PREVISTO 2026 REVISADO (2)'!$U$22 -> 302.4 | M30: ='REALIZADO 2025'!K54*'PREVISTO 2026 REVISADO (2)'!$U$22 -> 324 | ... Q30: ='REALIZADO 2025'!O54*'PREVISTO 2026 REVISADO (2)'!$U$22 -> 0 | R30: =SUM(F30:Q30) -> 3304.8 | S30: =R30/12 -> 275.4
C31: 2.2.17 Contribuição Sindical Patronal | F31: ='REALIZADO 2025'!D55*'PREVISTO 2026 REVISADO (2)'!$U$22 -> 0 | G31: ='REALIZADO 2025'!E55*'PREVISTO 2026 REVISADO (2)'!$U$22 -> 0 | H31: ='REALIZADO 2025'!F55*'PREVISTO 2026 REVISADO (2)'!$U$22 -> 0 | I31: ='REALIZADO 2025'!G55*'PREVISTO 2026 REVISADO (2)'!$U$22 -> 0 | J31: ='REALIZADO 2025'!H55*'PREVISTO 2026 REVISADO (2)'!$U$22 -> 0 | K31: ='REALIZADO 2025'!I55*'PREVISTO 2026 REVISADO (2)'!$U$22 -> 0 | L31: ='REALIZADO 2025'!J55*'PREVISTO 2026 REVISADO (2)'!$U$22 -> 0 | M31: ='REALIZADO 2025'!K55*'PREVISTO 2026 REVISADO (2)'!$U$22 -> 0 | ... Q31: ='REALIZADO 2025'!O55*'PREVISTO 2026 REVISADO (2)'!$U$22 -> 367.2 | R31: =SUM(F31:Q31) -> 712.8 | S31: =R31/12 -> 59.4
C32: 2.2.20 Tributos Dctf-web | F32: ='REALIZADO 2025'!D57*'PREVISTO 2026 REVISADO (2)'!$U$22 -> 26005.406 | G32: ='REALIZADO 2025'!E57*'PREVISTO 2026 REVISADO (2)'!$U$22 -> 25600.212 | H32: ='REALIZADO 2025'!F57*'PREVISTO 2026 REVISADO (2)'!$U$22 -> 24219.011 | I32: ='REALIZADO 2025'!G57*'PREVISTO 2026 REVISADO (2)'!$U$22 -> 24259.932 | J32: ='REALIZADO 2025'!H57*'PREVISTO 2026 REVISADO (2)'!$U$22 -> 26176.943 | K32: ='REALIZADO 2025'!I57*'PREVISTO 2026 REVISADO (2)'!$U$22 -> 27497.815 | L32: ='REALIZADO 2025'!J57*'PREVISTO 2026 REVISADO (2)'!$U$22 -> 29137.298 | M32: ='REALIZADO 2025'!K57*'PREVISTO 2026 REVISADO (2)'!$U$22 -> 28422.446 | ... Q32: ='REALIZADO 2025'!O57*'PREVISTO 2026 REVISADO (2)'!$U$22 -> 29389.878 | R32: =SUM(F32:Q32) -> 321580.7 | S32: =R32/12 -> 26798.392
C33: 2.2.3 Fgts | F33: ='REALIZADO 2025'!D58*'PREVISTO 2026 REVISADO (2)'!$U$22 -> 5940.0108 | G33: ='REALIZADO 2025'!E58*'PREVISTO 2026 REVISADO (2)'!$U$22 -> 6738.3576 | H33: ='REALIZADO 2025'!F58*'PREVISTO 2026 REVISADO (2)'!$U$22 -> 4368.816 | I33: ='REALIZADO 2025'!G58*'PREVISTO 2026 REVISADO (2)'!$U$22 -> 4458.0024 | J33: ='REALIZADO 2025'!H58*'PREVISTO 2026 REVISADO (2)'!$U$22 -> 4821.5196 | K33: ='REALIZADO 2025'!I58*'PREVISTO 2026 REVISADO (2)'!$U$22 -> 4989.3084 | L33: ='REALIZADO 2025'!J58*'PREVISTO 2026 REVISADO (2)'!$U$22 -> 5267.2032 | M33: ='REALIZADO 2025'!K58*'PREVISTO 2026 REVISADO (2)'!$U$22 -> 5605.5024 | ... Q33: ='REALIZADO 2025'!O58*'PREVISTO 2026 REVISADO (2)'!$U$22 -> 6208.488 | R33: =SUM(F33:Q33) -> 65711.941 | S33: =R33/12 -> 5475.9951
C34: 2.2.6 Férias | F34: ='REALIZADO 2025'!D59*'PREVISTO 2026 REVISADO (2)'!$U$22 -> 0 | G34: ='REALIZADO 2025'!E59*'PREVISTO 2026 REVISADO (2)'!$U$22 -> 0 | H34: ='REALIZADO 2025'!F59*'PREVISTO 2026 REVISADO (2)'!$U$22 -> 6453.5292 | I34: ='REALIZADO 2025'!G59*'PREVISTO 2026 REVISADO (2)'!$U$22 -> 9554.8356 | J34: ='REALIZADO 2025'!H59*'PREVISTO 2026 REVISADO (2)'!$U$22 -> 0 | K34: ='REALIZADO 2025'!I59*'PREVISTO 2026 REVISADO (2)'!$U$22 -> 14145.57 | L34: ='REALIZADO 2025'!J59*'PREVISTO 2026 REVISADO (2)'!$U$22 -> 18469.642 | M34: ='REALIZADO 2025'!K59*'PREVISTO 2026 REVISADO (2)'!$U$22 -> 0 | ... Q34: ='REALIZADO 2025'!O59*'PREVISTO 2026 REVISADO (2)'!$U$22 -> 0 | R34: =SUM(F34:Q34) -> 57366.209 | S34: =R34/12 -> 4780.5174
C35: 2.2.7 13 Salário | F35: ='REALIZADO 2025'!D60*'PREVISTO 2026 REVISADO (2)'!$U$22 -> 41884.214 | G35: ='REALIZADO 2025'!E60*'PREVISTO 2026 REVISADO (2)'!$U$22 -> 0 | H35: ='REALIZADO 2025'!F60*'PREVISTO 2026 REVISADO (2)'!$U$22 -> 0 | I35: ='REALIZADO 2025'!G60*'PREVISTO 2026 REVISADO (2)'!$U$22 -> 0 | J35: ='REALIZADO 2025'!H60*'PREVISTO 2026 REVISADO (2)'!$U$22 -> 0 | K35: ='REALIZADO 2025'!I60*'PREVISTO 2026 REVISADO (2)'!$U$22 -> 0 | L35: ='REALIZADO 2025'!J60*'PREVISTO 2026 REVISADO (2)'!$U$22 -> 0 | M35: ='REALIZADO 2025'!K60*'PREVISTO 2026 REVISADO (2)'!$U$22 -> 0 | ... Q35: ='REALIZADO 2025'!O60*'PREVISTO 2026 REVISADO (2)'!$U$22 -> 20089.08 | R35: =SUM(F35:Q35) -> 71808.854 | S35: =R35/12 -> 5984.0712
C36: 2.2.8 Rescisões | F36: ='REALIZADO 2025'!D61*'PREVISTO 2026 REVISADO (2)'!$U$22 -> 0 | G36: ='REALIZADO 2025'!E61*'PREVISTO 2026 REVISADO (2)'!$U$22 -> 7352.1864 | H36: ='REALIZADO 2025'!F61*'PREVISTO 2026 REVISADO (2)'!$U$22 -> 0 | I36: ='REALIZADO 2025'!G61*'PREVISTO 2026 REVISADO (2)'!$U$22 -> 13862.48 | J36: ='REALIZADO 2025'!H61*'PREVISTO 2026 REVISADO (2)'!$U$22 -> 0 | K36: ='REALIZADO 2025'!I61*'PREVISTO 2026 REVISADO (2)'!$U$22 -> 0 | L36: ='REALIZADO 2025'!J61*'PREVISTO 2026 REVISADO (2)'!$U$22 -> 0 | M36: ='REALIZADO 2025'!K61*'PREVISTO 2026 REVISADO (2)'!$U$22 -> 0 | ... Q36: ='REALIZADO 2025'!O61*'PREVISTO 2026 REVISADO (2)'!$U$22 -> 1015.2 | R36: 90000 | S36: =R36/12 -> 7500
C37: 2.2.9 Vale Transporte | F37: ='REALIZADO 2025'!D62*'PREVISTO 2026 REVISADO (2)'!$U$22 -> 816.48 | G37: ='REALIZADO 2025'!E62*'PREVISTO 2026 REVISADO (2)'!$U$22 -> 1516.32 | H37: ='REALIZADO 2025'!F62*'PREVISTO 2026 REVISADO (2)'!$U$22 -> 1856.52 | I37: ='REALIZADO 2025'!G62*'PREVISTO 2026 REVISADO (2)'!$U$22 -> 106.92 | J37: ='REALIZADO 2025'!H62*'PREVISTO 2026 REVISADO (2)'!$U$22 -> 1487.16 | K37: ='REALIZADO 2025'!I62*'PREVISTO 2026 REVISADO (2)'!$U$22 -> 1653.048 | L37: ='REALIZADO 2025'!J62*'PREVISTO 2026 REVISADO (2)'!$U$22 -> 1341.36 | M37: ='REALIZADO 2025'!K62*'PREVISTO 2026 REVISADO (2)'!$U$22 -> 1253.88 | ... Q37: ='REALIZADO 2025'!O62*'PREVISTO 2026 REVISADO (2)'!$U$22 -> 0 | R37: =SUM(F37:Q37) -> 12277.008 | S37: =R37/12 -> 1023.084
C38: 2.3 Manutenção | F38: =F39+F55+F68+F72 -> 48895.278 | G38: =G39+G55+G68+G72 -> 40170.981 | H38: =H39+H55+H68+H72 -> 45046.554 | I38: =I39+I55+I68+I72 -> 48792.712 | J38: =J39+J55+J68+J72 -> 77235.741 | K38: =K39+K55+K68+K72 -> 75126.429 | L38: =L39+L55+L68+L72 -> 57768.373 | M38: =M39+M55+M68+M72 -> 45237.298 | ... R38: =R39+R55+R68+R72 -> 638498.62 | S38: =R38/12 -> 53208.219 | T38: REAJUSTE | U38: 1.045 | V38: 0.045
C39: 2.3.1 Areas De Lazer | F39: =SUM(F40:F48) -> 11772.991 | G39: =SUM(G40:G48) -> 6239.162 | H39: =SUM(H40:H48) -> 4612.3374 | I39: =SUM(I40:I48) -> 5200.2335 | J39: =SUM(J40:J48) -> 55340.149 | K39: =SUM(K40:K48) -> 52472.271 | L39: =SUM(L40:L48) -> 32692.501 | M39: =SUM(M40:M48) -> 16665.378 | ... Q39: =SUM(Q40:Q48) -> 24886.111 | R39: =SUM(R40:R54) -> 332522.31 | S39: =R39/12 -> 27710.192
C40: 2.3.1.1 Salão De Festas Bosque | F40: ='REALIZADO 2025'!D65*'PREVISTO 2026 REVISADO (2)'!$U$38 -> 1550.686 | G40: ='REALIZADO 2025'!E65*'PREVISTO 2026 REVISADO (2)'!$U$38 -> 470.25 | H40: ='REALIZADO 2025'!F65*'PREVISTO 2026 REVISADO (2)'!$U$38 -> 1302.07 | I40: ='REALIZADO 2025'!G65*'PREVISTO 2026 REVISADO (2)'!$U$38 -> 767.64655 | J40: ='REALIZADO 2025'!H65*'PREVISTO 2026 REVISADO (2)'!$U$38 -> 8109.0955 | K40: ='REALIZADO 2025'!I65*'PREVISTO 2026 REVISADO (2)'!$U$38 -> 9680.88 | L40: ='REALIZADO 2025'!J65*'PREVISTO 2026 REVISADO (2)'!$U$38 -> 1657.37 | M40: ='REALIZADO 2025'!K65*'PREVISTO 2026 REVISADO (2)'!$U$38 -> 5182.4685 | ... Q40: ='REALIZADO 2025'!O65*'PREVISTO 2026 REVISADO (2)'!$U$38 -> 1478.9467 | R40: 63600 | S40: =R40/12 -> 5300
C41: 2.3.1.12 Churrasqueira Costela Fogo De Chão | F41: ='REALIZADO 2025'!D67*'PREVISTO 2026 REVISADO (2)'!$U$38 -> 0 | G41: ='REALIZADO 2025'!E67*'PREVISTO 2026 REVISADO (2)'!$U$38 -> 0 | H41: ='REALIZADO 2025'!F67*'PREVISTO 2026 REVISADO (2)'!$U$38 -> 0 | I41: ='REALIZADO 2025'!G67*'PREVISTO 2026 REVISADO (2)'!$U$38 -> 0 | J41: ='REALIZADO 2025'!H67*'PREVISTO 2026 REVISADO (2)'!$U$38 -> 0 | K41: ='REALIZADO 2025'!I67*'PREVISTO 2026 REVISADO (2)'!$U$38 -> 468.996 | L41: ='REALIZADO 2025'!J67*'PREVISTO 2026 REVISADO (2)'!$U$38 -> 0 | M41: ='REALIZADO 2025'!K67*'PREVISTO 2026 REVISADO (2)'!$U$38 -> 0 | ... Q41: ='REALIZADO 2025'!O67*'PREVISTO 2026 REVISADO (2)'!$U$38 -> 1730.1229 | R41: =SUM(F41:Q41) -> 2199.1189 | S41: =R41/12 -> 183.25991
C42: 2.3.1.2 Salão De Festas Piscina | F42: ='REALIZADO 2025'!D68*'PREVISTO 2026 REVISADO (2)'!$U$38 -> 3193.8857 | G42: ='REALIZADO 2025'!E68*'PREVISTO 2026 REVISADO (2)'!$U$38 -> 491.15 | H42: ='REALIZADO 2025'!F68*'PREVISTO 2026 REVISADO (2)'!$U$38 -> 778.525 | I42: ='REALIZADO 2025'!G68*'PREVISTO 2026 REVISADO (2)'!$U$38 -> 1744.0527 | J42: ='REALIZADO 2025'!H68*'PREVISTO 2026 REVISADO (2)'!$U$38 -> 39798.062 | K42: ='REALIZADO 2025'!I68*'PREVISTO 2026 REVISADO (2)'!$U$38 -> 33495.207 | L42: ='REALIZADO 2025'!J68*'PREVISTO 2026 REVISADO (2)'!$U$38 -> 22087.862 | M42: ='REALIZADO 2025'!K68*'PREVISTO 2026 REVISADO (2)'!$U$38 -> 5523.6296 | ... Q42: ='REALIZADO 2025'!O68*'PREVISTO 2026 REVISADO (2)'!$U$38 -> 8769.3787 | R42: 24000 | S42: =R42/12 -> 2000
C43: 2.3.1.3 Salão De Festas Pub | F43: ='REALIZADO 2025'!D69*'PREVISTO 2026 REVISADO (2)'!$U$38 -> 610.8025 | G43: ='REALIZADO 2025'!E69*'PREVISTO 2026 REVISADO (2)'!$U$38 -> 485.03675 | H43: ='REALIZADO 2025'!F69*'PREVISTO 2026 REVISADO (2)'!$U$38 -> 192.4263 | I43: ='REALIZADO 2025'!G69*'PREVISTO 2026 REVISADO (2)'!$U$38 -> 62.7 | J43: ='REALIZADO 2025'!H69*'PREVISTO 2026 REVISADO (2)'!$U$38 -> 3135 | K43: ='REALIZADO 2025'!I69*'PREVISTO 2026 REVISADO (2)'!$U$38 -> 5643 | L43: ='REALIZADO 2025'!J69*'PREVISTO 2026 REVISADO (2)'!$U$38 -> 0 | M43: ='REALIZADO 2025'!K69*'PREVISTO 2026 REVISADO (2)'!$U$38 -> 401.22775 | ... Q43: ='REALIZADO 2025'!O69*'PREVISTO 2026 REVISADO (2)'!$U$38 -> 6967.1195 | R43: 16000 | S43: =R43/12 -> 1333.3333
C44: 2.3.1.4 Quiosque | F44: ='REALIZADO 2025'!D70*'PREVISTO 2026 REVISADO (2)'!$U$38 -> 554.5188 | G44: ='REALIZADO 2025'!E70*'PREVISTO 2026 REVISADO (2)'!$U$38 -> 0 | H44: ='REALIZADO 2025'!F70*'PREVISTO 2026 REVISADO (2)'!$U$38 -> 0 | I44: ='REALIZADO 2025'!G70*'PREVISTO 2026 REVISADO (2)'!$U$38 -> 0 | J44: ='REALIZADO 2025'!H70*'PREVISTO 2026 REVISADO (2)'!$U$38 -> 0 | K44: ='REALIZADO 2025'!I70*'PREVISTO 2026 REVISADO (2)'!$U$38 -> 0 | L44: ='REALIZADO 2025'!J70*'PREVISTO 2026 REVISADO (2)'!$U$38 -> 0 | M44: ='REALIZADO 2025'!K70*'PREVISTO 2026 REVISADO (2)'!$U$38 -> 0 | ... Q44: ='REALIZADO 2025'!O70*'PREVISTO 2026 REVISADO (2)'!$U$38 -> 271.7 | R44: =SUM(F44:Q44) -> 5771.5977 | S44: =R44/12 -> 480.96648
C45: 2.3.1.5 Espaço Juvenil | F45: ='REALIZADO 2025'!D71*'PREVISTO 2026 REVISADO (2)'!$U$38 -> 0 | G45: ='REALIZADO 2025'!E71*'PREVISTO 2026 REVISADO (2)'!$U$38 -> 0 | H45: ='REALIZADO 2025'!F71*'PREVISTO 2026 REVISADO (2)'!$U$38 -> 0 | I45: ='REALIZADO 2025'!G71*'PREVISTO 2026 REVISADO (2)'!$U$38 -> 0 | J45: ='REALIZADO 2025'!H71*'PREVISTO 2026 REVISADO (2)'!$U$38 -> 0 | K45: ='REALIZADO 2025'!I71*'PREVISTO 2026 REVISADO (2)'!$U$38 -> 0 | L45: ='REALIZADO 2025'!J71*'PREVISTO 2026 REVISADO (2)'!$U$38 -> 1440.01 | M45: ='REALIZADO 2025'!K71*'PREVISTO 2026 REVISADO (2)'!$U$38 -> 543.4 | ... Q45: ='REALIZADO 2025'!O71*'PREVISTO 2026 REVISADO (2)'!$U$38 -> 683.3464 | R45: =SUM(F45:Q45) -> 12602.575 | S45: =R45/12 -> 1050.2145
C46: 2.3.1.6 Piscina | F46: ='REALIZADO 2025'!D72*'PREVISTO 2026 REVISADO (2)'!$U$38 -> 5500.8486 | G46: ='REALIZADO 2025'!E72*'PREVISTO 2026 REVISADO (2)'!$U$38 -> 4596.8505 | H46: ='REALIZADO 2025'!F72*'PREVISTO 2026 REVISADO (2)'!$U$38 -> 1380.1106 | I46: ='REALIZADO 2025'!G72*'PREVISTO 2026 REVISADO (2)'!$U$38 -> 1256.4348 | J46: ='REALIZADO 2025'!H72*'PREVISTO 2026 REVISADO (2)'!$U$38 -> 1988.7499 | K46: ='REALIZADO 2025'!I72*'PREVISTO 2026 REVISADO (2)'!$U$38 -> 252.7646 | L46: ='REALIZADO 2025'!J72*'PREVISTO 2026 REVISADO (2)'!$U$38 -> 202.7718 | M46: ='REALIZADO 2025'!K72*'PREVISTO 2026 REVISADO (2)'!$U$38 -> 2318.855 | ... Q46: ='REALIZADO 2025'!O72*'PREVISTO 2026 REVISADO (2)'!$U$38 -> 4023.1559 | R46: 20000 | S46: =R46/12 -> 1666.6667
C47: 2.3.1.7 Playground - Bosque | F47: ='REALIZADO 2025'!D73*'PREVISTO 2026 REVISADO (2)'!$U$38 -> 349.70925 | G47: ='REALIZADO 2025'!E73*'PREVISTO 2026 REVISADO (2)'!$U$38 -> 60.5055 | H47: ='REALIZADO 2025'!F73*'PREVISTO 2026 REVISADO (2)'!$U$38 -> 60.5055 | I47: ='REALIZADO 2025'!G73*'PREVISTO 2026 REVISADO (2)'!$U$38 -> 60.5055 | J47: ='REALIZADO 2025'!H73*'PREVISTO 2026 REVISADO (2)'!$U$38 -> 60.5055 | K47: ='REALIZADO 2025'!I73*'PREVISTO 2026 REVISADO (2)'!$U$38 -> 530.7555 | L47: ='REALIZADO 2025'!J73*'PREVISTO 2026 REVISADO (2)'!$U$38 -> 3445.156 | M47: ='REALIZADO 2025'!K73*'PREVISTO 2026 REVISADO (2)'!$U$38 -> 257.07 | ... Q47: ='REALIZADO 2025'!O73*'PREVISTO 2026 REVISADO (2)'!$U$38 -> 0 | R47: 25000 | S47: =R47/12 -> 2083.3333
C48: 2.3.1.8 Academia | F48: ='REALIZADO 2025'!D74*'PREVISTO 2026 REVISADO (2)'!$U$38 -> 12.54 | G48: ='REALIZADO 2025'!E74*'PREVISTO 2026 REVISADO (2)'!$U$38 -> 135.3693 | H48: ='REALIZADO 2025'!F74*'PREVISTO 2026 REVISADO (2)'!$U$38 -> 898.7 | I48: ='REALIZADO 2025'!G74*'PREVISTO 2026 REVISADO (2)'!$U$38 -> 1308.8938 | J48: ='REALIZADO 2025'!H74*'PREVISTO 2026 REVISADO (2)'!$U$38 -> 2248.7355 | K48: ='REALIZADO 2025'!I74*'PREVISTO 2026 REVISADO (2)'!$U$38 -> 2400.668 | L48: ='REALIZADO 2025'!J74*'PREVISTO 2026 REVISADO (2)'!$U$38 -> 3859.3313 | M48: ='REALIZADO 2025'!K74*'PREVISTO 2026 REVISADO (2)'!$U$38 -> 2438.7269 | ... Q48: ='REALIZADO 2025'!O74*'PREVISTO 2026 REVISADO (2)'!$U$38 -> 962.3405 | R48: =SUM(F48:Q48) -> 17349.017 | S48: =R48/12 -> 1445.7514
C49: 2.3.1.13 Quadra Futebol | R49: 10000 | S49: =R49/12 -> 833.33333
C50: 2.3.1.14 Quadra de tenis | R50: 10000 | S50: =R50/12 -> 833.33333
C51: 2.3.1.15 Quadra Poliesportiva | R51: 90000 | S51: =R51/12 -> 7500
C52: 2.3.1.16 Quadra Padle | R52: 3000 | S52: =R52/12 -> 250
C53: 2.3.1.17 Quadra de areia | R53: 3000 | S53: =R53/12 -> 250
C54: 2.3.1.18 Playground - Piscina | R54: 30000 | S54: =R54/12 -> 2500
C55: 2.3.2 Estrutura | F55: =SUM(F56:F67) -> 13069.94 | G55: =SUM(G56:G67) -> 14929.142 | H55: =SUM(H56:H67) -> 19163.168 | I55: =SUM(I56:I67) -> 16750.493 | J55: =SUM(J56:J67) -> 10903.938 | K55: =SUM(K56:K67) -> 10419.653 | L55: =SUM(L56:L67) -> 14561.835 | M55: =SUM(M56:M67) -> 8672.9984 | ... R55: =SUM(R56:R67) -> 149101.29 | S55: =R55/12 -> 12425.108
C56: 2.3.2.1 Areas e Instalações Comuns | F56: ='REALIZADO 2025'!D76*'PREVISTO 2026 REVISADO (2)'!$U$38 -> 1201.7082 | G56: ='REALIZADO 2025'!E76*'PREVISTO 2026 REVISADO (2)'!$U$38 -> 5668.4353 | H56: ='REALIZADO 2025'!F76*'PREVISTO 2026 REVISADO (2)'!$U$38 -> 1839.4299 | I56: ='REALIZADO 2025'!G76*'PREVISTO 2026 REVISADO (2)'!$U$38 -> 1707.436 | J56: ='REALIZADO 2025'!H76*'PREVISTO 2026 REVISADO (2)'!$U$38 -> 1130.7213 | K56: ='REALIZADO 2025'!I76*'PREVISTO 2026 REVISADO (2)'!$U$38 -> 410.50735 | L56: ='REALIZADO 2025'!J76*'PREVISTO 2026 REVISADO (2)'!$U$38 -> 2901.2753 | M56: ='REALIZADO 2025'!K76*'PREVISTO 2026 REVISADO (2)'!$U$38 -> 1329.752 | ... Q56: ='REALIZADO 2025'!O76*'PREVISTO 2026 REVISADO (2)'!$U$38 -> 1431.65 | R56: =SUM(F56:Q56) -> 22780.404 | S56: =R56/12 -> 1898.367
C57: 2.3.2.10 Ruas-meio Fio-lombada-sinalização | F57: ='REALIZADO 2025'!D77*'PREVISTO 2026 REVISADO (2)'!$U$38 -> 0 | G57: ='REALIZADO 2025'!E77*'PREVISTO 2026 REVISADO (2)'!$U$38 -> 2427.5245 | H57: ='REALIZADO 2025'!F77*'PREVISTO 2026 REVISADO (2)'!$U$38 -> 3773.1188 | I57: ='REALIZADO 2025'!G77*'PREVISTO 2026 REVISADO (2)'!$U$38 -> 1885.3785 | J57: ='REALIZADO 2025'!H77*'PREVISTO 2026 REVISADO (2)'!$U$38 -> 1016.2625 | K57: ='REALIZADO 2025'!I77*'PREVISTO 2026 REVISADO (2)'!$U$38 -> 3881.9869 | L57: ='REALIZADO 2025'!J77*'PREVISTO 2026 REVISADO (2)'!$U$38 -> 3093.2 | M57: ='REALIZADO 2025'!K77*'PREVISTO 2026 REVISADO (2)'!$U$38 -> 1703.35 | ... Q57: ='REALIZADO 2025'!O77*'PREVISTO 2026 REVISADO (2)'!$U$38 -> 2277.6716 | R57: =SUM(F57:Q57) -> 29107.096 | S57: =R57/12 -> 2425.5913
C58: 2.3.2.12 Pergola | F58: ='REALIZADO 2025'!D78*'PREVISTO 2026 REVISADO (2)'!$U$38 -> 888.25 | G58: ='REALIZADO 2025'!E78*'PREVISTO 2026 REVISADO (2)'!$U$38 -> 548.625 | H58: ='REALIZADO 2025'!F78*'PREVISTO 2026 REVISADO (2)'!$U$38 -> 0 | I58: ='REALIZADO 2025'!G78*'PREVISTO 2026 REVISADO (2)'!$U$38 -> 0 | J58: ='REALIZADO 2025'!H78*'PREVISTO 2026 REVISADO (2)'!$U$38 -> 0 | K58: ='REALIZADO 2025'!I78*'PREVISTO 2026 REVISADO (2)'!$U$38 -> 0 | L58: ='REALIZADO 2025'!J78*'PREVISTO 2026 REVISADO (2)'!$U$38 -> 0 | M58: ='REALIZADO 2025'!K78*'PREVISTO 2026 REVISADO (2)'!$U$38 -> 0 | ... Q58: ='REALIZADO 2025'!O78*'PREVISTO 2026 REVISADO (2)'!$U$38 -> 0 | R58: =SUM(F58:Q58) -> 1436.875 | S58: =R58/12 -> 119.73958
C59: 2.3.2.13 Dog Park | F59: ='REALIZADO 2025'!D79*'PREVISTO 2026 REVISADO (2)'!$U$38 -> 0 | G59: ='REALIZADO 2025'!E79*'PREVISTO 2026 REVISADO (2)'!$U$38 -> 0 | H59: ='REALIZADO 2025'!F79*'PREVISTO 2026 REVISADO (2)'!$U$38 -> 0 | I59: ='REALIZADO 2025'!G79*'PREVISTO 2026 REVISADO (2)'!$U$38 -> 0 | J59: ='REALIZADO 2025'!H79*'PREVISTO 2026 REVISADO (2)'!$U$38 -> 0 | K59: ='REALIZADO 2025'!I79*'PREVISTO 2026 REVISADO (2)'!$U$38 -> 0 | L59: ='REALIZADO 2025'!J79*'PREVISTO 2026 REVISADO (2)'!$U$38 -> 0 | M59: ='REALIZADO 2025'!K79*'PREVISTO 2026 REVISADO (2)'!$U$38 -> 0 | ... Q59: ='REALIZADO 2025'!O79*'PREVISTO 2026 REVISADO (2)'!$U$38 -> 0 | R59: =SUM(F59:Q59) -> 42.5733 | S59: =R59/12 -> 3.547775
C60: 2.3.2.2 Elétrica- Iluminação | F60: ='REALIZADO 2025'!D80*'PREVISTO 2026 REVISADO (2)'!$U$38 -> 2080.5114 | G60: ='REALIZADO 2025'!E80*'PREVISTO 2026 REVISADO (2)'!$U$38 -> 1775.5804 | H60: ='REALIZADO 2025'!F80*'PREVISTO 2026 REVISADO (2)'!$U$38 -> 2668.5329 | I60: ='REALIZADO 2025'!G80*'PREVISTO 2026 REVISADO (2)'!$U$38 -> 5443.0915 | J60: ='REALIZADO 2025'!H80*'PREVISTO 2026 REVISADO (2)'!$U$38 -> 3762.7419 | K60: ='REALIZADO 2025'!I80*'PREVISTO 2026 REVISADO (2)'!$U$38 -> 3642.0862 | L60: ='REALIZADO 2025'!J80*'PREVISTO 2026 REVISADO (2)'!$U$38 -> 372.7933 | M60: ='REALIZADO 2025'!K80*'PREVISTO 2026 REVISADO (2)'!$U$38 -> 968.1925 | ... Q60: ='REALIZADO 2025'!O80*'PREVISTO 2026 REVISADO (2)'!$U$38 -> 4547.422 | R60: 10000 | S60: =R60/12 -> 833.33333
C61: 2.3.2.3 Instalações Hidráulicas- Esgoto | F61: ='REALIZADO 2025'!D81*'PREVISTO 2026 REVISADO (2)'!$U$38 -> 0 | G61: ='REALIZADO 2025'!E81*'PREVISTO 2026 REVISADO (2)'!$U$38 -> 0 | H61: ='REALIZADO 2025'!F81*'PREVISTO 2026 REVISADO (2)'!$U$38 -> 0 | I61: ='REALIZADO 2025'!G81*'PREVISTO 2026 REVISADO (2)'!$U$38 -> 104.5 | J61: ='REALIZADO 2025'!H81*'PREVISTO 2026 REVISADO (2)'!$U$38 -> 0 | K61: ='REALIZADO 2025'!I81*'PREVISTO 2026 REVISADO (2)'!$U$38 -> 0 | L61: ='REALIZADO 2025'!J81*'PREVISTO 2026 REVISADO (2)'!$U$38 -> 0 | M61: ='REALIZADO 2025'!K81*'PREVISTO 2026 REVISADO (2)'!$U$38 -> 0 | ... Q61: ='REALIZADO 2025'!O81*'PREVISTO 2026 REVISADO (2)'!$U$38 -> 56.7644 | R61: =SUM(F61:Q61) -> 161.2644 | S61: =R61/12 -> 13.4387
C62: 2.3.2.4 Jardim | F62: ='REALIZADO 2025'!D82*'PREVISTO 2026 REVISADO (2)'!$U$38 -> 7691.6598 | G62: ='REALIZADO 2025'!E82*'PREVISTO 2026 REVISADO (2)'!$U$38 -> 2713.0812 | H62: ='REALIZADO 2025'!F82*'PREVISTO 2026 REVISADO (2)'!$U$38 -> 1018.875 | I62: ='REALIZADO 2025'!G82*'PREVISTO 2026 REVISADO (2)'!$U$38 -> 2666.84 | J62: ='REALIZADO 2025'!H82*'PREVISTO 2026 REVISADO (2)'!$U$38 -> 2783.88 | K62: ='REALIZADO 2025'!I82*'PREVISTO 2026 REVISADO (2)'!$U$38 -> 836 | L62: ='REALIZADO 2025'!J82*'PREVISTO 2026 REVISADO (2)'!$U$38 -> 877.8 | M62: ='REALIZADO 2025'!K82*'PREVISTO 2026 REVISADO (2)'!$U$38 -> 1648.4875 | ... Q62: ='REALIZADO 2025'!O82*'PREVISTO 2026 REVISADO (2)'!$U$38 -> 2016.1812 | R62: =SUM(F62:Q62) -> 27564.09 | S62: =R62/12 -> 2297.0075
C63: 2.3.2.5 Portaria Social | F63: ='REALIZADO 2025'!D83*'PREVISTO 2026 REVISADO (2)'!$U$38 -> 1149.5 | G63: ='REALIZADO 2025'!E83*'PREVISTO 2026 REVISADO (2)'!$U$38 -> 1481.5592 | H63: ='REALIZADO 2025'!F83*'PREVISTO 2026 REVISADO (2)'!$U$38 -> 2122.2696 | I63: ='REALIZADO 2025'!G83*'PREVISTO 2026 REVISADO (2)'!$U$38 -> 2265.5914 | J63: ='REALIZADO 2025'!H83*'PREVISTO 2026 REVISADO (2)'!$U$38 -> 1493.2945 | K63: ='REALIZADO 2025'!I83*'PREVISTO 2026 REVISADO (2)'!$U$38 -> 1497.5163 | L63: ='REALIZADO 2025'!J83*'PREVISTO 2026 REVISADO (2)'!$U$38 -> 1918.2438 | M63: ='REALIZADO 2025'!K83*'PREVISTO 2026 REVISADO (2)'!$U$38 -> 2009.5663 | ... Q63: ='REALIZADO 2025'!O83*'PREVISTO 2026 REVISADO (2)'!$U$38 -> 1762.3507 | R63: 35000 | S63: =R63/12 -> 2916.6667
C64: 2.3.2.6 Portaria De Serviço | F64: ='REALIZADO 2025'!D84*'PREVISTO 2026 REVISADO (2)'!$U$38 -> 0 | G64: ='REALIZADO 2025'!E84*'PREVISTO 2026 REVISADO (2)'!$U$38 -> 0 | H64: ='REALIZADO 2025'!F84*'PREVISTO 2026 REVISADO (2)'!$U$38 -> 425.942 | I64: ='REALIZADO 2025'!G84*'PREVISTO 2026 REVISADO (2)'!$U$38 -> 250.8 | J64: ='REALIZADO 2025'!H84*'PREVISTO 2026 REVISADO (2)'!$U$38 -> 0 | K64: ='REALIZADO 2025'!I84*'PREVISTO 2026 REVISADO (2)'!$U$38 -> 78.2705 | L64: ='REALIZADO 2025'!J84*'PREVISTO 2026 REVISADO (2)'!$U$38 -> 1254 | M64: ='REALIZADO 2025'!K84*'PREVISTO 2026 REVISADO (2)'!$U$38 -> 731.5 | ... Q64: ='REALIZADO 2025'!O84*'PREVISTO 2026 REVISADO (2)'!$U$38 -> 0 | R64: =SUM(F64:Q64) -> 2855.4625 | S64: =R64/12 -> 237.95521
C65: 2.3.2.7 Prédio-sala Administrativo-garagem | F65: ='REALIZADO 2025'!D85*'PREVISTO 2026 REVISADO (2)'!$U$38 -> 58.311 | G65: ='REALIZADO 2025'!E85*'PREVISTO 2026 REVISADO (2)'!$U$38 -> 314.336 | H65: ='REALIZADO 2025'!F85*'PREVISTO 2026 REVISADO (2)'!$U$38 -> 0 | I65: ='REALIZADO 2025'!G85*'PREVISTO 2026 REVISADO (2)'!$U$38 -> 776.80075 | J65: ='REALIZADO 2025'!H85*'PREVISTO 2026 REVISADO (2)'!$U$38 -> 23.20945 | K65: ='REALIZADO 2025'!I85*'PREVISTO 2026 REVISADO (2)'!$U$38 -> 0 | L65: ='REALIZADO 2025'!J85*'PREVISTO 2026 REVISADO (2)'!$U$38 -> 3766.18 | M65: ='REALIZADO 2025'!K85*'PREVISTO 2026 REVISADO (2)'!$U$38 -> 282.15 | ... Q65: ='REALIZADO 2025'!O85*'PREVISTO 2026 REVISADO (2)'!$U$38 -> 0 | R65: =SUM(F65:Q65) -> 9779.6743 | S65: =R65/12 -> 814.97286
C66: 2.3.2.8 Poço Artesiano | F66: ='REALIZADO 2025'!D86*'PREVISTO 2026 REVISADO (2)'!$U$38 -> 0 | G66: ='REALIZADO 2025'!E86*'PREVISTO 2026 REVISADO (2)'!$U$38 -> 0 | H66: ='REALIZADO 2025'!F86*'PREVISTO 2026 REVISADO (2)'!$U$38 -> 7315 | I66: ='REALIZADO 2025'!G86*'PREVISTO 2026 REVISADO (2)'!$U$38 -> 1650.055 | J66: ='REALIZADO 2025'!H86*'PREVISTO 2026 REVISADO (2)'!$U$38 -> 0 | K66: ='REALIZADO 2025'!I86*'PREVISTO 2026 REVISADO (2)'!$U$38 -> 0 | L66: ='REALIZADO 2025'!J86*'PREVISTO 2026 REVISADO (2)'!$U$38 -> 0 | M66: ='REALIZADO 2025'!K86*'PREVISTO 2026 REVISADO (2)'!$U$38 -> 0 | ... Q66: ='REALIZADO 2025'!O86*'PREVISTO 2026 REVISADO (2)'!$U$38 -> 0 | R66: =SUM(F66:Q66) -> 9228.395 | S66: =R66/12 -> 769.03292
C67: 2.3.2.9 Cerca Muro | F67: ='REALIZADO 2025'!D87*'PREVISTO 2026 REVISADO (2)'!$U$38 -> 0 | G67: ='REALIZADO 2025'!E87*'PREVISTO 2026 REVISADO (2)'!$U$38 -> 0 | H67: ='REALIZADO 2025'!F87*'PREVISTO 2026 REVISADO (2)'!$U$38 -> 0 | I67: ='REALIZADO 2025'!G87*'PREVISTO 2026 REVISADO (2)'!$U$38 -> 0 | J67: ='REALIZADO 2025'!H87*'PREVISTO 2026 REVISADO (2)'!$U$38 -> 693.82775 | K67: ='REALIZADO 2025'!I87*'PREVISTO 2026 REVISADO (2)'!$U$38 -> 73.28585 | L67: ='REALIZADO 2025'!J87*'PREVISTO 2026 REVISADO (2)'!$U$38 -> 378.34225 | M67: ='REALIZADO 2025'!K87*'PREVISTO 2026 REVISADO (2)'!$U$38 -> 0 | ... Q67: ='REALIZADO 2025'!O87*'PREVISTO 2026 REVISADO (2)'!$U$38 -> 0 | R67: =SUM(F67:Q67) -> 1145.4559 | S67: =R67/12 -> 95.454654
C68: 2.3.3 Máquinas e Equipamentos | F68: =SUM(F69:F71) -> 16132.187 | G68: =SUM(G69:G71) -> 14734.814 | H68: =SUM(H69:H71) -> 13166.112 | I68: =SUM(I69:I71) -> 15843.767 | J68: =SUM(J69:J71) -> 6390.175 | K68: =SUM(K69:K71) -> 10054.99 | L68: =SUM(L69:L71) -> 7028.67 | M68: =SUM(M69:M71) -> 8206.0401 | ... R68: =SUM(R69:R71) -> 95374.689 | S68: =R68/12 -> 7947.8907
C69: 2.3.3.1 Sistema De Segurança | F69: ='REALIZADO 2025'!D89*'PREVISTO 2026 REVISADO (2)'!$U$38 -> 6040.6225 | G69: ='REALIZADO 2025'!E89*'PREVISTO 2026 REVISADO (2)'!$U$38 -> 6040.6225 | H69: ='REALIZADO 2025'!F89*'PREVISTO 2026 REVISADO (2)'!$U$38 -> 5339.95 | I69: ='REALIZADO 2025'!G89*'PREVISTO 2026 REVISADO (2)'!$U$38 -> 7947.225 | J69: ='REALIZADO 2025'!H89*'PREVISTO 2026 REVISADO (2)'!$U$38 -> 6390.175 | K69: ='REALIZADO 2025'!I89*'PREVISTO 2026 REVISADO (2)'!$U$38 -> 5956.5 | L69: ='REALIZADO 2025'!J89*'PREVISTO 2026 REVISADO (2)'!$U$38 -> 3423.42 | M69: ='REALIZADO 2025'!K89*'PREVISTO 2026 REVISADO (2)'!$U$38 -> 5016 | ... Q69: ='REALIZADO 2025'!O89*'PREVISTO 2026 REVISADO (2)'!$U$38 -> 0 | R69: =SUM(F69:Q69) -> 52460.045 | S69: =R69/12 -> 4371.6704
C70: 2.3.3.2 Aparelhos-máquinas-ferramentas-equipamentos | F70: ='REALIZADO 2025'!D90*'PREVISTO 2026 REVISADO (2)'!$U$38 -> 7357.845 | G70: ='REALIZADO 2025'!E90*'PREVISTO 2026 REVISADO (2)'!$U$38 -> 4558.081 | H70: ='REALIZADO 2025'!F90*'PREVISTO 2026 REVISADO (2)'!$U$38 -> 5275.1077 | I70: ='REALIZADO 2025'!G90*'PREVISTO 2026 REVISADO (2)'!$U$38 -> 7008.2925 | J70: ='REALIZADO 2025'!H90*'PREVISTO 2026 REVISADO (2)'!$U$38 -> 0 | K70: ='REALIZADO 2025'!I90*'PREVISTO 2026 REVISADO (2)'!$U$38 -> 2102.54 | L70: ='REALIZADO 2025'!J90*'PREVISTO 2026 REVISADO (2)'!$U$38 -> 606.1 | M70: ='REALIZADO 2025'!K90*'PREVISTO 2026 REVISADO (2)'!$U$38 -> 1864.9801 | ... Q70: ='REALIZADO 2025'!O90*'PREVISTO 2026 REVISADO (2)'!$U$38 -> 1264.3455 | R70: 25000 | S70: =R70/12 -> 2083.3333
C71: 2.3.3.3 Veículo-moto | F71: ='REALIZADO 2025'!D91*'PREVISTO 2026 REVISADO (2)'!$U$38 -> 2733.72 | G71: ='REALIZADO 2025'!E91*'PREVISTO 2026 REVISADO (2)'!$U$38 -> 4136.11 | H71: ='REALIZADO 2025'!F91*'PREVISTO 2026 REVISADO (2)'!$U$38 -> 2551.054 | I71: ='REALIZADO 2025'!G91*'PREVISTO 2026 REVISADO (2)'!$U$38 -> 888.25 | J71: ='REALIZADO 2025'!H91*'PREVISTO 2026 REVISADO (2)'!$U$38 -> 0 | K71: ='REALIZADO 2025'!I91*'PREVISTO 2026 REVISADO (2)'!$U$38 -> 1995.95 | L71: ='REALIZADO 2025'!J91*'PREVISTO 2026 REVISADO (2)'!$U$38 -> 2999.15 | M71: ='REALIZADO 2025'!K91*'PREVISTO 2026 REVISADO (2)'!$U$38 -> 1325.06 | ... Q71: ='REALIZADO 2025'!O91*'PREVISTO 2026 REVISADO (2)'!$U$38 -> 574.75 | R71: =SUM(F71:Q71) -> 17914.644 | S71: =R71/12 -> 1492.887
C72: 2.3.4 Serviços Especializados | F72: =SUM(F73:F77) -> 7920.1595 | G72: =SUM(G73:G77) -> 4267.8636 | H72: =SUM(H73:H77) -> 8104.9364 | I72: =SUM(I73:I77) -> 10998.217 | J72: =SUM(J73:J77) -> 4601.4798 | K72: =SUM(K73:K77) -> 2179.5147 | L72: =SUM(L73:L77) -> 3485.3676 | M72: =SUM(M73:M77) -> 11692.881 | ... R72: =SUM(R73:R77) -> 61500.336 | S72: =R72/12 -> 5125.028
C73: 2.3.4.1 Extintores | F73: ='REALIZADO 2025'!D93*'PREVISTO 2026 REVISADO (2)'!$U$38 -> 909.15 | G73: ='REALIZADO 2025'!E93*'PREVISTO 2026 REVISADO (2)'!$U$38 -> 0 | H73: ='REALIZADO 2025'!F93*'PREVISTO 2026 REVISADO (2)'!$U$38 -> 0 | I73: ='REALIZADO 2025'!G93*'PREVISTO 2026 REVISADO (2)'!$U$38 -> 0 | J73: ='REALIZADO 2025'!H93*'PREVISTO 2026 REVISADO (2)'!$U$38 -> 0 | K73: ='REALIZADO 2025'!I93*'PREVISTO 2026 REVISADO (2)'!$U$38 -> 0 | L73: ='REALIZADO 2025'!J93*'PREVISTO 2026 REVISADO (2)'!$U$38 -> 0 | M73: ='REALIZADO 2025'!K93*'PREVISTO 2026 REVISADO (2)'!$U$38 -> 0 | ... Q73: ='REALIZADO 2025'!O93*'PREVISTO 2026 REVISADO (2)'!$U$38 -> 0 | R73: =SUM(F73:Q73) -> 1018.875 | S73: =R73/12 -> 84.90625
C74: 2.3.4.2 Dedetização-desinsetização-desratização | F74: ='REALIZADO 2025'!D94*'PREVISTO 2026 REVISADO (2)'!$U$38 -> 752.4 | G74: ='REALIZADO 2025'!E94*'PREVISTO 2026 REVISADO (2)'!$U$38 -> 686.1888 | H74: ='REALIZADO 2025'!F94*'PREVISTO 2026 REVISADO (2)'!$U$38 -> 818.6112 | I74: ='REALIZADO 2025'!G94*'PREVISTO 2026 REVISADO (2)'!$U$38 -> 1368.95 | J74: ='REALIZADO 2025'!H94*'PREVISTO 2026 REVISADO (2)'!$U$38 -> 686.1888 | K74: ='REALIZADO 2025'!I94*'PREVISTO 2026 REVISADO (2)'!$U$38 -> 818.6112 | L74: ='REALIZADO 2025'!J94*'PREVISTO 2026 REVISADO (2)'!$U$38 -> 1813.3676 | M74: ='REALIZADO 2025'!K94*'PREVISTO 2026 REVISADO (2)'!$U$38 -> 1575.1912 | ... Q74: ='REALIZADO 2025'!O94*'PREVISTO 2026 REVISADO (2)'!$U$38 -> 852.72 | R74: =SUM(F74:Q74) -> 12477.3 | S74: =R74/12 -> 1039.775
C75: 2.3.4.3 Fossa-caixa De Gordura | F75: ='REALIZADO 2025'!D95*'PREVISTO 2026 REVISADO (2)'!$U$38 -> 2403.5 | G75: ='REALIZADO 2025'!E95*'PREVISTO 2026 REVISADO (2)'!$U$38 -> 545.49 | H75: ='REALIZADO 2025'!F95*'PREVISTO 2026 REVISADO (2)'!$U$38 -> 447.26 | I75: ='REALIZADO 2025'!G95*'PREVISTO 2026 REVISADO (2)'!$U$38 -> 900.69595 | J75: ='REALIZADO 2025'!H95*'PREVISTO 2026 REVISADO (2)'!$U$38 -> 469.19455 | K75: ='REALIZADO 2025'!I95*'PREVISTO 2026 REVISADO (2)'!$U$38 -> 0 | L75: ='REALIZADO 2025'!J95*'PREVISTO 2026 REVISADO (2)'!$U$38 -> 418 | M75: ='REALIZADO 2025'!K95*'PREVISTO 2026 REVISADO (2)'!$U$38 -> 921.69 | ... Q75: ='REALIZADO 2025'!O95*'PREVISTO 2026 REVISADO (2)'!$U$38 -> 516.82565 | R75: =SUM(F75:Q75) -> 8399.9608 | S75: =R75/12 -> 699.99673
C76: 2.3.4.4 Reservatórios De Água | F76: ='REALIZADO 2025'!D96*'PREVISTO 2026 REVISADO (2)'!$U$38 -> 1472.5095 | G76: ='REALIZADO 2025'!E96*'PREVISTO 2026 REVISADO (2)'!$U$38 -> 528.1848 | H76: ='REALIZADO 2025'!F96*'PREVISTO 2026 REVISADO (2)'!$U$38 -> 5585.0652 | I76: ='REALIZADO 2025'!G96*'PREVISTO 2026 REVISADO (2)'!$U$38 -> 6136.9715 | J76: ='REALIZADO 2025'!H96*'PREVISTO 2026 REVISADO (2)'!$U$38 -> 2192.0965 | K76: ='REALIZADO 2025'!I96*'PREVISTO 2026 REVISADO (2)'!$U$38 -> 106.9035 | L76: ='REALIZADO 2025'!J96*'PREVISTO 2026 REVISADO (2)'!$U$38 -> 0 | M76: ='REALIZADO 2025'!K96*'PREVISTO 2026 REVISADO (2)'!$U$38 -> 7942 | ... Q76: ='REALIZADO 2025'!O96*'PREVISTO 2026 REVISADO (2)'!$U$38 -> 428.7635 | R76: 20000 | S76: =R76/12 -> 1666.6667
C77: 2.3.4.5 Análise De Água | F77: ='REALIZADO 2025'!D97*'PREVISTO 2026 REVISADO (2)'!$U$38 -> 2382.6 | G77: ='REALIZADO 2025'!E97*'PREVISTO 2026 REVISADO (2)'!$U$38 -> 2508 | H77: ='REALIZADO 2025'!F97*'PREVISTO 2026 REVISADO (2)'!$U$38 -> 1254 | I77: ='REALIZADO 2025'!G97*'PREVISTO 2026 REVISADO (2)'!$U$38 -> 2591.6 | J77: ='REALIZADO 2025'!H97*'PREVISTO 2026 REVISADO (2)'!$U$38 -> 1254 | K77: ='REALIZADO 2025'!I97*'PREVISTO 2026 REVISADO (2)'!$U$38 -> 1254 | L77: ='REALIZADO 2025'!J97*'PREVISTO 2026 REVISADO (2)'!$U$38 -> 1254 | M77: ='REALIZADO 2025'!K97*'PREVISTO 2026 REVISADO (2)'!$U$38 -> 1254 | ... Q77: ='REALIZADO 2025'!O97*'PREVISTO 2026 REVISADO (2)'!$U$38 -> 1672 | R77: =SUM(F77:Q77) -> 19604.2 | S77: =R77/12 -> 1633.6833
C78: 2.4 Serviços | F78: =SUM(F79:F85) -> 74062.4 | G78: =SUM(G79:G85) -> 69791.715 | H78: =SUM(H79:H85) -> 66502.577 | I78: =SUM(I79:I85) -> 61074.283 | J78: =SUM(J79:J85) -> 83086.623 | K78: =SUM(K79:K85) -> 79588.203 | L78: =SUM(L79:L85) -> 78941.129 | M78: =SUM(M79:M85) -> 79605.331 | ... R78: =SUM(R79:R85) -> 916617.03 | S78: =R78/12 -> 76384.752 | T78: REAJUSTE | U78: 1.045
C79: 2.4.1 Honorários Advocatícios | F79: ='REALIZADO 2025'!D99*'PREVISTO 2026 REVISADO (2)'!$U$78 -> 4117.3 | G79: ='REALIZADO 2025'!E99*'PREVISTO 2026 REVISADO (2)'!$U$78 -> 2058.65 | H79: ='REALIZADO 2025'!F99*'PREVISTO 2026 REVISADO (2)'!$U$78 -> 0 | I79: ='REALIZADO 2025'!G99*'PREVISTO 2026 REVISADO (2)'!$U$78 -> 0 | J79: ='REALIZADO 2025'!H99*'PREVISTO 2026 REVISADO (2)'!$U$78 -> 6667.1 | K79: ='REALIZADO 2025'!I99*'PREVISTO 2026 REVISADO (2)'!$U$78 -> 2304.225 | L79: ='REALIZADO 2025'!J99*'PREVISTO 2026 REVISADO (2)'!$U$78 -> 2304.225 | M79: ='REALIZADO 2025'!K99*'PREVISTO 2026 REVISADO (2)'!$U$78 -> 2304.225 | ... Q79: ='REALIZADO 2025'!O99*'PREVISTO 2026 REVISADO (2)'!$U$78 -> 2304.225 | R79: =SUM(F79:Q79) -> 32003.344 | S79: =R79/12 -> 2666.9454
C80: 2.4.2 Honorários Engenharia | F80: ='REALIZADO 2025'!D100*'PREVISTO 2026 REVISADO (2)'!$U$78 -> 2951.08 | G80: ='REALIZADO 2025'!E100*'PREVISTO 2026 REVISADO (2)'!$U$78 -> 3172.62 | H80: ='REALIZADO 2025'!F100*'PREVISTO 2026 REVISADO (2)'!$U$78 -> 3172.62 | I80: ='REALIZADO 2025'!G100*'PREVISTO 2026 REVISADO (2)'!$U$78 -> 3172.62 | J80: ='REALIZADO 2025'!H100*'PREVISTO 2026 REVISADO (2)'!$U$78 -> 3172.62 | K80: ='REALIZADO 2025'!I100*'PREVISTO 2026 REVISADO (2)'!$U$78 -> 3172.62 | L80: ='REALIZADO 2025'!J100*'PREVISTO 2026 REVISADO (2)'!$U$78 -> 3172.62 | M80: ='REALIZADO 2025'!K100*'PREVISTO 2026 REVISADO (2)'!$U$78 -> 3172.62 | ... Q80: ='REALIZADO 2025'!O100*'PREVISTO 2026 REVISADO (2)'!$U$78 -> 3172.62 | R80: =SUM(F80:Q80) -> 37849.9 | S80: =R80/12 -> 3154.1583
C81: 2.4.3 Honorários Contábeis | F81: ='REALIZADO 2025'!D101*'PREVISTO 2026 REVISADO (2)'!$U$78 -> 4270.2671 | G81: ='REALIZADO 2025'!E101*'PREVISTO 2026 REVISADO (2)'!$U$78 -> 3642.0444 | H81: ='REALIZADO 2025'!F101*'PREVISTO 2026 REVISADO (2)'!$U$78 -> 2614.7885 | I81: ='REALIZADO 2025'!G101*'PREVISTO 2026 REVISADO (2)'!$U$78 -> 2692.4738 | J81: ='REALIZADO 2025'!H101*'PREVISTO 2026 REVISADO (2)'!$U$78 -> 2692.4634 | K81: ='REALIZADO 2025'!I101*'PREVISTO 2026 REVISADO (2)'!$U$78 -> 3530.1667 | L81: ='REALIZADO 2025'!J101*'PREVISTO 2026 REVISADO (2)'!$U$78 -> 2792.24 | M81: ='REALIZADO 2025'!K101*'PREVISTO 2026 REVISADO (2)'!$U$78 -> 3253.085 | ... Q81: ='REALIZADO 2025'!O101*'PREVISTO 2026 REVISADO (2)'!$U$78 -> 4425.0525 | R81: =SUM(F81:Q81) -> 38980.047 | S81: =R81/12 -> 3248.3372
C82: 2.4.4 Segurança- Serviço Vigilância | F82: ='REALIZADO 2025'!D102*'PREVISTO 2026 REVISADO (2)'!$U$78 -> 58965.41 | G82: ='REALIZADO 2025'!E102*'PREVISTO 2026 REVISADO (2)'!$U$78 -> 58988.808 | H82: ='REALIZADO 2025'!F102*'PREVISTO 2026 REVISADO (2)'!$U$78 -> 58988.808 | I82: ='REALIZADO 2025'!G102*'PREVISTO 2026 REVISADO (2)'!$U$78 -> 54895.689 | J82: ='REALIZADO 2025'!H102*'PREVISTO 2026 REVISADO (2)'!$U$78 -> 69237.739 | K82: ='REALIZADO 2025'!I102*'PREVISTO 2026 REVISADO (2)'!$U$78 -> 68417.164 | L82: ='REALIZADO 2025'!J102*'PREVISTO 2026 REVISADO (2)'!$U$78 -> 64109.026 | M82: ='REALIZADO 2025'!K102*'PREVISTO 2026 REVISADO (2)'!$U$78 -> 64109.026 | ... Q82: ='REALIZADO 2025'!O102*'PREVISTO 2026 REVISADO (2)'!$U$78 -> 64109.026 | R82: =SUM(F82:Q82) -> 754147.79 | S82: =R82/12 -> 62845.649
C83: 2.4.5 Cobertura De Férias | F83: ='REALIZADO 2025'!D103*'PREVISTO 2026 REVISADO (2)'!$U$78 -> 0 | G83: ='REALIZADO 2025'!E103*'PREVISTO 2026 REVISADO (2)'!$U$78 -> 0 | H83: ='REALIZADO 2025'!F103*'PREVISTO 2026 REVISADO (2)'!$U$78 -> 0 | I83: ='REALIZADO 2025'!G103*'PREVISTO 2026 REVISADO (2)'!$U$78 -> 0 | J83: ='REALIZADO 2025'!H103*'PREVISTO 2026 REVISADO (2)'!$U$78 -> 0 | K83: ='REALIZADO 2025'!I103*'PREVISTO 2026 REVISADO (2)'!$U$78 -> 0 | L83: ='REALIZADO 2025'!J103*'PREVISTO 2026 REVISADO (2)'!$U$78 -> 0 | M83: ='REALIZADO 2025'!K103*'PREVISTO 2026 REVISADO (2)'!$U$78 -> 5198.875 | ... Q83: ='REALIZADO 2025'!O103*'PREVISTO 2026 REVISADO (2)'!$U$78 -> 0 | R83: =SUM(F83:Q83) -> 10528.375 | S83: =R83/12 -> 877.36458
C84: 2.4.6 Serviços Extras | F84: ='REALIZADO 2025'!D104*'PREVISTO 2026 REVISADO (2)'!$U$78 -> 2508 | G84: ='REALIZADO 2025'!E104*'PREVISTO 2026 REVISADO (2)'!$U$78 -> 679.25 | H84: ='REALIZADO 2025'!F104*'PREVISTO 2026 REVISADO (2)'!$U$78 -> 476.0184 | I84: ='REALIZADO 2025'!G104*'PREVISTO 2026 REVISADO (2)'!$U$78 -> 313.5 | J84: ='REALIZADO 2025'!H104*'PREVISTO 2026 REVISADO (2)'!$U$78 -> 0 | K84: ='REALIZADO 2025'!I104*'PREVISTO 2026 REVISADO (2)'!$U$78 -> 2164.0278 | L84: ='REALIZADO 2025'!J104*'PREVISTO 2026 REVISADO (2)'!$U$78 -> 746.548 | M84: ='REALIZADO 2025'!K104*'PREVISTO 2026 REVISADO (2)'!$U$78 -> 1567.5 | ... Q84: ='REALIZADO 2025'!O104*'PREVISTO 2026 REVISADO (2)'!$U$78 -> 418 | R84: =SUM(F84:Q84) -> 9290.8442 | S84: =R84/12 -> 774.23702
C85: 2.4.7 Eletro-eletrônica-comunicação-sistemas | F85: ='REALIZADO 2025'!D106*'PREVISTO 2026 REVISADO (2)'!$U$78 -> 1250.3425 | G85: ='REALIZADO 2025'!E106*'PREVISTO 2026 REVISADO (2)'!$U$78 -> 1250.3425 | H85: ='REALIZADO 2025'!F106*'PREVISTO 2026 REVISADO (2)'!$U$78 -> 1250.3425 | I85: ='REALIZADO 2025'!G106*'PREVISTO 2026 REVISADO (2)'!$U$78 -> 0 | J85: ='REALIZADO 2025'!H106*'PREVISTO 2026 REVISADO (2)'!$U$78 -> 1316.7 | K85: ='REALIZADO 2025'!I106*'PREVISTO 2026 REVISADO (2)'!$U$78 -> 0 | L85: ='REALIZADO 2025'!J106*'PREVISTO 2026 REVISADO (2)'!$U$78 -> 5816.47 | M85: ='REALIZADO 2025'!K106*'PREVISTO 2026 REVISADO (2)'!$U$78 -> 0 | ... Q85: ='REALIZADO 2025'!O106*'PREVISTO 2026 REVISADO (2)'!$U$78 -> 5016 | R85: =SUM(F85:Q85) -> 33816.722 | S85: =R85/12 -> 2818.0602
C86: 2.5 Consumíveis | F86: =SUM(F87:F96) -> 13871.894 | G86: =SUM(G87:G96) -> 20017.059 | H86: =SUM(H87:H96) -> 18725.418 | I86: =SUM(I87:I96) -> 7115.7603 | J86: =SUM(J87:J96) -> 33776.177 | K86: =SUM(K87:K96) -> 17102.825 | L86: =SUM(L87:L96) -> 16127.475 | M86: =SUM(M87:M96) -> 17502.475 | ... Q86: =SUM(Q87:Q96) -> 9433.4449 | R86: =SUM(R87:R99) -> 167560.8 | S86: =R86/12 -> 13963.4 | T86: REAJUSTE | U86: 1.045
C87: 2.5.1 Energia Elétrica | F87: ='REALIZADO 2025'!D109*'PREVISTO 2026 REVISADO (2)'!$U$86 -> 11147.161 | G87: ='REALIZADO 2025'!E109*'PREVISTO 2026 REVISADO (2)'!$U$86 -> 13803.468 | H87: ='REALIZADO 2025'!F109*'PREVISTO 2026 REVISADO (2)'!$U$86 -> 13427.445 | I87: ='REALIZADO 2025'!G109*'PREVISTO 2026 REVISADO (2)'!$U$86 -> 0 | J87: ='REALIZADO 2025'!H109*'PREVISTO 2026 REVISADO (2)'!$U$86 -> 28468.81 | K87: ='REALIZADO 2025'!I109*'PREVISTO 2026 REVISADO (2)'!$U$86 -> 12181.69 | L87: ='REALIZADO 2025'!J109*'PREVISTO 2026 REVISADO (2)'!$U$86 -> 11368.022 | M87: ='REALIZADO 2025'!K109*'PREVISTO 2026 REVISADO (2)'!$U$86 -> 12092.416 | ... Q87: ='REALIZADO 2025'!O109*'PREVISTO 2026 REVISADO (2)'!$U$86 -> 3925.4798 | R87: 70000 | S87: =R87/12 -> 5833.3333
C88: 2.5.2 Semasa-esgoto | F88: ='REALIZADO 2025'!D113*'PREVISTO 2026 REVISADO (2)'!$U$86 -> 0 | G88: ='REALIZADO 2025'!E113*'PREVISTO 2026 REVISADO (2)'!$U$86 -> 2439.7824 | H88: ='REALIZADO 2025'!F113*'PREVISTO 2026 REVISADO (2)'!$U$86 -> 2439.7824 | I88: ='REALIZADO 2025'!G113*'PREVISTO 2026 REVISADO (2)'!$U$86 -> 2439.7824 | J88: ='REALIZADO 2025'!H113*'PREVISTO 2026 REVISADO (2)'!$U$86 -> 2439.7824 | K88: ='REALIZADO 2025'!I113*'PREVISTO 2026 REVISADO (2)'!$U$86 -> 2439.7824 | L88: ='REALIZADO 2025'!J113*'PREVISTO 2026 REVISADO (2)'!$U$86 -> 2439.7824 | M88: ='REALIZADO 2025'!K113*'PREVISTO 2026 REVISADO (2)'!$U$86 -> 2439.7824 | ... Q88: ='REALIZADO 2025'!O113*'PREVISTO 2026 REVISADO (2)'!$U$86 -> 2649.4512 | R88: =SUM(F88:Q88) -> 27256.944 | S88: =R88/12 -> 2271.412
C89: 2.5.3 Telefone Fixo | F89: ='REALIZADO 2025'!D114*'PREVISTO 2026 REVISADO (2)'!$U$86 -> 102.8489 | G89: ='REALIZADO 2025'!E114*'PREVISTO 2026 REVISADO (2)'!$U$86 -> 105.09565 | H89: ='REALIZADO 2025'!F114*'PREVISTO 2026 REVISADO (2)'!$U$86 -> 104.92845 | I89: ='REALIZADO 2025'!G114*'PREVISTO 2026 REVISADO (2)'!$U$86 -> 104.92845 | J89: ='REALIZADO 2025'!H114*'PREVISTO 2026 REVISADO (2)'!$U$86 -> 102.8489 | K89: ='REALIZADO 2025'!I114*'PREVISTO 2026 REVISADO (2)'!$U$86 -> 0 | L89: ='REALIZADO 2025'!J114*'PREVISTO 2026 REVISADO (2)'!$U$86 -> 102.8489 | M89: ='REALIZADO 2025'!K114*'PREVISTO 2026 REVISADO (2)'!$U$86 -> 102.8489 | ... Q89: ='REALIZADO 2025'!O114*'PREVISTO 2026 REVISADO (2)'!$U$86 -> 92.2735 | R89: =SUM(F89:Q89) -> 1127.1683 | S89: =R89/12 -> 93.930696
C90: 2.5.4 Telefone Móvel | F90: ='REALIZADO 2025'!D115*'PREVISTO 2026 REVISADO (2)'!$U$86 -> 208.98955 | G90: ='REALIZADO 2025'!E115*'PREVISTO 2026 REVISADO (2)'!$U$86 -> 594.6677 | H90: ='REALIZADO 2025'!F115*'PREVISTO 2026 REVISADO (2)'!$U$86 -> 188.3926 | I90: ='REALIZADO 2025'!G115*'PREVISTO 2026 REVISADO (2)'!$U$86 -> 619.476 | J90: ='REALIZADO 2025'!H115*'PREVISTO 2026 REVISADO (2)'!$U$86 -> 411.88675 | K90: ='REALIZADO 2025'!I115*'PREVISTO 2026 REVISADO (2)'!$U$86 -> 197.4841 | L90: ='REALIZADO 2025'!J115*'PREVISTO 2026 REVISADO (2)'!$U$86 -> 312.36095 | M90: ='REALIZADO 2025'!K115*'PREVISTO 2026 REVISADO (2)'!$U$86 -> 0 | ... Q90: ='REALIZADO 2025'!O115*'PREVISTO 2026 REVISADO (2)'!$U$86 -> 88.62645 | R90: =SUM(F90:Q90) -> 3469.6613 | S90: =R90/12 -> 289.13844
C92: 2.5.5 Tv a Cabo | F92: ='REALIZADO 2025'!D116*'PREVISTO 2026 REVISADO (2)'!$U$86 -> 0 | G92: ='REALIZADO 2025'!E116*'PREVISTO 2026 REVISADO (2)'!$U$86 -> 128.21105 | H92: ='REALIZADO 2025'!F116*'PREVISTO 2026 REVISADO (2)'!$U$86 -> 256.4221 | I92: ='REALIZADO 2025'!G116*'PREVISTO 2026 REVISADO (2)'!$U$86 -> 9.54085 | J92: ='REALIZADO 2025'!H116*'PREVISTO 2026 REVISADO (2)'!$U$86 -> 128.21105 | K92: ='REALIZADO 2025'!I116*'PREVISTO 2026 REVISADO (2)'!$U$86 -> 140.35395 | L92: ='REALIZADO 2025'!J116*'PREVISTO 2026 REVISADO (2)'!$U$86 -> 0 | M92: ='REALIZADO 2025'!K116*'PREVISTO 2026 REVISADO (2)'!$U$86 -> 335.35095 | ... Q92: ='REALIZADO 2025'!O116*'PREVISTO 2026 REVISADO (2)'!$U$86 -> 140.9078 | R92: =SUM(F92:Q92) -> 1560.9269 | S92: =R92/12 -> 130.07725
C93: 2.5.6 Internet | F93: ='REALIZADO 2025'!D117*'PREVISTO 2026 REVISADO (2)'!$U$86 -> 101.25005 | G93: ='REALIZADO 2025'!E117*'PREVISTO 2026 REVISADO (2)'!$U$86 -> 101.25005 | H93: ='REALIZADO 2025'!F117*'PREVISTO 2026 REVISADO (2)'!$U$86 -> 101.25005 | I93: ='REALIZADO 2025'!G117*'PREVISTO 2026 REVISADO (2)'!$U$86 -> 101.25005 | J93: ='REALIZADO 2025'!H117*'PREVISTO 2026 REVISADO (2)'!$U$86 -> 0 | K93: ='REALIZADO 2025'!I117*'PREVISTO 2026 REVISADO (2)'!$U$86 -> 550.70455 | L93: ='REALIZADO 2025'!J117*'PREVISTO 2026 REVISADO (2)'!$U$86 -> 137.7519 | M93: ='REALIZADO 2025'!K117*'PREVISTO 2026 REVISADO (2)'!$U$86 -> 352.46805 | ... Q93: ='REALIZADO 2025'!O117*'PREVISTO 2026 REVISADO (2)'!$U$86 -> 308.93335 | R93: =SUM(F93:Q93) -> 2371.5334 | S93: =R93/12 -> 197.62779
C94: 2.5.7 Hospedagem Site - E-mail | F94: ='REALIZADO 2025'!D118*'PREVISTO 2026 REVISADO (2)'!$U$86 -> 36.4705 | G94: ='REALIZADO 2025'!E118*'PREVISTO 2026 REVISADO (2)'!$U$86 -> 36.4705 | H94: ='REALIZADO 2025'!F118*'PREVISTO 2026 REVISADO (2)'!$U$86 -> 36.4705 | I94: ='REALIZADO 2025'!G118*'PREVISTO 2026 REVISADO (2)'!$U$86 -> 36.4705 | J94: ='REALIZADO 2025'!H118*'PREVISTO 2026 REVISADO (2)'!$U$86 -> 36.4705 | K94: ='REALIZADO 2025'!I118*'PREVISTO 2026 REVISADO (2)'!$U$86 -> 0 | L94: ='REALIZADO 2025'!J118*'PREVISTO 2026 REVISADO (2)'!$U$86 -> 36.4705 | M94: ='REALIZADO 2025'!K118*'PREVISTO 2026 REVISADO (2)'!$U$86 -> 36.4705 | ... Q94: ='REALIZADO 2025'!O118*'PREVISTO 2026 REVISADO (2)'!$U$86 -> 36.4705 | R94: =SUM(F94:Q94) -> 401.1755 | S94: =R94/12 -> 33.431292
C95: 2.5.8 Gás | F95: ='REALIZADO 2025'!D119*'PREVISTO 2026 REVISADO (2)'!$U$86 -> 762.85 | G95: ='REALIZADO 2025'!E119*'PREVISTO 2026 REVISADO (2)'!$U$86 -> 0 | H95: ='REALIZADO 2025'!F119*'PREVISTO 2026 REVISADO (2)'!$U$86 -> 0 | I95: ='REALIZADO 2025'!G119*'PREVISTO 2026 REVISADO (2)'!$U$86 -> 893.475 | J95: ='REALIZADO 2025'!H119*'PREVISTO 2026 REVISADO (2)'!$U$86 -> 0 | K95: ='REALIZADO 2025'!I119*'PREVISTO 2026 REVISADO (2)'!$U$86 -> 0 | L95: ='REALIZADO 2025'!J119*'PREVISTO 2026 REVISADO (2)'!$U$86 -> 0 | M95: ='REALIZADO 2025'!K119*'PREVISTO 2026 REVISADO (2)'!$U$86 -> 893.475 | ... Q95: ='REALIZADO 2025'!O119*'PREVISTO 2026 REVISADO (2)'!$U$86 -> 0 | R95: =SUM(F95:Q95) -> 3443.275 | S95: =R95/12 -> 286.93958
C96: 2.5.9 Combustível | F96: ='REALIZADO 2025'!D120*'PREVISTO 2026 REVISADO (2)'!$U$86 -> 1512.324 | G96: ='REALIZADO 2025'!E120*'PREVISTO 2026 REVISADO (2)'!$U$86 -> 2808.1136 | H96: ='REALIZADO 2025'!F120*'PREVISTO 2026 REVISADO (2)'!$U$86 -> 2170.7262 | I96: ='REALIZADO 2025'!G120*'PREVISTO 2026 REVISADO (2)'!$U$86 -> 2910.837 | J96: ='REALIZADO 2025'!H120*'PREVISTO 2026 REVISADO (2)'!$U$86 -> 2188.1673 | K96: ='REALIZADO 2025'!I120*'PREVISTO 2026 REVISADO (2)'!$U$86 -> 1592.8099 | L96: ='REALIZADO 2025'!J120*'PREVISTO 2026 REVISADO (2)'!$U$86 -> 1730.2378 | M96: ='REALIZADO 2025'!K120*'PREVISTO 2026 REVISADO (2)'!$U$86 -> 1249.6632 | ... Q96: ='REALIZADO 2025'!O120*'PREVISTO 2026 REVISADO (2)'!$U$86 -> 2191.3023 | R96: =SUM(F96:Q96) -> 24092.621 | S96: =R96/12 -> 2007.7184
C97: 2.5.10 Material De Limpeza | F97: ='REALIZADO 2025'!D110*'PREVISTO 2026 REVISADO (2)'!$U$86 -> 1863.7366 | G97: ='REALIZADO 2025'!E110*'PREVISTO 2026 REVISADO (2)'!$U$86 -> 1517.8625 | H97: ='REALIZADO 2025'!F110*'PREVISTO 2026 REVISADO (2)'!$U$86 -> 2064.8155 | I97: ='REALIZADO 2025'!G110*'PREVISTO 2026 REVISADO (2)'!$U$86 -> 2181.124 | J97: ='REALIZADO 2025'!H110*'PREVISTO 2026 REVISADO (2)'!$U$86 -> 1091.8264 | K97: ='REALIZADO 2025'!I110*'PREVISTO 2026 REVISADO (2)'!$U$86 -> 2025.4085 | L97: ='REALIZADO 2025'!J110*'PREVISTO 2026 REVISADO (2)'!$U$86 -> 5704.5505 | M97: ='REALIZADO 2025'!K110*'PREVISTO 2026 REVISADO (2)'!$U$86 -> 2946.691 | ... Q97: ='REALIZADO 2025'!O110*'PREVISTO 2026 REVISADO (2)'!$U$86 -> 1340.735 | R97: 24000 | S97: =R97/12 -> 2000
C98: 2.5.11 Pomar-reciclagem | F98: ='REALIZADO 2025'!D111*'PREVISTO 2026 REVISADO (2)'!$U$86 -> 0 | G98: ='REALIZADO 2025'!E111*'PREVISTO 2026 REVISADO (2)'!$U$86 -> 0 | H98: ='REALIZADO 2025'!F111*'PREVISTO 2026 REVISADO (2)'!$U$86 -> 276.1935 | I98: ='REALIZADO 2025'!G111*'PREVISTO 2026 REVISADO (2)'!$U$86 -> 64.31975 | J98: ='REALIZADO 2025'!H111*'PREVISTO 2026 REVISADO (2)'!$U$86 -> 0 | K98: ='REALIZADO 2025'!I111*'PREVISTO 2026 REVISADO (2)'!$U$86 -> 1661.55 | L98: ='REALIZADO 2025'!J111*'PREVISTO 2026 REVISADO (2)'!$U$86 -> 852.72 | M98: ='REALIZADO 2025'!K111*'PREVISTO 2026 REVISADO (2)'!$U$86 -> 2309.45 | ... Q98: ='REALIZADO 2025'!O111*'PREVISTO 2026 REVISADO (2)'!$U$86 -> 0 | R98: =SUM(F98:Q98) -> 8386.8251 | S98: =R98/12 -> 698.9021
C99: 2.5.12 Açúde | F99: ='REALIZADO 2025'!D112*'PREVISTO 2026 REVISADO (2)'!$U$86 -> 169.6035 | G99: ='REALIZADO 2025'!E112*'PREVISTO 2026 REVISADO (2)'!$U$86 -> 366.32475 | H99: ='REALIZADO 2025'!F112*'PREVISTO 2026 REVISADO (2)'!$U$86 -> 196.72125 | I99: ='REALIZADO 2025'!G112*'PREVISTO 2026 REVISADO (2)'!$U$86 -> 169.6035 | J99: ='REALIZADO 2025'!H112*'PREVISTO 2026 REVISADO (2)'!$U$86 -> 169.6035 | K99: ='REALIZADO 2025'!I112*'PREVISTO 2026 REVISADO (2)'!$U$86 -> 0 | L99: ='REALIZADO 2025'!J112*'PREVISTO 2026 REVISADO (2)'!$U$86 -> 0 | M99: ='REALIZADO 2025'!K112*'PREVISTO 2026 REVISADO (2)'!$U$86 -> 182.5615 | ... Q99: ='REALIZADO 2025'!O112*'PREVISTO 2026 REVISADO (2)'!$U$86 -> 0 | R99: =SUM(F99:Q99) -> 1450.669 | S99: =R99/12 -> 120.88908
C101: TOTAL GERAL DESPESAS | F101: =F4 -> #REF! | G101: =G4 -> #REF! | H101: =H4 -> #REF! | I101: =I4 -> #REF! | J101: =J4 -> #REF! | K101: =K4 -> #REF! | L101: =L4 -> #REF! | M101: =M4 -> #REF! | ... Q101: =Q4 -> #REF! | R101: =R86+R78+R38+R22+R5 -> 3409357.7 | S101: =R101/12 -> 284113.14
C103: Previsão Mensal 2025 | E103: 270297.34
...

Sheet PREVISTO 2026
D1: Dezembro | E1: Janeiro | F1: Fevereiro | G1: Março | H1: Abril | I1: Maio | J1: Junho | K1: Julho | L1: Agosto | M1: Setembro | N1: Outubro | O1: Novembro | P1: Total | Q1: Média
A2: 1 Receitas | D2: =SUM(D3:D24) -> 290185.65 | E2: =SUM(E3:E24) -> 308732.3 | F2: =SUM(F3:F24) -> 313677.08 | G2: =SUM(G3:G24) -> 309911.84 | H2: =SUM(H3:H24) -> 316572.56 | I2: =SUM(I3:I24) -> 290740.15 | J2: =SUM(J3:J24) -> 318477.94 | K2: =SUM(K3:K24) -> 363077.67 | ... O2: =SUM(O3:O24) -> 341763.38 | P2: =SUM(D2:O2) -> 3896477.6 | Q2: =P2/12 -> 324706.47
A3: 1.1 Taxa Condominial | D3: 239580.04 | E3: 253005.09 | F3: 265582.35 | G3: 262254.65 | H3: 263648.06 | I3: 255243.67 | J3: 276285.49 | K3: 278926.44 | L3: 289938.72 | M3: 267854.46 | N3: 263900.09 | O3: 284892.08 | P3: =SUM(D3:O3) -> 3201111.1 | Q3: =P3/12 -> 266759.26
A4: 1.10 Rendimentos | D4: 8221.95 | E4: 12462.57 | F4: 8020.57 | G4: 9758.01 | H4: 14865.92 | I4: 131.75 | J4: 1440.44 | K4: 750.81 | L4: 6352.3 | M4: 19987.08 | N4: 6970.17 | O4: 4858.56 | P4: =SUM(D4:O4) -> 93820.13 | Q4: =P4/12 -> 7818.3442
A5: 1.11 Liberação Obra | D5: 0 | E5: 0 | F5: 0 | G5: 0 | H5: 0 | I5: 0 | J5: 0 | K5: 1379.6 | L5: 2950.48 | M5: 1379.6 | N5: 0 | O5: 0 | P5: =SUM(D5:O5) -> 5709.68 | Q5: =P5/12 -> 475.80667
A6: 1.12 Honorário Advocatício | D6: 0 | E6: 0 | F6: 0 | G6: 0 | H6: 0 | I6: 0 | J6: 1458.91 | K6: 0 | L6: 3358.15 | M6: 0 | N6: 0 | O6: 686.92 | P6: =SUM(D6:O6) -> 5503.98 | Q6: =P6/12 -> 458.665
A7: 1.13 Pagamentos a Menor | D7: 0 | E7: 0 | F7: 0 | G7: 0 | H7: -10.85 | I7: 0 | J7: 10.85 | K7: 0 | L7: 0 | M7: 0 | N7: 0 | O7: 0 | P7: =SUM(D7:O7) -> 0 | Q7: =P7/12 -> 0
A8: 1.17 Taxa Salão Bosque | D8: 525 | E8: 1050 | F8: 0 | G8: 1050 | H8: 1050 | I8: 0 | J8: 0 | K8: 1050 | L8: 525 | M8: 0 | N8: 0 | O8: 0 | P8: =SUM(D8:O8) -> 5250 | Q8: =P8/12 -> 437.5
A9: 1.18 Taxa Salão Piscina | D9: 1260 | E9: 1260 | F9: 3150 | G9: 1680 | H9: 1470 | I9: 1680 | J9: 420 | K9: 1680 | L9: 1218 | M9: 1890 | N9: 1470 | O9: 882 | P9: =SUM(D9:O9) -> 18060 | Q9: =P9/12 -> 1505
A10: 1.19 Taxa Salão Pub | D10: 1706.95 | E10: 2126.95 | F10: 0 | G10: 1916.95 | H10: 1496.95 | I10: 1050 | J10: 1890 | K10: 1050 | L10: 1680 | M10: 2520 | N10: 1470 | O10: 1470 | P10: =SUM(D10:O10) -> 18377.8 | Q10: =P10/12 -> 1531.4833
A11: 1.2 Fundo De Reserva | D11: 23926.35 | E11: 25269.43 | F11: 26519.07 | G11: 26186.3 | H11: 26325.65 | I11: 25485.2 | J11: 27589.36 | K11: 27853.49 | L11: 28954.69 | M11: 26746.27 | N11: 26277.64 | O11: 28063.87 | P11: =SUM(D11:O11) -> 319197.32 | Q11: =P11/12 -> 26599.777
A12: 1.20 Taxa Quiosque | D12: 150 | E12: 250 | F12: 150 | G12: 450 | H12: 200 | I12: 250 | J12: 200 | K12: 100 | L12: 100 | M12: 300 | N12: 150 | O12: 0 | P12: =SUM(D12:O12) -> 2300 | Q12: =P12/12 -> 191.66667
A13: 1.21 Taxa Campo Futebol | D13: 0 | E13: 0 | F13: 1800 | G13: 0 | H13: 800 | I13: 1700 | J13: 1900 | K13: 1800 | L13: 1400 | M13: 1400 | N13: 1200 | O13: 1200 | P13: =SUM(D13:O13) -> 13200 | Q13: =P13/12 -> 1100
A14: 1.23 Ressarcimento Utensílios-danos | D14: 317.67 | E14: 447.46 | F14: 419.33 | G14: 489.74 | H14: 439.72 | I14: 21.99 | J14: 111.24 | K14: 631.29 | L14: 196.05 | M14: 326.5 | N14: 57.39 | O14: 0 | P14: =SUM(D14:O14) -> 3458.38 | Q14: =P14/12 -> 288.19833
... A24: 1.9 Atualização Monetária | D24: 164.67 | E24: 211.09 | F24: 253.21 | G24: 64.91 | H24: 75.54 | I24: 0 | J24: 297.41 | K24: 23.96 | L24: 688.42 | M24: 50.05 | N24: 0 | O24: 49.94 | P24: =SUM(D24:O24) -> 1879.2 | Q24: =P24/12 -> 156.6
A25: TOTAL GERAL RECEITAS | D25: =D2 -> 290185.65 | E25: =E2 -> 308732.3 | F25: =F2 -> 313677.08 | G25: =G2 -> 309911.84 | H25: =H2 -> 316572.56 | I25: =I2 -> 290740.15 | J25: =J2 -> 318477.94 | K25: =K2 -> 363077.67 | ... O25: =O2 -> 341763.38 | P25: =SUM(D25:O25) -> 3896477.6 | Q25: =P25/12 -> 324706.47
A27: 2 Despesas | D27: =D28+D45+D61+D102+D110+D123 -> 302630.67 | E27: =E28+E45+E61+E102+E110+E123 -> 252297.15 | F27: =F28+F45+F61+F102+F110+F123 -> 311244 | G27: =G28+G45+G61+G102+G110+G123 -> 270394.26 | H27: =H28+H45+H61+H102+H110+H123 -> 305090.9 | I27: =I28+I45+I61+I102+I110+I123 -> 321672.91 | J27: =J28+J45+J61+J102+J110+J123 -> 296836.26 | K27: =K28+K45+K61+K102+K110+K123 -> 265450.16 | ... O27: =O28+O45+O61+O102+O110+O123 -> 278154.67 | P27: =SUM(D27:O27) -> 3442718.4 | Q27: =P27/12 -> 286893.2 | R27: REAJUSTE | S27: 1.045 | T27: 0.045
A28: 2.1 Administrativas | D28: =SUM(D29:D44) -> 9137.3607 | E28: =SUM(E29:E44) -> 8418.0037 | F28: =SUM(F29:F44) -> 83898.212 | G28: =SUM(G29:G44) -> 11787.819 | H28: =SUM(H29:H44) -> 9820.2203 | I28: =SUM(I29:I44) -> 11732.215 | J28: =SUM(J29:J44) -> 11683.814 | K28: =SUM(K29:K44) -> 10756.028 | ... P28: =SUM(P29:P44) -> 203286.84 | Q28: =P28/12 -> 16940.57
A29: 2.1.1 Despesas Bancárias | D29: 34 | E29: 34 | F29: ='REALIZADO 2025'!F28*'PREVISTO 2026'!$S$27 -> 82.54455 | G29: ='REALIZADO 2025'!G28*'PREVISTO 2026'!$S$27 -> 62.06255 | H29: ='REALIZADO 2025'!H28*'PREVISTO 2026'!$S$27 -> 101.5949 | I29: ='REALIZADO 2025'!I28*'PREVISTO 2026'!$S$27 -> 39.6055 | J29: 35 | K29: ='REALIZADO 2025'!K28*'PREVISTO 2026'!$S$27 -> 33.3355 | L29: ='REALIZADO 2025'!L28*'PREVISTO 2026'!$S$27 -> 33.3355 | M29: ='REALIZADO 2025'!M28*'PREVISTO 2026'!$S$27 -> 34.3805 | N29: ='REALIZADO 2025'!N28*'PREVISTO 2026'!$S$27 -> 31.2455 | O29: ='REALIZADO 2025'!O28*'PREVISTO 2026'!$S$27 -> 31.5172 | P29: =SUM(D29:O29) -> 552.6217 | Q29: =P29/12 -> 46.051808
A30: 2.1.11 Reuniões-treinamentos | D30: ='REALIZADO 2025'!D29*'PREVISTO 2026'!$S$27 -> 0 | E30: ='REALIZADO 2025'!E29*'PREVISTO 2026'!$S$27 -> 0 | F30: ='REALIZADO 2025'!F29*'PREVISTO 2026'!$S$27 -> 196.34505 | G30: ='REALIZADO 2025'!G29*'PREVISTO 2026'!$S$27 -> 0 | H30: ='REALIZADO 2025'!H29*'PREVISTO 2026'!$S$27 -> 0 | I30: ='REALIZADO 2025'!I29*'PREVISTO 2026'!$S$27 -> 0 | J30: ='REALIZADO 2025'!J29*'PREVISTO 2026'!$S$27 -> 415.91 | K30: ='REALIZADO 2025'!K29*'PREVISTO 2026'!$S$27 -> 176.5423 | ... O30: ='REALIZADO 2025'!O29*'PREVISTO 2026'!$S$27 -> 0 | P30: =SUM(D30:O30) -> 1213.4853 | Q30: =P30/12 -> 101.12378
A31: 2.1.12 Certificado Digital | D31: ='REALIZADO 2025'!D30*'PREVISTO 2026'!$S$27 -> 0 | E31: ='REALIZADO 2025'!E30*'PREVISTO 2026'!$S$27 -> 0 | F31: ='REALIZADO 2025'!F30*'PREVISTO 2026'!$S$27 -> 0 | G31: ='REALIZADO 2025'!G30*'PREVISTO 2026'!$S$27 -> 0 | H31: ='REALIZADO 2025'!H30*'PREVISTO 2026'!$S$27 -> 187.65065 | I31: ='REALIZADO 2025'!I30*'PREVISTO 2026'!$S$27 -> 0 | J31: ='REALIZADO 2025'!J30*'PREVISTO 2026'!$S$27 -> 0 | K31: ='REALIZADO 2025'!K30*'PREVISTO 2026'!$S$27 -> 0 | ... O31: ='REALIZADO 2025'!O30*'PREVISTO 2026'!$S$27 -> 0 | P31: =SUM(D31:O31) -> 396.65065 | Q31: =P31/12 -> 33.054221
A32: 2.1.14 Outros-não Previstos | D32: ='REALIZADO 2025'!D31*'PREVISTO 2026'!$S$27 -> 0 | E32: ='REALIZADO 2025'!E31*'PREVISTO 2026'!$S$27 -> 0 | F32: ='REALIZADO 2025'!F31*'PREVISTO 2026'!$S$27 -> 0 | G32: ='REALIZADO 2025'!G31*'PREVISTO 2026'!$S$27 -> 2612.5 | H32: ='REALIZADO 2025'!H31*'PREVISTO 2026'!$S$27 -> 0 | I32: ='REALIZADO 2025'!I31*'PREVISTO 2026'!$S$27 -> 0 | J32: ='REALIZADO 2025'!J31*'PREVISTO 2026'!$S$27 -> 0 | K32: ='REALIZADO 2025'!K31*'PREVISTO 2026'!$S$27 -> 0 | ... O32: ='REALIZADO 2025'!O31*'PREVISTO 2026'!$S$27 -> 0 | P32: =SUM(D32:O32) -> 2612.5 | Q32: =P32/12 -> 217.70833
A33: 2.1.19 Alvará De Funcionamento | D33: ='REALIZADO 2025'!D34*'PREVISTO 2026'!$S$27 -> 0 | E33: ='REALIZADO 2025'!E34*'PREVISTO 2026'!$S$27 -> 0 | F33: ='REALIZADO 2025'!F34*'PREVISTO 2026'!$S$27 -> 0 | G33: ='REALIZADO 2025'!G34*'PREVISTO 2026'!$S$27 -> 0 | H33: ='REALIZADO 2025'!H34*'PREVISTO 2026'!$S$27 -> 0 | I33: ='REALIZADO 2025'!I34*'PREVISTO 2026'!$S$27 -> 621.4824 | J33: ='REALIZADO 2025'!J34*'PREVISTO 2026'!$S$27 -> 0 | K33: ='REALIZADO 2025'!K34*'PREVISTO 2026'!$S$27 -> 0 | ... O33: ='REALIZADO 2025'!O34*'PREVISTO 2026'!$S$27 -> 0 | P33: =SUM(D33:O33) -> 621.4824 | Q33: =P33/12 -> 51.7902
A34: 2.1.2 Material De Expediente-correio | D34: ='REALIZADO 2025'!D35*'PREVISTO 2026'!$S$27 -> 372.17675 | E34: ='REALIZADO 2025'!E35*'PREVISTO 2026'!$S$27 -> 365.75 | F34: ='REALIZADO 2025'!F35*'PREVISTO 2026'!$S$27 -> 937.0515 | G34: ='REALIZADO 2025'!G35*'PREVISTO 2026'!$S$27 -> 510.43025 | H34: ='REALIZADO 2025'!H35*'PREVISTO 2026'!$S$27 -> 320.76275 | I34: ='REALIZADO 2025'!I35*'PREVISTO 2026'!$S$27 -> 403.37 | J34: ='REALIZADO 2025'!J35*'PREVISTO 2026'!$S$27 -> 1135.706 | K34: ='REALIZADO 2025'!K35*'PREVISTO 2026'!$S$27 -> 406.45275 | ... O34: ='REALIZADO 2025'!O35*'PREVISTO 2026'!$S$27 -> 328.757 | P34: =SUM(D34:O34) -> 7239.9167 | Q34: =P34/12 -> 603.3264
A35: 2.1.21 Sistema De Reservas On-line | D35: ='REALIZADO 2025'!D36*'PREVISTO 2026'!$S$27 -> 522.5 | E35: ='REALIZADO 2025'!E36*'PREVISTO 2026'!$S$27 -> 0 | F35: ='REALIZADO 2025'!F36*'PREVISTO 2026'!$S$27 -> 522.5 | G35: ='REALIZADO 2025'!G36*'PREVISTO 2026'!$S$27 -> 522.5 | H35: ='REALIZADO 2025'!H36*'PREVISTO 2026'!$S$27 -> 522.5 | I35: ='REALIZADO 2025'!I36*'PREVISTO 2026'!$S$27 -> 522.5 | J35: ='REALIZADO 2025'!J36*'PREVISTO 2026'!$S$27 -> 0 | K35: ='REALIZADO 2025'!K36*'PREVISTO 2026'!$S$27 -> 522.5 | ... O35: ='REALIZADO 2025'!O36*'PREVISTO 2026'!$S$27 -> 0 | P35: =SUM(D35:O35) -> 4702.5 | Q35: =P35/12 -> 391.875
A36: 2.1.22 Material Expediente- Impressões/Digitalizações/Encadernação/Envelopes | D36: ='REALIZADO 2025'!D37*'PREVISTO 2026'!$S$27 -> 0 | E36: ='REALIZADO 2025'!E37*'PREVISTO 2026'!$S$27 -> 0 | F36: ='REALIZADO 2025'!F37*'PREVISTO 2026'!$S$27 -> 0 | G36: ='REALIZADO 2025'!G37*'PREVISTO 2026'!$S$27 -> 0 | H36: ='REALIZADO 2025'!H37*'PREVISTO 2026'!$S$27 -> 0 | I36: ='REALIZADO 2025'!I37*'PREVISTO 2026'!$S$27 -> 0 | J36: ='REALIZADO 2025'!J37*'PREVISTO 2026'!$S$27 -> 0 | K36: ='REALIZADO 2025'!K37*'PREVISTO 2026'!$S$27 -> 0 | ... O36: ='REALIZADO 2025'!O37*'PREVISTO 2026'!$S$27 -> 1418.4307 | P36: =SUM(D36:O36) -> 1418.4307 | Q36: =P36/12 -> 118.20256
A37: 2.1.3 Honorário Síndico | D37: =5043.17*$S$27 -> 5270.1127 | E37: =5043.17*$S$27 -> 5270.1127 | F37: =5043.17*$S$27 -> 5270.1127 | G37: =5043.17*$S$27 -> 5270.1127 | H37: =5043.17*$S$27 -> 5270.1127 | I37: =5043.17*$S$27 -> 5270.1127 | J37: =5043.17*$S$27 -> 5270.1127 | K37: =5043.17*$S$27 -> 5270.1127 | ... O37: =5043.17*$S$27 -> 5270.1127 | P37: =SUM(D37:O37) -> 63241.352 | Q37: =P37/12 -> 5270.1127
A38: 2.1.4 Inss-ir-síndico | D38: =2570.4*$S$27 -> 2686.068 | E38: =2570.4*$S$27 -> 2686.068 | F38: =2570.4*$S$27 -> 2686.068 | G38: =2570.4*$S$27 -> 2686.068 | H38: =2570.4*$S$27 -> 2686.068 | I38: =2570.4*$S$27 -> 2686.068 | J38: =2570.4*$S$27 -> 2686.068 | K38: =2570.4*$S$27 -> 2686.068 | ... O38: =2570.4*$S$27 -> 2686.068 | P38: =SUM(D38:O38) -> 32232.816 | Q38: =P38/12 -> 2686.068
A39: 2.1.5 Iptu | D39: ='REALIZADO 2025'!D40*'PREVISTO 2026'!$S$27 -> 0 | E39: ='REALIZADO 2025'!E40*'PREVISTO 2026'!$S$27 -> 0 | F39: ='REALIZADO 2025'!F40*'PREVISTO 2026'!$S$27 -> 68382.052 | G39: ='REALIZADO 2025'!G40*'PREVISTO 2026'!$S$27 -> 0 | H39: ='REALIZADO 2025'!H40*'PREVISTO 2026'!$S$27 -> 0 | I39: ='REALIZADO 2025'!I40*'PREVISTO 2026'!$S$27 -> 0 | J39: ='REALIZADO 2025'!J40*'PREVISTO 2026'!$S$27 -> 0 | K39: ='REALIZADO 2025'!K40*'PREVISTO 2026'!$S$27 -> 0 | ... O39: ='REALIZADO 2025'!O40*'PREVISTO 2026'!$S$27 -> 0 | P39: =SUM(D39:O39) -> 68382.052 | Q39: =P39/12 -> 5698.5043
A40: 2.1.6 Taxa De Lixo | D40: ='REALIZADO 2025'!D41*'PREVISTO 2026'!$S$27 -> 0 | E40: ='REALIZADO 2025'!E41*'PREVISTO 2026'!$S$27 -> 0 | F40: ='REALIZADO 2025'!F41*'PREVISTO 2026'!$S$27 -> 5540.266 | G40: ='REALIZADO 2025'!G41*'PREVISTO 2026'!$S$27 -> 0 | H40: ='REALIZADO 2025'!H41*'PREVISTO 2026'!$S$27 -> 0 | I40: ='REALIZADO 2025'!I41*'PREVISTO 2026'!$S$27 -> 0 | J40: ='REALIZADO 2025'!J41*'PREVISTO 2026'!$S$27 -> 0 | K40: ='REALIZADO 2025'!K41*'PREVISTO 2026'!$S$27 -> 0 | ... O40: ='REALIZADO 2025'!O41*'PREVISTO 2026'!$S$27 -> 0 | P40: =SUM(D40:O40) -> 5540.266 | Q40: =P40/12 -> 461.68884
A41: 2.1.60 Outros | D41: ='REALIZADO 2025'!D42*'PREVISTO 2026'!$S$27 -> 0 | E41: ='REALIZADO 2025'!E42*'PREVISTO 2026'!$S$27 -> 0 | F41: ='REALIZADO 2025'!F42*'PREVISTO 2026'!$S$27 -> 0 | G41: ='REALIZADO 2025'!G42*'PREVISTO 2026'!$S$27 -> 0 | H41: ='REALIZADO 2025'!H42*'PREVISTO 2026'!$S$27 -> 731.53135 | I41: ='REALIZADO 2025'!I42*'PREVISTO 2026'!$S$27 -> 0 | J41: ='REALIZADO 2025'!J42*'PREVISTO 2026'!$S$27 -> 0 | K41: ='REALIZADO 2025'!K42*'PREVISTO 2026'!$S$27 -> 0 | ... O41: ='REALIZADO 2025'!O42*'PREVISTO 2026'!$S$27 -> 0 | P41: =SUM(D41:O41) -> 731.53135 | Q41: =P41/12 -> 60.960946
A42: 2.1.7 Seguro | D42: ='REALIZADO 2025'!D43*'PREVISTO 2026'!$S$27 -> 0 | E42: ='REALIZADO 2025'!E43*'PREVISTO 2026'!$S$27 -> 0 | F42: ='REALIZADO 2025'!F43*'PREVISTO 2026'!$S$27 -> 0 | G42: ='REALIZADO 2025'!G43*'PREVISTO 2026'!$S$27 -> 0 | H42: ='REALIZADO 2025'!H43*'PREVISTO 2026'!$S$27 -> 0 | I42: ='REALIZADO 2025'!I43*'PREVISTO 2026'!$S$27 -> 1386.6418 | J42: ='REALIZADO 2025'!J43*'PREVISTO 2026'!$S$27 -> 1386.6418 | K42: ='REALIZADO 2025'!K43*'PREVISTO 2026'!$S$27 -> 1386.6418 | ... O42: ='REALIZADO 2025'!O43*'PREVISTO 2026'!$S$27 -> 0 | P42: =SUM(D42:O42) -> 8319.9556 | Q42: =P42/12 -> 693.32963
A43: 2.1.8 Cartório | D43: ='REALIZADO 2025'!D44*'PREVISTO 2026'!$S$27 -> 252.50335 | E43: ='REALIZADO 2025'!E44*'PREVISTO 2026'!$S$27 -> 62.073 | F43: ='REALIZADO 2025'!F44*'PREVISTO 2026'!$S$27 -> 281.2722 | G43: ='REALIZADO 2025'!G44*'PREVISTO 2026'!$S$27 -> 124.146 | H43: ='REALIZADO 2025'!H44*'PREVISTO 2026'!$S$27 -> 0 | I43: ='REALIZADO 2025'!I44*'PREVISTO 2026'!$S$27 -> 802.4346 | J43: ='REALIZADO 2025'!J44*'PREVISTO 2026'!$S$27 -> 754.37505 | K43: ='REALIZADO 2025'!K44*'PREVISTO 2026'!$S$27 -> 274.3752 | ... O43: ='REALIZADO 2025'!O44*'PREVISTO 2026'!$S$27 -> 0 | P43: =SUM(D43:O43) -> 2818.6576 | Q43: =P43/12 -> 234.88813
A44: 2.1.9 Documentação Veículo / Multas e Infrações | D44: ='REALIZADO 2025'!D45*'PREVISTO 2026'!$S$27 -> 0 | E44: ='REALIZADO 2025'!E45*'PREVISTO 2026'!$S$27 -> 0 | F44: ='REALIZADO 2025'!F45*'PREVISTO 2026'!$S$27 -> 0 | G44: ='REALIZADO 2025'!G45*'PREVISTO 2026'!$S$27 -> 0 | H44: ='REALIZADO 2025'!H45*'PREVISTO 2026'!$S$27 -> 0 | I44: ='REALIZADO 2025'!I45*'PREVISTO 2026'!$S$27 -> 0 | J44: ='REALIZADO 2025'!J45*'PREVISTO 2026'!$S$27 -> 0 | K44: ='REALIZADO 2025'!K45*'PREVISTO 2026'!$S$27 -> 0 | ... O44: ='REALIZADO 2025'!O45*'PREVISTO 2026'!$S$27 -> 0 | P44: =SUM(D44:O44) -> 3262.6258 | Q44: =P44/12 -> 271.88549
A45: 2.2 Colaboradores | D45: =SUM(D46:D60) -> 154479.97 | E45: =SUM(E46:E60) -> 112015.2 | F45: =SUM(F46:F60) -> 94533.512 | G45: =SUM(G46:G60) -> 129753.64 | H45: =SUM(H46:H60) -> 99742.99 | I45: =SUM(I46:I60) -> 125942.13 | J45: =SUM(J46:J60) -> 124648.07 | K45: =SUM(K46:K60) -> 100689.33 | ... P45: =SUM(P46:P60) -> 1483394.4 | Q45: =P45/12 -> 123616.2 | R45: REAJUSTE | S45: 1.08 | T45: 0.08
A46: 2.2.1 Salários Líquidos | D46: ='REALIZADO 2025'!D47*'PREVISTO 2026'!$S$45 -> 52560.36 | E46: ='REALIZADO 2025'!E47*'PREVISTO 2026'!$S$45 -> 50335.56 | F46: ='REALIZADO 2025'!F47*'PREVISTO 2026'!$S$45 -> 47781.36 | G46: ='REALIZADO 2025'!G47*'PREVISTO 2026'!$S$45 -> 51606.72 | H46: ='REALIZADO 2025'!H47*'PREVISTO 2026'!$S$45 -> 47565.36 | I46: ='REALIZADO 2025'!I47*'PREVISTO 2026'!$S$45 -> 51570.432 | J46: ='REALIZADO 2025'!J47*'PREVISTO 2026'!$S$45 -> 52953.48 | K46: ='REALIZADO 2025'!K47*'PREVISTO 2026'!$S$45 -> 47341.8 | ... O46: ='REALIZADO 2025'!O47*'PREVISTO 2026'!$S$45 -> 57690.36 | P46: =SUM(D46:O46) -> 616611.1 | Q46: =P46/12 -> 51384.258
A47: 2.2.10 Benefícios Saúde-cesta Básica-copa | D47: ='REALIZADO 2025'!D48*'PREVISTO 2026'!$S$45 -> 23252.497 | E47: ='REALIZADO 2025'!E48*'PREVISTO 2026'!$S$45 -> 15102.04 | F47: ='REALIZADO 2025'!F48*'PREVISTO 2026'!$S$45 -> 6936.1164 | G47: ='REALIZADO 2025'!G48*'PREVISTO 2026'!$S$45 -> 23643.932 | H47: ='REALIZADO 2025'!H48*'PREVISTO 2026'!$S$45 -> 16979.242 | I47: ='REALIZADO 2025'!I48*'PREVISTO 2026'!$S$45 -> 21597.602 | J47: ='REALIZADO 2025'!J48*'PREVISTO 2026'!$S$45 -> 16055.701 | K47: ='REALIZADO 2025'!K48*'PREVISTO 2026'!$S$45 -> 17160.498 | ... O47: ='REALIZADO 2025'!O48*'PREVISTO 2026'!$S$45 -> 17840.444 | P47: =SUM(D47:O47) -> 210724.09 | Q47: =P47/12 -> 17560.341 | U47: =113000/12 -> 9416.6667
A48: 2.2.11 Uniforme-epi | D48: ='REALIZADO 2025'!D49*'PREVISTO 2026'!$S$45 -> 77.652 | E48: ='REALIZADO 2025'!E49*'PREVISTO 2026'!$S$45 -> 847.4112 | F48: ='REALIZADO 2025'!F49*'PREVISTO 2026'!$S$45 -> 342.9108 | G48: ='REALIZADO 2025'!G49*'PREVISTO 2026'!$S$45 -> 528.444 | H48: ='REALIZADO 2025'!H49*'PREVISTO 2026'!$S$45 -> 1798.74 | I48: ='REALIZADO 2025'!I49*'PREVISTO 2026'!$S$45 -> 1893.78 | J48: ='REALIZADO 2025'!J49*'PREVISTO 2026'!$S$45 -> 539.784 | K48: ='REALIZADO 2025'!K49*'PREVISTO 2026'!$S$45 -> 0 | ... O48: ='REALIZADO 2025'!O49*'PREVISTO 2026'!$S$45 -> 1808.298 | P48: 12000 | Q48: =P48/12 -> 1000
A49: 2.2.12 Laudos Médicos-exames | D49: ='REALIZADO 2025'!D50*'PREVISTO 2026'!$S$45 -> 266.1444 | E49: ='REALIZADO 2025'!E50*'PREVISTO 2026'!$S$45 -> 263.25 | F49: ='REALIZADO 2025'!F50*'PREVISTO 2026'!$S$45 -> 291.5676 | G49: ='REALIZADO 2025'!G50*'PREVISTO 2026'!$S$45 -> 278.7804 | H49: ='REALIZADO 2025'!H50*'PREVISTO 2026'!$S$45 -> 235.6236 | I49: ='REALIZADO 2025'!I50*'PREVISTO 2026'!$S$45 -> 247.7088 | J49: ='REALIZADO 2025'!J50*'PREVISTO 2026'!$S$45 -> 248.4 | K49: ='REALIZADO 2025'!K50*'PREVISTO 2026'!$S$45 -> 248.4 | ... O49: ='REALIZADO 2025'!O50*'PREVISTO 2026'!$S$45 -> 308.6208 | P49: =SUM(D49:O49) -> 3452.004 | Q49: =P49/12 -> 287.667
A50: 2.2.13 Cursos-treinamentos | D50: ='REALIZADO 2025'!D51*'PREVISTO 2026'!$S$45 -> 0 | E50: ='REALIZADO 2025'!E51*'PREVISTO 2026'!$S$45 -> 0 | F50: ='REALIZADO 2025'!F51*'PREVISTO 2026'!$S$45 -> 0 | G50: ='REALIZADO 2025'!G51*'PREVISTO 2026'!$S$45 -> 0 | H50: ='REALIZADO 2025'!H51*'PREVISTO 2026'!$S$45 -> 0 | I50: ='REALIZADO 2025'!I51*'PREVISTO 2026'!$S$45 -> 0 | J50: ='REALIZADO 2025'!J51*'PREVISTO 2026'!$S$45 -> 0 | K50: ='REALIZADO 2025'!K51*'PREVISTO 2026'!$S$45 -> 0 | ... O50: ='REALIZADO 2025'!O51*'PREVISTO 2026'!$S$45 -> 51.0624 | P50: =SUM(D50:O50) -> 2204.2584 | Q50: =P50/12 -> 183.6882
A51: 2.2.14 Brindes-confraternizações | D51: ='REALIZADO 2025'!D52*'PREVISTO 2026'!$S$45 -> 3033.612 | E51: ='REALIZADO 2025'!E52*'PREVISTO 2026'!$S$45 -> 3616.272 | F51: ='REALIZADO 2025'!F52*'PREVISTO 2026'!$S$45 -> 1596.888 | G51: ='REALIZADO 2025'!G52*'PREVISTO 2026'!$S$45 -> 788.4 | H51: ='REALIZADO 2025'!H52*'PREVISTO 2026'!$S$45 -> 0 | I51: ='REALIZADO 2025'!I52*'PREVISTO 2026'!$S$45 -> 1690.0596 | J51: ='REALIZADO 2025'!J52*'PREVISTO 2026'!$S$45 -> 0 | K51: ='REALIZADO 2025'!K52*'PREVISTO 2026'!$S$45 -> 0 | ... O51: ='REALIZADO 2025'!O52*'PREVISTO 2026'!$S$45 -> 0 | P51: =SUM(D51:O51) -> 11296.422 | Q51: =P51/12 -> 941.3685
A52: 2.2.15 Seguro De Vida | D52: ='REALIZADO 2025'!D53*'PREVISTO 2026'!$S$45 -> 319.5936 | E52: ='REALIZADO 2025'!E53*'PREVISTO 2026'!$S$45 -> 319.5936 | F52: ='REALIZADO 2025'!F53*'PREVISTO 2026'!$S$45 -> 319.5936 | G52: ='REALIZADO 2025'!G53*'PREVISTO 2026'!$S$45 -> 319.5936 | H52: ='REALIZADO 2025'!H53*'PREVISTO 2026'!$S$45 -> 332.802 | I52: ='REALIZADO 2025'!I53*'PREVISTO 2026'!$S$45 -> 332.802 | J52: ='REALIZADO 2025'!J53*'PREVISTO 2026'!$S$45 -> 332.802 | K52: ='REALIZADO 2025'!K53*'PREVISTO 2026'!$S$45 -> 332.802 | ... O52: ='REALIZADO 2025'!O53*'PREVISTO 2026'!$S$45 -> 534.5352 | P52: =SUM(D52:O52) -> 4344.2568 | Q52: =P52/12 -> 362.0214
A53: 2.2.16 Contribuição Sindical Empregados | D53: ='REALIZADO 2025'!D54*'PREVISTO 2026'!$S$45 -> 324 | E53: ='REALIZADO 2025'!E54*'PREVISTO 2026'!$S$45 -> 324 | F53: ='REALIZADO 2025'!F54*'PREVISTO 2026'!$S$45 -> 367.2 | G53: ='REALIZADO 2025'!G54*'PREVISTO 2026'!$S$45 -> 345.6 | H53: ='REALIZADO 2025'!H54*'PREVISTO 2026'!$S$45 -> 345.6 | I53: ='REALIZADO 2025'!I54*'PREVISTO 2026'!$S$45 -> 324 | J53: ='REALIZADO 2025'!J54*'PREVISTO 2026'!$S$45 -> 302.4 | K53: ='REALIZADO 2025'!K54*'PREVISTO 2026'!$S$45 -> 324 | ... O53: ='REALIZADO 2025'!O54*'PREVISTO 2026'!$S$45 -> 0 | P53: =SUM(D53:O53) -> 3304.8 | Q53: =P53/12 -> 275.4
A54: 2.2.17 Contribuição Sindical Patronal | D54: ='REALIZADO 2025'!D55*'PREVISTO 2026'!$S$45 -> 0 | E54: ='REALIZADO 2025'!E55*'PREVISTO 2026'!$S$45 -> 0 | F54: ='REALIZADO 2025'!F55*'PREVISTO 2026'!$S$45 -> 0 | G54: ='REALIZADO 2025'!G55*'PREVISTO 2026'!$S$45 -> 0 | H54: ='REALIZADO 2025'!H55*'PREVISTO 2026'!$S$45 -> 0 | I54: ='REALIZADO 2025'!I55*'PREVISTO 2026'!$S$45 -> 0 | J54: ='REALIZADO 2025'!J55*'PREVISTO 2026'!$S$45 -> 0 | K54: ='REALIZADO 2025'!K55*'PREVISTO 2026'!$S$45 -> 0 | ... O54: ='REALIZADO 2025'!O55*'PREVISTO 2026'!$S$45 -> 367.2 | P54: =SUM(D54:O54) -> 712.8 | Q54: =P54/12 -> 59.4
A55: 2.2.20 Tributos Dctf-web | D55: ='REALIZADO 2025'!D57*'PREVISTO 2026'!$S$45 -> 26005.406 | E55: ='REALIZADO 2025'!E57*'PREVISTO 2026'!$S$45 -> 25600.212 | F55: ='REALIZADO 2025'!F57*'PREVISTO 2026'!$S$45 -> 24219.011 | G55: ='REALIZADO 2025'!G57*'PREVISTO 2026'!$S$45 -> 24259.932 | H55: ='REALIZADO 2025'!H57*'PREVISTO 2026'!$S$45 -> 26176.943 | I55: ='REALIZADO 2025'!I57*'PREVISTO 2026'!$S$45 -> 27497.815 | J55: ='REALIZADO 2025'!J57*'PREVISTO 2026'!$S$45 -> 29137.298 | K55: ='REALIZADO 2025'!K57*'PREVISTO 2026'!$S$45 -> 28422.446 | ... O55: ='REALIZADO 2025'!O57*'PREVISTO 2026'!$S$45 -> 29389.878 | P55: =SUM(D55:O55) -> 321580.7 | Q55: =P55/12 -> 26798.392
A56: 2.2.3 Fgts | D56: ='REALIZADO 2025'!D58*'PREVISTO 2026'!$S$45 -> 5940.0108 | E56: ='REALIZADO 2025'!E58*'PREVISTO 2026'!$S$45 -> 6738.3576 | F56: ='REALIZADO 2025'!F58*'PREVISTO 2026'!$S$45 -> 4368.816 | G56: ='REALIZADO 2025'!G58*'PREVISTO 2026'!$S$45 -> 4458.0024 | H56: ='REALIZADO 2025'!H58*'PREVISTO 2026'!$S$45 -> 4821.5196 | I56: ='REALIZADO 2025'!I58*'PREVISTO 2026'!$S$45 -> 4989.3084 | J56: ='REALIZADO 2025'!J58*'PREVISTO 2026'!$S$45 -> 5267.2032 | K56: ='REALIZADO 2025'!K58*'PREVISTO 2026'!$S$45 -> 5605.5024 | ... O56: ='REALIZADO 2025'!O58*'PREVISTO 2026'!$S$45 -> 6208.488 | P56: =SUM(D56:O56) -> 65711.941 | Q56: =P56/12 -> 5475.9951
A57: 2.2.6 Férias | D57: ='REALIZADO 2025'!D59*'PREVISTO 2026'!$S$45 -> 0 | E57: ='REALIZADO 2025'!E59*'PREVISTO 2026'!$S$45 -> 0 | F57: ='REALIZADO 2025'!F59*'PREVISTO 2026'!$S$45 -> 6453.5292 | G57: ='REALIZADO 2025'!G59*'PREVISTO 2026'!$S$45 -> 9554.8356 | H57: ='REALIZADO 2025'!H59*'PREVISTO 2026'!$S$45 -> 0 | I57: ='REALIZADO 2025'!I59*'PREVISTO 2026'!$S$45 -> 14145.57 | J57: ='REALIZADO 2025'!J59*'PREVISTO 2026'!$S$45 -> 18469.642 | K57: ='REALIZADO 2025'!K59*'PREVISTO 2026'!$S$45 -> 0 | ... O57: ='REALIZADO 2025'!O59*'PREVISTO 2026'!$S$45 -> 0 | P57: =SUM(D57:O57) -> 57366.209 | Q57: =P57/12 -> 4780.5174
A58: 2.2.7 13 Salário | D58: ='REALIZADO 2025'!D60*'PREVISTO 2026'!$S$45 -> 41884.214 | E58: ='REALIZADO 2025'!E60*'PREVISTO 2026'!$S$45 -> 0 | F58: ='REALIZADO 2025'!F60*'PREVISTO 2026'!$S$45 -> 0 | G58: ='REALIZADO 2025'!G60*'PREVISTO 2026'!$S$45 -> 0 | H58: ='REALIZADO 2025'!H60*'PREVISTO 2026'!$S$45 -> 0 | I58: ='REALIZADO 2025'!I60*'PREVISTO 2026'!$S$45 -> 0 | J58: ='REALIZADO 2025'!J60*'PREVISTO 2026'!$S$45 -> 0 | K58: ='REALIZADO 2025'!K60*'PREVISTO 2026'!$S$45 -> 0 | ... O58: ='REALIZADO 2025'!O60*'PREVISTO 2026'!$S$45 -> 20089.08 | P58: =SUM(D58:O58) -> 71808.854 | Q58: =P58/12 -> 5984.0712
A59: 2.2.8 Rescisões | D59: ='REALIZADO 2025'!D61*'PREVISTO 2026'!$S$45 -> 0 | E59: ='REALIZADO 2025'!E61*'PREVISTO 2026'!$S$45 -> 7352.1864 | F59: ='REALIZADO 2025'!F61*'PREVISTO 2026'!$S$45 -> 0 | G59: ='REALIZADO 2025'!G61*'PREVISTO 2026'!$S$45 -> 13862.48 | H59: ='REALIZADO 2025'!H61*'PREVISTO 2026'!$S$45 -> 0 | I59: ='REALIZADO 2025'!I61*'PREVISTO 2026'!$S$45 -> 0 | J59: ='REALIZADO 2025'!J61*'PREVISTO 2026'!$S$45 -> 0 | K59: ='REALIZADO 2025'!K61*'PREVISTO 2026'!$S$45 -> 0 | ... O59: ='REALIZADO 2025'!O61*'PREVISTO 2026'!$S$45 -> 1015.2 | P59: 90000 | Q59: =P59/12 -> 7500
A60: 2.2.9 Vale Transporte | D60: ='REALIZADO 2025'!D62*'PREVISTO 2026'!$S$45 -> 816.48 | E60: ='REALIZADO 2025'!E62*'PREVISTO 2026'!$S$45 -> 1516.32 | F60: ='REALIZADO 2025'!F62*'PREVISTO 2026'!$S$45 -> 1856.52 | G60: ='REALIZADO 2025'!G62*'PREVISTO 2026'!$S$45 -> 106.92 | H60: ='REALIZADO 2025'!H62*'PREVISTO 2026'!$S$45 -> 1487.16 | I60: ='REALIZADO 2025'!I62*'PREVISTO 2026'!$S$45 -> 1653.048 | J60: ='REALIZADO 2025'!J62*'PREVISTO 2026'!$S$45 -> 1341.36 | K60: ='REALIZADO 2025'!K62*'PREVISTO 2026'!$S$45 -> 1253.88 | ... O60: ='REALIZADO 2025'!O62*'PREVISTO 2026'!$S$45 -> 0 | P60: =SUM(D60:O60) -> 12277.008 | Q60: =P60/12 -> 1023.084
A61: 2.3 Manutenção | D61: =D62+D79+D92+D96 -> 49045.706 | E61: =E62+E79+E92+E96 -> 40170.981 | F61: =F62+F79+F92+F96 -> 45046.554 | G61: =G62+G79+G92+G96 -> 58247.704 | H61: =H62+H79+H92+H96 -> 77403.463 | I61: =I62+I79+I92+I96 -> 83620.587 | J61: =J62+J79+J92+J96 -> 58878.498 | K61: =K62+K79+K92+K96 -> 51458.298 | ... P61: =P62+P79+P92+P96 -> 638498.62 | Q61: =P61/12 -> 53208.219 | R61: REAJUSTE | S61: 1.045 | T61: 0.045
A62: 2.3.1 Areas De Lazer | D62: =SUM(D63:D72) -> 11923.419 | E62: =SUM(E63:E72) -> 6239.162 | F62: =SUM(F63:F72) -> 4612.3374 | G62: =SUM(G63:G72) -> 14655.226 | H62: =SUM(H63:H72) -> 55507.871 | I62: =SUM(I63:I72) -> 60966.429 | J62: =SUM(J63:J72) -> 33802.625 | K62: =SUM(K63:K72) -> 22886.378 | ... O62: =SUM(O63:O72) -> 25496.067 | P62: =SUM(P63:P78) -> 332522.31 | Q62: =P62/12 -> 27710.192
A63: 2.3.1.1 Salão De Festas Bosque | D63: ='REALIZADO 2025'!D65*'PREVISTO 2026'!$S$61 -> 1550.686 | E63: ='REALIZADO 2025'!E65*'PREVISTO 2026'!$S$61 -> 470.25 | F63: ='REALIZADO 2025'!F65*'PREVISTO 2026'!$S$61 -> 1302.07 | G63: ='REALIZADO 2025'!G65*'PREVISTO 2026'!$S$61 -> 767.64655 | H63: ='REALIZADO 2025'!H65*'PREVISTO 2026'!$S$61 -> 8109.0955 | I63: ='REALIZADO 2025'!I65*'PREVISTO 2026'!$S$61 -> 9680.88 | J63: ='REALIZADO 2025'!J65*'PREVISTO 2026'!$S$61 -> 1657.37 | K63: ='REALIZADO 2025'!K65*'PREVISTO 2026'!$S$61 -> 5182.4685 | ... O63: ='REALIZADO 2025'!O65*'PREVISTO 2026'!$S$61 -> 1478.9467 | P63: 63600 | Q63: =P63/12 -> 5300 | T63: =207000*1.045 -> 216315 | V63: 20000
A64: 2.3.1.10 Quadras-campo | D64: ='REALIZADO 2025'!D66*'PREVISTO 2026'!$S$61 -> 150.42775 | E64: ='REALIZADO 2025'!E66*'PREVISTO 2026'!$S$61 -> 0 | F64: ='REALIZADO 2025'!F66*'PREVISTO 2026'!$S$61 -> 0 | G64: ='REALIZADO 2025'!G66*'PREVISTO 2026'!$S$61 -> 9454.9928 | H64: ='REALIZADO 2025'!H66*'PREVISTO 2026'!$S$61 -> 167.7225 | I64: ='REALIZADO 2025'!I66*'PREVISTO 2026'!$S$61 -> 8494.1571 | J64: ='REALIZADO 2025'!J66*'PREVISTO 2026'!$S$61 -> 1110.1244 | K64: ='REALIZADO 2025'!K66*'PREVISTO 2026'!$S$61 -> 6220.9999 | ... O64: ='REALIZADO 2025'!O66*'PREVISTO 2026'!$S$61 -> 609.95605 | Q64: =P64/12 -> 0 | T64: =112000*1.045 -> 117040 | V64: 20000
A65: 2.3.1.12 Churrasqueira Costela Fogo De Chão | D65: ='REALIZADO 2025'!D67*'PREVISTO 2026'!$S$61 -> 0 | E65: ='REALIZADO 2025'!E67*'PREVISTO 2026'!$S$61 -> 0 | F65: ='REALIZADO 2025'!F67*'PREVISTO 2026'!$S$61 -> 0 | G65: ='REALIZADO 2025'!G67*'PREVISTO 2026'!$S$61 -> 0 | H65: ='REALIZADO 2025'!H67*'PREVISTO 2026'!$S$61 -> 0 | I65: ='REALIZADO 2025'!I67*'PREVISTO 2026'!$S$61 -> 468.996 | J65: ='REALIZADO 2025'!J67*'PREVISTO 2026'!$S$61 -> 0 | K65: ='REALIZADO 2025'!K67*'PREVISTO 2026'!$S$61 -> 0 | ... O65: ='REALIZADO 2025'!O67*'PREVISTO 2026'!$S$61 -> 1730.1229 | P65: =SUM(D65:O65) -> 2199.1189 | Q65: =P65/12 -> 183.25991 | T65: =T63+T64 -> 333355 | V65: 2199.1189
A66: 2.3.1.2 Salão De Festas Piscina | D66: ='REALIZADO 2025'!D68*'PREVISTO 2026'!$S$61 -> 3193.8857 | E66: ='REALIZADO 2025'!E68*'PREVISTO 2026'!$S$61 -> 491.15 | F66: ='REALIZADO 2025'!F68*'PREVISTO 2026'!$S$61 -> 778.525 | G66: ='REALIZADO 2025'!G68*'PREVISTO 2026'!$S$61 -> 1744.0527 | H66: ='REALIZADO 2025'!H68*'PREVISTO 2026'!$S$61 -> 39798.062 | I66: ='REALIZADO 2025'!I68*'PREVISTO 2026'!$S$61 -> 33495.207 | J66: ='REALIZADO 2025'!J68*'PREVISTO 2026'!$S$61 -> 22087.862 | K66: ='REALIZADO 2025'!K68*'PREVISTO 2026'!$S$61 -> 5523.6296 | ... O66: ='REALIZADO 2025'!O68*'PREVISTO 2026'!$S$61 -> 8769.3787 | P66: 24000 | Q66: =P66/12 -> 2000 | T66: =T65-P62 -> 832.69195 | V66: 25000
A67: 2.3.1.3 Salão De Festas Pub | D67: ='REALIZADO 2025'!D69*'PREVISTO 2026'!$S$61 -> 610.8025 | E67: ='REALIZADO 2025'!E69*'PREVISTO 2026'!$S$61 -> 485.03675 | F67: ='REALIZADO 2025'!F69*'PREVISTO 2026'!$S$61 -> 192.4263 | G67: ='REALIZADO 2025'!G69*'PREVISTO 2026'!$S$61 -> 62.7 | H67: ='REALIZADO 2025'!H69*'PREVISTO 2026'!$S$61 -> 3135 | I67: ='REALIZADO 2025'!I69*'PREVISTO 2026'!$S$61 -> 5643 | J67: ='REALIZADO 2025'!J69*'PREVISTO 2026'!$S$61 -> 0 | K67: ='REALIZADO 2025'!K69*'PREVISTO 2026'!$S$61 -> 401.22775 | ... O67: ='REALIZADO 2025'!O69*'PREVISTO 2026'!$S$61 -> 6967.1195 | P67: 16000 | Q67: =P67/12 -> 1333.3333 | V67: 15000
A68: 2.3.1.4 Quiosque | D68: ='REALIZADO 2025'!D70*'PREVISTO 2026'!$S$61 -> 554.5188 | E68: ='REALIZADO 2025'!E70*'PREVISTO 2026'!$S$61 -> 0 | F68: ='REALIZADO 2025'!F70*'PREVISTO 2026'!$S$61 -> 0 | G68: ='REALIZADO 2025'!G70*'PREVISTO 2026'!$S$61 -> 0 | H68: ='REALIZADO 2025'!H70*'PREVISTO 2026'!$S$61 -> 0 | I68: ='REALIZADO 2025'!I70*'PREVISTO 2026'!$S$61 -> 0 | J68: ='REALIZADO 2025'!J70*'PREVISTO 2026'!$S$61 -> 0 | K68: ='REALIZADO 2025'!K70*'PREVISTO 2026'!$S$61 -> 0 | ... O68: ='REALIZADO 2025'!O70*'PREVISTO 2026'!$S$61 -> 271.7 | P68: =SUM(D68:O68) -> 5771.5977 | Q68: =P68/12 -> 480.96648 | V68: 5771.5977
A69: 2.3.1.5 Espaço Juvenil | D69: ='REALIZADO 2025'!D71*'PREVISTO 2026'!$S$61 -> 0 | E69: ='REALIZADO 2025'!E71*'PREVISTO 2026'!$S$61 -> 0 | F69: ='REALIZADO 2025'!F71*'PREVISTO 2026'!$S$61 -> 0 | G69: ='REALIZADO 2025'!G71*'PREVISTO 2026'!$S$61 -> 0 | H69: ='REALIZADO 2025'!H71*'PREVISTO 2026'!$S$61 -> 0 | I69: ='REALIZADO 2025'!I71*'PREVISTO 2026'!$S$61 -> 0 | J69: ='REALIZADO 2025'!J71*'PREVISTO 2026'!$S$61 -> 1440.01 | K69: ='REALIZADO 2025'!K71*'PREVISTO 2026'!$S$61 -> 543.4 | ... O69: ='REALIZADO 2025'!O71*'PREVISTO 2026'!$S$61 -> 683.3464 | P69: =SUM(D69:O69) -> 12602.575 | Q69: =P69/12 -> 1050.2145 | V69: 12602.575
A70: 2.3.1.6 Piscina | D70: ='REALIZADO 2025'!D72*'PREVISTO 2026'!$S$61 -> 5500.8486 | E70: ='REALIZADO 2025'!E72*'PREVISTO 2026'!$S$61 -> 4596.8505 | F70: ='REALIZADO 2025'!F72*'PREVISTO 2026'!$S$61 -> 1380.1106 | G70: ='REALIZADO 2025'!G72*'PREVISTO 2026'!$S$61 -> 1256.4348 | H70: ='REALIZADO 2025'!H72*'PREVISTO 2026'!$S$61 -> 1988.7499 | I70: ='REALIZADO 2025'!I72*'PREVISTO 2026'!$S$61 -> 252.7646 | J70: ='REALIZADO 2025'!J72*'PREVISTO 2026'!$S$61 -> 202.7718 | K70: ='REALIZADO 2025'!K72*'PREVISTO 2026'!$S$61 -> 2318.855 | ... O70: ='REALIZADO 2025'!O72*'PREVISTO 2026'!$S$61 -> 4023.1559 | P70: 20000 | Q70: =P70/12 -> 1666.6667 | V70: 26205.486
A71: 2.3.1.7 Playground - Bosque | D71: ='REALIZADO 2025'!D73*'PREVISTO 2026'!$S$61 -> 349.70925 | E71: ='REALIZADO 2025'!E73*'PREVISTO 2026'!$S$61 -> 60.5055 | F71: ='REALIZADO 2025'!F73*'PREVISTO 2026'!$S$61 -> 60.5055 | G71: ='REALIZADO 2025'!G73*'PREVISTO 2026'!$S$61 -> 60.5055 | H71: ='REALIZADO 2025'!H73*'PREVISTO 2026'!$S$61 -> 60.5055 | I71: ='REALIZADO 2025'!I73*'PREVISTO 2026'!$S$61 -> 530.7555 | J71: ='REALIZADO 2025'!J73*'PREVISTO 2026'!$S$61 -> 3445.156 | K71: ='REALIZADO 2025'!K73*'PREVISTO 2026'!$S$61 -> 257.07 | ... O71: ='REALIZADO 2025'!O73*'PREVISTO 2026'!$S$61 -> 0 | P71: 25000 | Q71: =P71/12 -> 2083.3333 | V71: 15206.328
A72: 2.3.1.8 Academia | D72: ='REALIZADO 2025'!D74*'PREVISTO 2026'!$S$61 -> 12.54 | E72: ='REALIZADO 2025'!E74*'PREVISTO 2026'!$S$61 -> 135.3693 | F72: ='REALIZADO 2025'!F74*'PREVISTO 2026'!$S$61 -> 898.7 | G72: ='REALIZADO 2025'!G74*'PREVISTO 2026'!$S$61 -> 1308.8938 | H72: ='REALIZADO 2025'!H74*'PREVISTO 2026'!$S$61 -> 2248.7355 | I72: ='REALIZADO 2025'!I74*'PREVISTO 2026'!$S$61 -> 2400.668 | J72: ='REALIZADO 2025'!J74*'PREVISTO 2026'!$S$61 -> 3859.3313 | K72: ='REALIZADO 2025'!K74*'PREVISTO 2026'!$S$61 -> 2438.7269 | ... O72: ='REALIZADO 2025'!O74*'PREVISTO 2026'!$S$61 -> 962.3405 | P72: =SUM(D72:O72) -> 17349.017 | Q72: =P72/12 -> 1445.7514 | V72: 17349.017
A73: Quadra Futebol | P73: 10000 | Q73: =P73/12 -> 833.33333 | U73: =P64/3 -> 0
A74: Quadra de tenis | P74: 10000 | Q74: =P74/12 -> 833.33333
A75: Quadra Poliesportiva | P75: 90000 | Q75: =P75/12 -> 7500
A76: Quadra Padle | P76: 3000 | Q76: =P76/12 -> 250
A77: Quadra de areia | P77: 3000 | Q77: =P77/12 -> 250
A78: Playground - Piscina | P78: 30000 | Q78: =P78/12 -> 2500
A79: 2.3.2 Estrutura | D79: =SUM(D80:D91) -> 13069.94 | E79: =SUM(E80:E91) -> 14929.142 | F79: =SUM(F80:F91) -> 19163.168 | G79: =SUM(G80:G91) -> 16750.493 | H79: =SUM(H80:H91) -> 10903.938 | I79: =SUM(I80:I91) -> 10419.653 | J79: =SUM(J80:J91) -> 14561.835 | K79: =SUM(K80:K91) -> 8672.9984 | ... P79: =SUM(P80:P91) -> 149101.29 | Q79: =P79/12 -> 12425.108
A80: 2.3.2.1 Areas e Instalações Comuns | D80: ='REALIZADO 2025'!D76*'PREVISTO 2026'!$S$61 -> 1201.7082 | E80: ='REALIZADO 2025'!E76*'PREVISTO 2026'!$S$61 -> 5668.4353 | F80: ='REALIZADO 2025'!F76*'PREVISTO 2026'!$S$61 -> 1839.4299 | G80: ='REALIZADO 2025'!G76*'PREVISTO 2026'!$S$61 -> 1707.436 | H80: ='REALIZADO 2025'!H76*'PREVISTO 2026'!$S$61 -> 1130.7213 | I80: ='REALIZADO 2025'!I76*'PREVISTO 2026'!$S$61 -> 410.50735 | J80: ='REALIZADO 2025'!J76*'PREVISTO 2026'!$S$61 -> 2901.2753 | K80: ='REALIZADO 2025'!K76*'PREVISTO 2026'!$S$61 -> 1329.752 | ... O80: ='REALIZADO 2025'!O76*'PREVISTO 2026'!$S$61 -> 1431.65 | P80: =SUM(D80:O80) -> 22780.404 | Q80: =P80/12 -> 1898.367
A81: 2.3.2.10 Ruas-meio Fio-lombada-sinalização | D81: ='REALIZADO 2025'!D77*'PREVISTO 2026'!$S$61 -> 0 | E81: ='REALIZADO 2025'!E77*'PREVISTO 2026'!$S$61 -> 2427.5245 | F81: ='REALIZADO 2025'!F77*'PREVISTO 2026'!$S$61 -> 3773.1188 | G81: ='REALIZADO 2025'!G77*'PREVISTO 2026'!$S$61 -> 1885.3785 | H81: ='REALIZADO 2025'!H77*'PREVISTO 2026'!$S$61 -> 1016.2625 | I81: ='REALIZADO 2025'!I77*'PREVISTO 2026'!$S$61 -> 3881.9869 | J81: ='REALIZADO 2025'!J77*'PREVISTO 2026'!$S$61 -> 3093.2 | K81: ='REALIZADO 2025'!K77*'PREVISTO 2026'!$S$61 -> 1703.35 | ... O81: ='REALIZADO 2025'!O77*'PREVISTO 2026'!$S$61 -> 2277.6716 | P81: =SUM(D81:O81) -> 29107.096 | Q81: =P81/12 -> 2425.5913
A82: 2.3.2.12 Pergola | D82: ='REALIZADO 2025'!D78*'PREVISTO 2026'!$S$61 -> 888.25 | E82: ='REALIZADO 2025'!E78*'PREVISTO 2026'!$S$61 -> 548.625 | F82: ='REALIZADO 2025'!F78*'PREVISTO 2026'!$S$61 -> 0 | G82: ='REALIZADO 2025'!G78*'PREVISTO 2026'!$S$61 -> 0 | H82: ='REALIZADO 2025'!H78*'PREVISTO 2026'!$S$61 -> 0 | I82: ='REALIZADO 2025'!I78*'PREVISTO 2026'!$S$61 -> 0 | J82: ='REALIZADO 2025'!J78*'PREVISTO 2026'!$S$61 -> 0 | K82: ='REALIZADO 2025'!K78*'PREVISTO 2026'!$S$61 -> 0 | ... O82: ='REALIZADO 2025'!O78*'PREVISTO 2026'!$S$61 -> 0 | P82: =SUM(D82:O82) -> 1436.875 | Q82: =P82/12 -> 119.73958
A83: 2.3.2.13 Dog Park | D83: ='REALIZADO 2025'!D79*'PREVISTO 2026'!$S$61 -> 0 | E83: ='REALIZADO 2025'!E79*'PREVISTO 2026'!$S$61 -> 0 | F83: ='REALIZADO 2025'!F79*'PREVISTO 2026'!$S$61 -> 0 | G83: ='REALIZADO 2025'!G79*'PREVISTO 2026'!$S$61 -> 0 | H83: ='REALIZADO 2025'!H79*'PREVISTO 2026'!$S$61 -> 0 | I83: ='REALIZADO 2025'!I79*'PREVISTO 2026'!$S$61 -> 0 | J83: ='REALIZADO 2025'!J79*'PREVISTO 2026'!$S$61 -> 0 | K83: ='REALIZADO 2025'!K79*'PREVISTO 2026'!$S$61 -> 0 | ... O83: ='REALIZADO 2025'!O79*'PREVISTO 2026'!$S$61 -> 0 | P83: =SUM(D83:O83) -> 42.5733 | Q83: =P83/12 -> 3.547775
A84: 2.3.2.2 Elétrica- Iluminação | D84: ='REALIZADO 2025'!D80*'PREVISTO 2026'!$S$61 -> 2080.5114 | E84: ='REALIZADO 2025'!E80*'PREVISTO 2026'!$S$61 -> 1775.5804 | F84: ='REALIZADO 2025'!F80*'PREVISTO 2026'!$S$61 -> 2668.5329 | G84: ='REALIZADO 2025'!G80*'PREVISTO 2026'!$S$61 -> 5443.0915 | H84: ='REALIZADO 2025'!H80*'PREVISTO 2026'!$S$61 -> 3762.7419 | I84: ='REALIZADO 2025'!I80*'PREVISTO 2026'!$S$61 -> 3642.0862 | J84: ='REALIZADO 2025'!J80*'PREVISTO 2026'!$S$61 -> 372.7933 | K84: ='REALIZADO 2025'!K80*'PREVISTO 2026'!$S$61 -> 968.1925 | ... O84: ='REALIZADO 2025'!O80*'PREVISTO 2026'!$S$61 -> 4547.422 | P84: 10000 | Q84: =P84/12 -> 833.33333
A85: 2.3.2.3 Instalações Hidráulicas- Esgoto | D85: ='REALIZADO 2025'!D81*'PREVISTO 2026'!$S$61 -> 0 | E85: ='REALIZADO 2025'!E81*'PREVISTO 2026'!$S$61 -> 0 | F85: ='REALIZADO 2025'!F81*'PREVISTO 2026'!$S$61 -> 0 | G85: ='REALIZADO 2025'!G81*'PREVISTO 2026'!$S$61 -> 104.5 | H85: ='REALIZADO 2025'!H81*'PREVISTO 2026'!$S$61 -> 0 | I85: ='REALIZADO 2025'!I81*'PREVISTO 2026'!$S$61 -> 0 | J85: ='REALIZADO 2025'!J81*'PREVISTO 2026'!$S$61 -> 0 | K85: ='REALIZADO 2025'!K81*'PREVISTO 2026'!$S$61 -> 0 | ... O85: ='REALIZADO 2025'!O81*'PREVISTO 2026'!$S$61 -> 56.7644 | P85: =SUM(D85:O85) -> 161.2644 | Q85: =P85/12 -> 13.4387
A86: 2.3.2.4 Jardim | D86: ='REALIZADO 2025'!D82*'PREVISTO 2026'!$S$61 -> 7691.6598 | E86: ='REALIZADO 2025'!E82*'PREVISTO 2026'!$S$61 -> 2713.0812 | F86: ='REALIZADO 2025'!F82*'PREVISTO 2026'!$S$61 -> 1018.875 | G86: ='REALIZADO 2025'!G82*'PREVISTO 2026'!$S$61 -> 2666.84 | H86: ='REALIZADO 2025'!H82*'PREVISTO 2026'!$S$61 -> 2783.88 | I86: ='REALIZADO 2025'!I82*'PREVISTO 2026'!$S$61 -> 836 | J86: ='REALIZADO 2025'!J82*'PREVISTO 2026'!$S$61 -> 877.8 | K86: ='REALIZADO 2025'!K82*'PREVISTO 2026'!$S$61 -> 1648.4875 | ... O86: ='REALIZADO 2025'!O82*'PREVISTO 2026'!$S$61 -> 2016.1812 | P86: =SUM(D86:O86) -> 27564.09 | Q86: =P86/12 -> 2297.0075
A87: 2.3.2.5 Portaria Social | D87: ='REALIZADO 2025'!D83*'PREVISTO 2026'!$S$61 -> 1149.5 | E87: ='REALIZADO 2025'!E83*'PREVISTO 2026'!$S$61 -> 1481.5592 | F87: ='REALIZADO 2025'!F83*'PREVISTO 2026'!$S$61 -> 2122.2696 | G87: ='REALIZADO 2025'!G83*'PREVISTO 2026'!$S$61 -> 2265.5914 | H87: ='REALIZADO 2025'!H83*'PREVISTO 2026'!$S$61 -> 1493.2945 | I87: ='REALIZADO 2025'!I83*'PREVISTO 2026'!$S$61 -> 1497.5163 | J87: ='REALIZADO 2025'!J83*'PREVISTO 2026'!$S$61 -> 1918.2438 | K87: ='REALIZADO 2025'!K83*'PREVISTO 2026'!$S$61 -> 2009.5663 | ... O87: ='REALIZADO 2025'!O83*'PREVISTO 2026'!$S$61 -> 1762.3507 | P87: 35000 | Q87: =P87/12 -> 2916.6667
A88: 2.3.2.6 Portaria De Serviço | D88: ='REALIZADO 2025'!D84*'PREVISTO 2026'!$S$61 -> 0 | E88: ='REALIZADO 2025'!E84*'PREVISTO 2026'!$S$61 -> 0 | F88: ='REALIZADO 2025'!F84*'PREVISTO 2026'!$S$61 -> 425.942 | G88: ='REALIZADO 2025'!G84*'PREVISTO 2026'!$S$61 -> 250.8 | H88: ='REALIZADO 2025'!H84*'PREVISTO 2026'!$S$61 -> 0 | I88: ='REALIZADO 2025'!I84*'PREVISTO 2026'!$S$61 -> 78.2705 | J88: ='REALIZADO 2025'!J84*'PREVISTO 2026'!$S$61 -> 1254 | K88: ='REALIZADO 2025'!K84*'PREVISTO 2026'!$S$61 -> 731.5 | ... O88: ='REALIZADO 2025'!O84*'PREVISTO 2026'!$S$61 -> 0 | P88: =SUM(D88:O88) -> 2855.4625 | Q88: =P88/12 -> 237.95521
A89: 2.3.2.7 Prédio-sala Administrativo-garagem | D89: ='REALIZADO 2025'!D85*'PREVISTO 2026'!$S$61 -> 58.311 | E89: ='REALIZADO 2025'!E85*'PREVISTO 2026'!$S$61 -> 314.336 | F89: ='REALIZADO 2025'!F85*'PREVISTO 2026'!$S$61 -> 0 | G89: ='REALIZADO 2025'!G85*'PREVISTO 2026'!$S$61 -> 776.80075 | H89: ='REALIZADO 2025'!H85*'PREVISTO 2026'!$S$61 -> 23.20945 | I89: ='REALIZADO 2025'!I85*'PREVISTO 2026'!$S$61 -> 0 | J89: ='REALIZADO 2025'!J85*'PREVISTO 2026'!$S$61 -> 3766.18 | K89: ='REALIZADO 2025'!K85*'PREVISTO 2026'!$S$61 -> 282.15 | ... O89: ='REALIZADO 2025'!O85*'PREVISTO 2026'!$S$61 -> 0 | P89: =SUM(D89:O89) -> 9779.6743 | Q89: =P89/12 -> 814.97286
A90: 2.3.2.8 Poço Artesiano | D90: ='REALIZADO 2025'!D86*'PREVISTO 2026'!$S$61 -> 0 | E90: ='REALIZADO 2025'!E86*'PREVISTO 2026'!$S$61 -> 0 | F90: ='REALIZADO 2025'!F86*'PREVISTO 2026'!$S$61 -> 7315 | G90: ='REALIZADO 2025'!G86*'PREVISTO 2026'!$S$61 -> 1650.055 | H90: ='REALIZADO 2025'!H86*'PREVISTO 2026'!$S$61 -> 0 | I90: ='REALIZADO 2025'!I86*'PREVISTO 2026'!$S$61 -> 0 | J90: ='REALIZADO 2025'!J86*'PREVISTO 2026'!$S$61 -> 0 | K90: ='REALIZADO 2025'!K86*'PREVISTO 2026'!$S$61 -> 0 | ... O90: ='REALIZADO 2025'!O86*'PREVISTO 2026'!$S$61 -> 0 | P90: =SUM(D90:O90) -> 9228.395 | Q90: =P90/12 -> 769.03292
A91: 2.3.2.9 Cerca Muro | D91: ='REALIZADO 2025'!D87*'PREVISTO 2026'!$S$61 -> 0 | E91: ='REALIZADO 2025'!E87*'PREVISTO 2026'!$S$61 -> 0 | F91: ='REALIZADO 2025'!F87*'PREVISTO 2026'!$S$61 -> 0 | G91: ='REALIZADO 2025'!G87*'PREVISTO 2026'!$S$61 -> 0 | H91: ='REALIZADO 2025'!H87*'PREVISTO 2026'!$S$61 -> 693.82775 | I91: ='REALIZADO 2025'!I87*'PREVISTO 2026'!$S$61 -> 73.28585 | J91: ='REALIZADO 2025'!J87*'PREVISTO 2026'!$S$61 -> 378.34225 | K91: ='REALIZADO 2025'!K87*'PREVISTO 2026'!$S$61 -> 0 | ... O91: ='REALIZADO 2025'!O87*'PREVISTO 2026'!$S$61 -> 0 | P91: =SUM(D91:O91) -> 1145.4559 | Q91: =P91/12 -> 95.454654
A92: 2.3.3 Máquinas e Equipamentos | D92: =SUM(D93:D95) -> 16132.187 | E92: =SUM(E93:E95) -> 14734.814 | F92: =SUM(F93:F95) -> 13166.112 | G92: =SUM(G93:G95) -> 15843.767 | H92: =SUM(H93:H95) -> 6390.175 | I92: =SUM(I93:I95) -> 10054.99 | J92: =SUM(J93:J95) -> 7028.67 | K92: =SUM(K93:K95) -> 8206.0401 | ... P92: =SUM(P93:P95) -> 95374.689 | Q92: =P92/12 -> 7947.8907
A93: 2.3.3.1 Sistema De Segurança | D93: ='REALIZADO 2025'!D89*'PREVISTO 2026'!$S$61 -> 6040.6225 | E93: ='REALIZADO 2025'!E89*'PREVISTO 2026'!$S$61 -> 6040.6225 | F93: ='REALIZADO 2025'!F89*'PREVISTO 2026'!$S$61 -> 5339.95 | G93: ='REALIZADO 2025'!G89*'PREVISTO 2026'!$S$61 -> 7947.225 | H93: ='REALIZADO 2025'!H89*'PREVISTO 2026'!$S$61 -> 6390.175 | I93: ='REALIZADO 2025'!I89*'PREVISTO 2026'!$S$61 -> 5956.5 | J93: ='REALIZADO 2025'!J89*'PREVISTO 2026'!$S$61 -> 3423.42 | K93: ='REALIZADO 2025'!K89*'PREVISTO 2026'!$S$61 -> 5016 | ... O93: ='REALIZADO 2025'!O89*'PREVISTO 2026'!$S$61 -> 0 | P93: =SUM(D93:O93) -> 52460.045 | Q93: =P93/12 -> 4371.6704
A94: 2.3.3.2 Aparelhos-máquinas-ferramentas-equipamentos | D94: ='REALIZADO 2025'!D90*'PREVISTO 2026'!$S$61 -> 7357.845 | E94: ='REALIZADO 2025'!E90*'PREVISTO 2026'!$S$61 -> 4558.081 | F94: ='REALIZADO 2025'!F90*'PREVISTO 2026'!$S$61 -> 5275.1077 | G94: ='REALIZADO 2025'!G90*'PREVISTO 2026'!$S$61 -> 7008.2925 | H94: ='REALIZADO 2025'!H90*'PREVISTO 2026'!$S$61 -> 0 | I94: ='REALIZADO 2025'!I90*'PREVISTO 2026'!$S$61 -> 2102.54 | J94: ='REALIZADO 2025'!J90*'PREVISTO 2026'!$S$61 -> 606.1 | K94: ='REALIZADO 2025'!K90*'PREVISTO 2026'!$S$61 -> 1864.9801 | ... O94: ='REALIZADO 2025'!O90*'PREVISTO 2026'!$S$61 -> 1264.3455 | P94: 25000 | Q94: =P94/12 -> 2083.3333
A95: 2.3.3.3 Veículo-moto | D95: ='REALIZADO 2025'!D91*'PREVISTO 2026'!$S$61 -> 2733.72 | E95: ='REALIZADO 2025'!E91*'PREVISTO 2026'!$S$61 -> 4136.11 | F95: ='REALIZADO 2025'!F91*'PREVISTO 2026'!$S$61 -> 2551.054 | G95: ='REALIZADO 2025'!G91*'PREVISTO 2026'!$S$61 -> 888.25 | H95: ='REALIZADO 2025'!H91*'PREVISTO 2026'!$S$61 -> 0 | I95: ='REALIZADO 2025'!I91*'PREVISTO 2026'!$S$61 -> 1995.95 | J95: ='REALIZADO 2025'!J91*'PREVISTO 2026'!$S$61 -> 2999.15 | K95: ='REALIZADO 2025'!K91*'PREVISTO 2026'!$S$61 -> 1325.06 | ... O95: ='REALIZADO 2025'!O91*'PREVISTO 2026'!$S$61 -> 574.75 | P95: =SUM(D95:O95) -> 17914.644 | Q95: =P95/12 -> 1492.887
A96: 2.3.4 Serviços Especializados | D96: =SUM(D97:D101) -> 7920.1595 | E96: =SUM(E97:E101) -> 4267.8636 | F96: =SUM(F97:F101) -> 8104.9364 | G96: =SUM(G97:G101) -> 10998.217 | H96: =SUM(H97:H101) -> 4601.4798 | I96: =SUM(I97:I101) -> 2179.5147 | J96: =SUM(J97:J101) -> 3485.3676 | K96: =SUM(K97:K101) -> 11692.881 | ... P96: =SUM(P97:P101) -> 61500.336 | Q96: =P96/12 -> 5125.028
A97: 2.3.4.1 Extintores | D97: ='REALIZADO 2025'!D93*'PREVISTO 2026'!$S$61 -> 909.15 | E97: ='REALIZADO 2025'!E93*'PREVISTO 2026'!$S$61 -> 0 | F97: ='REALIZADO 2025'!F93*'PREVISTO 2026'!$S$61 -> 0 | G97: ='REALIZADO 2025'!G93*'PREVISTO 2026'!$S$61 -> 0 | H97: ='REALIZADO 2025'!H93*'PREVISTO 2026'!$S$61 -> 0 | I97: ='REALIZADO 2025'!I93*'PREVISTO 2026'!$S$61 -> 0 | J97: ='REALIZADO 2025'!J93*'PREVISTO 2026'!$S$61 -> 0 | K97: ='REALIZADO 2025'!K93*'PREVISTO 2026'!$S$61 -> 0 | ... O97: ='REALIZADO 2025'!O93*'PREVISTO 2026'!$S$61 -> 0 | P97: =SUM(D97:O97) -> 1018.875 | Q97: =P97/12 -> 84.90625
A98: 2.3.4.2 Dedetização-desinsetização-desratização | D98: ='REALIZADO 2025'!D94*'PREVISTO 2026'!$S$61 -> 752.4 | E98: ='REALIZADO 2025'!E94*'PREVISTO 2026'!$S$61 -> 686.1888 | F98: ='REALIZADO 2025'!F94*'PREVISTO 2026'!$S$61 -> 818.6112 | G98: ='REALIZADO 2025'!G94*'PREVISTO 2026'!$S$61 -> 1368.95 | H98: ='REALIZADO 2025'!H94*'PREVISTO 2026'!$S$61 -> 686.1888 | I98: ='REALIZADO 2025'!I94*'PREVISTO 2026'!$S$61 -> 818.6112 | J98: ='REALIZADO 2025'!J94*'PREVISTO 2026'!$S$61 -> 1813.3676 | K98: ='REALIZADO 2025'!K94*'PREVISTO 2026'!$S$61 -> 1575.1912 | ... O98: ='REALIZADO 2025'!O94*'PREVISTO 2026'!$S$61 -> 852.72 | P98: =SUM(D98:O98) -> 12477.3 | Q98: =P98/12 -> 1039.775
A99: 2.3.4.3 Fossa-caixa De Gordura | D99: ='REALIZADO 2025'!D95*'PREVISTO 2026'!$S$61 -> 2403.5 | E99: ='REALIZADO 2025'!E95*'PREVISTO 2026'!$S$61 -> 545.49 | F99: ='REALIZADO 2025'!F95*'PREVISTO 2026'!$S$61 -> 447.26 | G99: ='REALIZADO 2025'!G95*'PREVISTO 2026'!$S$61 -> 900.69595 | H99: ='REALIZADO 2025'!H95*'PREVISTO 2026'!$S$61 -> 469.19455 | I99: ='REALIZADO 2025'!I95*'PREVISTO 2026'!$S$61 -> 0 | J99: ='REALIZADO 2025'!J95*'PREVISTO 2026'!$S$61 -> 418 | K99: ='REALIZADO 2025'!K95*'PREVISTO 2026'!$S$61 -> 921.69 | ... O99: ='REALIZADO 2025'!O95*'PREVISTO 2026'!$S$61 -> 516.82565 | P99: =SUM(D99:O99) -> 8399.9608 | Q99: =P99/12 -> 699.99673
A100: 2.3.4.4 Reservatórios De Água | D100: ='REALIZADO 2025'!D96*'PREVISTO 2026'!$S$61 -> 1472.5095 | E100: ='REALIZADO 2025'!E96*'PREVISTO 2026'!$S$61 -> 528.1848 | F100: ='REALIZADO 2025'!F96*'PREVISTO 2026'!$S$61 -> 5585.0652 | G100: ='REALIZADO 2025'!G96*'PREVISTO 2026'!$S$61 -> 6136.9715 | H100: ='REALIZADO 2025'!H96*'PREVISTO 2026'!$S$61 -> 2192.0965 | I100: ='REALIZADO 2025'!I96*'PREVISTO 2026'!$S$61 -> 106.9035 | J100: ='REALIZADO 2025'!J96*'PREVISTO 2026'!$S$61 -> 0 | K100: ='REALIZADO 2025'!K96*'PREVISTO 2026'!$S$61 -> 7942 | ... O100: ='REALIZADO 2025'!O96*'PREVISTO 2026'!$S$61 -> 428.7635 | P100: 20000 | Q100: =P100/12 -> 1666.6667
A101: 2.3.4.5 Análise De Água | D101: ='REALIZADO 2025'!D97*'PREVISTO 2026'!$S$61 -> 2382.6 | E101: ='REALIZADO 2025'!E97*'PREVISTO 2026'!$S$61 -> 2508 | F101: ='REALIZADO 2025'!F97*'PREVISTO 2026'!$S$61 -> 1254 | G101: ='REALIZADO 2025'!G97*'PREVISTO 2026'!$S$61 -> 2591.6 | H101: ='REALIZADO 2025'!H97*'PREVISTO 2026'!$S$61 -> 1254 | I101: ='REALIZADO 2025'!I97*'PREVISTO 2026'!$S$61 -> 1254 | J101: ='REALIZADO 2025'!J97*'PREVISTO 2026'!$S$61 -> 1254 | K101: ='REALIZADO 2025'!K97*'PREVISTO 2026'!$S$61 -> 1254 | ... O101: ='REALIZADO 2025'!O97*'PREVISTO 2026'!$S$61 -> 1672 | P101: =SUM(D101:O101) -> 19604.2 | Q101: =P101/12 -> 1633.6833
A102: 2.4 Serviços | D102: =SUM(D103:D109) -> 74062.4 | E102: =SUM(E103:E109) -> 69791.715 | F102: =SUM(F103:F109) -> 66502.577 | G102: =SUM(G103:G109) -> 61074.283 | H102: =SUM(H103:H109) -> 83086.623 | I102: =SUM(I103:I109) -> 79588.203 | J102: =SUM(J103:J109) -> 78941.129 | K102: =SUM(K103:K109) -> 79605.331 | ... P102: =SUM(P103:P109) -> 916617.03 | Q102: =P102/12 -> 76384.752 | R102: REAJUSTE | S102: 1.045
A103: 2.4.1 Honorários Advocatícios | D103: ='REALIZADO 2025'!D99*'PREVISTO 2026'!$S$102 -> 4117.3 | E103: ='REALIZADO 2025'!E99*'PREVISTO 2026'!$S$102 -> 2058.65 | F103: ='REALIZADO 2025'!F99*'PREVISTO 2026'!$S$102 -> 0 | G103: ='REALIZADO 2025'!G99*'PREVISTO 2026'!$S$102 -> 0 | H103: ='REALIZADO 2025'!H99*'PREVISTO 2026'!$S$102 -> 6667.1 | I103: ='REALIZADO 2025'!I99*'PREVISTO 2026'!$S$102 -> 2304.225 | J103: ='REALIZADO 2025'!J99*'PREVISTO 2026'!$S$102 -> 2304.225 | K103: ='REALIZADO 2025'!K99*'PREVISTO 2026'!$S$102 -> 2304.225 | ... O103: ='REALIZADO 2025'!O99*'PREVISTO 2026'!$S$102 -> 2304.225 | P103: =SUM(D103:O103) -> 32003.344 | Q103: =P103/12 -> 2666.9454
A104: 2.4.2 Honorários Engenharia | D104: ='REALIZADO 2025'!D100*'PREVISTO 2026'!$S$102 -> 2951.08 | E104: ='REALIZADO 2025'!E100*'PREVISTO 2026'!$S$102 -> 3172.62 | F104: ='REALIZADO 2025'!F100*'PREVISTO 2026'!$S$102 -> 3172.62 | G104: ='REALIZADO 2025'!G100*'PREVISTO 2026'!$S$102 -> 3172.62 | H104: ='REALIZADO 2025'!H100*'PREVISTO 2026'!$S$102 -> 3172.62 | I104: ='REALIZADO 2025'!I100*'PREVISTO 2026'!$S$102 -> 3172.62 | J104: ='REALIZADO 2025'!J100*'PREVISTO 2026'!$S$102 -> 3172.62 | K104: ='REALIZADO 2025'!K100*'PREVISTO 2026'!$S$102 -> 3172.62 | ... O104: ='REALIZADO 2025'!O100*'PREVISTO 2026'!$S$102 -> 3172.62 | P104: =SUM(D104:O104) -> 37849.9 | Q104: =P104/12 -> 3154.1583
A105: 2.4.3 Honorários Contábeis | D105: ='REALIZADO 2025'!D101*'PREVISTO 2026'!$S$102 -> 4270.2671 | E105: ='REALIZADO 2025'!E101*'PREVISTO 2026'!$S$102 -> 3642.0444 | F105: ='REALIZADO 2025'!F101*'PREVISTO 2026'!$S$102 -> 2614.7885 | G105: ='REALIZADO 2025'!G101*'PREVISTO 2026'!$S$102 -> 2692.4738 | H105: ='REALIZADO 2025'!H101*'PREVISTO 2026'!$S$102 -> 2692.4634 | I105: ='REALIZADO 2025'!I101*'PREVISTO 2026'!$S$102 -> 3530.1667 | J105: ='REALIZADO 2025'!J101*'PREVISTO 2026'!$S$102 -> 2792.24 | K105: ='REALIZADO 2025'!K101*'PREVISTO 2026'!$S$102 -> 3253.085 | ... O105: ='REALIZADO 2025'!O101*'PREVISTO 2026'!$S$102 -> 4425.0525 | P105: =SUM(D105:O105) -> 38980.047 | Q105: =P105/12 -> 3248.3372
A106: 2.4.4 Segurança- Serviço Vigilância | D106: ='REALIZADO 2025'!D102*'PREVISTO 2026'!$S$102 -> 58965.41 | E106: ='REALIZADO 2025'!E102*'PREVISTO 2026'!$S$102 -> 58988.808 | F106: ='REALIZADO 2025'!F102*'PREVISTO 2026'!$S$102 -> 58988.808 | G106: ='REALIZADO 2025'!G102*'PREVISTO 2026'!$S$102 -> 54895.689 | H106: ='REALIZADO 2025'!H102*'PREVISTO 2026'!$S$102 -> 69237.739 | I106: ='REALIZADO 2025'!I102*'PREVISTO 2026'!$S$102 -> 68417.164 | J106: ='REALIZADO 2025'!J102*'PREVISTO 2026'!$S$102 -> 64109.026 | K106: ='REALIZADO 2025'!K102*'PREVISTO 2026'!$S$102 -> 64109.026 | ... O106: ='REALIZADO 2025'!O102*'PREVISTO 2026'!$S$102 -> 64109.026 | P106: =SUM(D106:O106) -> 754147.79 | Q106: =P106/12 -> 62845.649
